Workbook
Name Excel_BuiltIn_Print_Area_1: #REF!
Name Excel_BuiltIn_Print_Area_1: #REF!
Name Excel_BuiltIn_Print_Area_1: #REF!
Name Excel_BuiltIn_Print_Area_3: #REF!
Name Excel_BuiltIn_Print_Area_3: #REF!
Name Excel_BuiltIn_Print_Area_3: #REF!

Sheet 12_21
A1: 0 | B1: tm | C1: CodCli | D1: Nome | E1: dtvcto | F1: Valor | G1: tipo | H1: Pagto.
C2: SOCIOS | D2: SEGURO DE VIDA RUBENS c | E2: 44531 | F2: 1020 | G2: Distribuição de Lucros | H2: =VLOOKUP(E2,$E$2783:$H$2814,4,FALSE) -> 44531
C3: EPI | D3: ZAPA | E3: 44531 | F3: 1043.68 | G3: Empresa 2 | H3: =VLOOKUP(E3,$E$2783:$H$2814,4,FALSE) -> 44531
C4: ENERGIA | D4: RGE | E4: 44532 | F4: 1000 | G4: Empresa 1 | H4: =VLOOKUP(E4,$E$2783:$H$2814,4,FALSE) -> 44532
C5: SALARIOS | D5: SALARIOS | E5: 44532 | F5: 6000 | G5: Empresa 1 | H5: =VLOOKUP(E5,$E$2783:$H$2814,4,FALSE) -> 44532
C6: SALARIOS | D6: SALARIOS | E6: 44532 | F6: 90000 | G6: Empresa 2 | H6: =VLOOKUP(E6,$E$2783:$H$2814,4,FALSE) -> 44532
C7: SOCIOS | D7: RETIRADA LUIS b | E7: 44532 | F7: 2500 | G7: Distribuição de Lucros | H7: =VLOOKUP(E7,$E$2783:$H$2814,4,FALSE) -> 44532
C8: SOCIOS | D8: RETIRADA PAULO d | E8: 44532 | F8: 2000 | G8: Distribuição de Lucros | H8: =VLOOKUP(E8,$E$2783:$H$2814,4,FALSE) -> 44532
C9: ACORDO | D9: LEONARDO - CIFERAL - 11/14 | E9: 44533 | F9: 1500 | G9: Empresa 2 | H9: =VLOOKUP(E9,$E$2783:$H$2814,4,FALSE) -> 44533
C10: EPI | D10: JUSTINA | E10: 44533 | F10: 900 | G10: Empresa 2 | H10: =VLOOKUP(E10,$E$2783:$H$2814,4,FALSE) -> 44533
C11: PARCELAMENTO | D11: EMPRESTIMO FOLHA BB - 12/30 | E11: 44533 | F11: 2090.64 | G11: Empresa 2 | H11: =VLOOKUP(E11,$E$2783:$H$2814,4,FALSE) -> 44533
C12: PARCELAMENTO | D12: EMPRESTIMO FOLHA BB - 13/30 | E12: 44534 | F12: 2008.11 | G12: Empresa 2 | H12: =VLOOKUP(E12,$E$2783:$H$2814,4,FALSE) -> 44536
C13: FÉRIAS | D13: CLEBER MELLO - vcto 01/11 - não tem salario | E13: 44535 | F13: 5953 | G13: Empresa 2 | H13: =VLOOKUP(E13,$E$2783:$H$2814,4,FALSE) -> 44536
... C69: PARCELAMENTO | D69: CSLL - DEBITO BB | E69: 44560 | F69: 526.26 | G69: Empresa 2 | H69: =VLOOKUP(E69,$E$2783:$H$2814,4,FALSE) -> 44560
D2782: CALENDÁRIO A AJUSTAR | E2782: VCTO
A2783: RELAÇÃO DAS CONTAS DO FLUXO | D2783: DIAS CORRIDOS > | E2783: 44531 | G2783: A VERIFICAR | H2783: 44531 | I2783: >>Data de Pagto
A2784: (Preenchet até a linha 2.100) | D2784: DIAS CORRIDOS > | E2784: 44532 | G2784: ALUGUEIS DEPÓSITOS PFT/GUGELMIN - MATRIZ | H2784: 44532 | I2784: >>Data de Pagto
D2785: DIAS CORRIDOS > | E2785: 44533 | G2785: ALUGUEL EQUIPAMENTOS E MÁQUINAS | H2785: 44533 | I2785: >>Data de Pagto
D2786: DIAS CORRIDOS > | E2786: 44534 | G2786: COMBUSTÍVEIS E LUBRIFICANTES | H2786: 44536 | I2786: >>Data de Pagto
D2787: DIAS CORRIDOS > | E2787: 44535 | G2787: COMISSÕES COM VENDAS | H2787: 44536 | I2787: >>Data de Pagto
D2788: DIAS CORRIDOS > | E2788: 44536 | G2788: COMPRA DE MADEIRA | H2788: 44536 | I2788: >>Data de Pagto
D2789: DIAS CORRIDOS > | E2789: 44537 | G2789: COMPRA DE TORAS | H2789: 44537 | I2789: >>Data de Pagto
D2790: DIAS CORRIDOS > | E2790: 44538 | G2790: CONTROLADORIA - W-90X | H2790: 44538 | I2790: >>Data de Pagto
D2791: DIAS CORRIDOS > | E2791: 44539 | G2791: CONTROLADORIA - À VISTA | H2791: 44539 | I2791: >>Data de Pagto
D2792: DIAS CORRIDOS > | E2792: 44540 | G2792: CONTROLADORIA - ADIANTAMENTOS | H2792: 44540 | I2792: >>Data de Pagto
D2793: DIAS CORRIDOS > | E2793: 44541 | G2793: CONTROLADORIA - FRETES INTERNACIONAIS | H2793: 44543 | I2793: >>Data de Pagto
D2794: DIAS CORRIDOS > | E2794: 44542 | G2794: CONTROLADORIA - SILVEIRA | H2794: 44543 | I2794: >>Data de Pagto
D2795: DIAS CORRIDOS > | E2795: 44543 | G2795: CREDORES DIVERSOS | H2795: 44543 | I2795: >>Data de Pagto
D2796: DIAS CORRIDOS > | E2796: 44544 | G2796: DESPESAS ADUANEIRAS | H2796: 44544 | I2796: >>Data de Pagto
... D2812: DIAS CORRIDOS > | E2812: 44560 | G2812: OPERAÇÕES DE CRÉDITO/FORNECEDOR | H2812: 44560 | I2812: >>Data de Pagto
D2813: DIAS CORRIDOS > | E2813: 44561 | H2813: 44561 | I2813: >>Data de Pagto
D2814: SÁBADOS E DOMINGOS > | E2814: 44534 | G2814: OPERAÇÕES FINANCEIRAS DIVS. | H2814: 44534
D2815: SÁBADOS E DOMINGOS > | E2815: 44535 | G2815: PRESTAÇÃO DE SERVIÇOS E ASESSORIAS | H2815: 44535
D2816: SÁBADOS E DOMINGOS > | E2816: 44541 | G2816: PRIME RIBAS | H2816: 44541
D2817: SÁBADOS E DOMINGOS > | E2817: 44542 | G2817: PRIME RIBAS PREVISTO | H2817: 44542
D2818: SÁBADOS E DOMINGOS > | E2818: 44548 | G2818: PROGRAMAS ESPECIAIS | H2818: 44548
D2819: SÁBADOS E DOMINGOS > | E2819: 44549 | G2819: SALÁRIOS + ASSESSORIA DIRETA + BENEFÍCIOS | H2819: 44549
D2820: SÁBADOS E DOMINGOS > | E2820: 44555 | G2820: SERVIÇOS PÚBLICOS | H2820: 44555
D2821: SÁBADOS E DOMINGOS > | E2821: 44556 | H2821: 44556
D2822: SÁBADOS E DOMINGOS >

Sheet Fluxo_12_21
B1: =IF(B5=1,"Domingo",IF(B5=2,"Segunda",IF(B5=3,"Terça",IF(B5=4,"Quarta",IF(B5=5,"Quinta",IF(B5=6,"Sexta",IF(B5=7,"Sábado",0))))))) -> Quarta | C1: =IF(C5=1,"Domingo",IF(C5=2,"Segunda",IF(C5=3,"Terça",IF(C5=4,"Quarta",IF(C5=5,"Quinta",IF(C5=6,"Sexta",IF(C5=7,"Sábado",0))))))) -> Quinta | D1: =IF(D5=1,"Domingo",IF(D5=2,"Segunda",IF(D5=3,"Terça",IF(D5=4,"Quarta",IF(D5=5,"Quinta",IF(D5=6,"Sexta",IF(D5=7,"Sábado",0))))))) -> Sexta | E1: =IF(E5=1,"Domingo",IF(E5=2,"Segunda",IF(E5=3,"Terça",IF(E5=4,"Quarta",IF(E5=5,"Quinta",IF(E5=6,"Sexta",IF(E5=7,"Sábado",0))))))) -> Segunda | F1: =IF(F5=1,"Domingo",IF(F5=2,"Segunda",IF(F5=3,"Terça",IF(F5=4,"Quarta",IF(F5=5,"Quinta",IF(F5=6,"Sexta",IF(F5=7,"Sábado",0))))))) -> Terça | G1: =IF(G5=1,"Domingo",IF(G5=2,"Segunda",IF(G5=3,"Terça",IF(G5=4,"Quarta",IF(G5=5,"Quinta",IF(G5=6,"Sexta",IF(G5=7,"Sábado",0))))))) -> Quarta | H1: =IF(H5=1,"Domingo",IF(H5=2,"Segunda",IF(H5=3,"Terça",IF(H5=4,"Quarta",IF(H5=5,"Quinta",IF(H5=6,"Sexta",IF(H5=7,"Sábado",0))))))) -> Quinta | I1: =IF(I5=1,"Domingo",IF(I5=2,"Segunda",IF(I5=3,"Terça",IF(I5=4,"Quarta",IF(I5=5,"Quinta",IF(I5=6,"Sexta",IF(I5=7,"Sábado",0))))))) -> Sexta | ... W1: =IF(W5=1,"Domingo",IF(W5=2,"Segunda",IF(W5=3,"Terça",IF(W5=4,"Quarta",IF(W5=5,"Quinta",IF(W5=6,"Sexta",IF(W5=7,"Sábado",0))))))) -> Quinta
A2: Localizado no banco | B2: =B29 -> 44531 | C2: =C29 -> 44532 | D2: =D29 -> 44533 | E2: =E29 -> 44536 | F2: =F29 -> 44537 | G2: =G29 -> 44538 | H2: =H29 -> 44539 | I2: =I29 -> 44540 | ... W2: =W29 -> 44560
A4: SALDO INICIAL | B4: =Fluxo_11_21!U38 -> -242393.87 | C4: =B38 -> -243413.87 | D4: =C38 -> -344913.87 | E4: =D38 -> -348504.51 | F4: =E38 -> -359194.62 | G4: =F38 -> -366194.62 | H4: =G38 -> -367698.88 | I4: =H38 -> -372198.88 | J4: =I38 -> -375198.88 | ... W4: =V38 -> -528042.39
B5: =WEEKDAY(B2) -> 4 | C5: =WEEKDAY(C2) -> 5 | D5: =WEEKDAY(D2) -> 6 | E5: =WEEKDAY(E2) -> 2 | F5: =WEEKDAY(F2) -> 3 | G5: =WEEKDAY(G2) -> 4 | H5: =WEEKDAY(H2) -> 5 | I5: =WEEKDAY(I2) -> 6 | ... W5: =WEEKDAY(W2) -> 5
A6: RECEBIMENTOS (OPERAÇÃO) | B6: =SUM(B7:B26) -> 0 | C6: =SUM(C7:C26) -> 0 | D6: =SUM(D7:D26) -> 0 | E6: =SUM(E7:E26) -> 0 | F6: =SUM(F7:F26) -> 0 | G6: =SUM(G7:G26) -> 0 | H6: =SUM(H7:H26) -> 0 | I6: =SUM(I7:I26) -> 0 | ... W6: =SUM(W7:W26) -> 0
A7: MARCOPOLO/SEMAN
A8: MARCOPOLO
A9: VOLARE
A10: HIDROVER
A11: WSUL
A12: RUGERI
A13: CIFERAL
A14: SAN MARINO
A15: LIBRELATO
A27: PAGAMENTOS PROGRAMADOS
A28: Soma de Valor | B28: Pagto.
A29: tipo | B29: 44531 | C29: 44532 | D29: 44533 | E29: 44536 | F29: 44537 | G29: 44538 | H29: 44539 | I29: 44540 | J29: 44543 | K29: 44544 | L29: 44545 | M29: 44546 | N29: 44547 | O29: 44550 | P29: 44551 | Q29: 44552 | R29: 44553 | S29: 44554 | T29: 44557 | U29: 44558 | V29: 44559 | W29: 44560 | X29: Total Geral
A30: PARTICULAR | B30: 1020 | C30: 4500 | H30: 4500 | I30: 3000 | L30: 2573.42 | M30: 4500 | N30: 246.8 | R30: 4500 | T30: 3500 | V30: 404.34 | X30: 28744.56
A31: VENTURE | C31: 7000 | F31: 1000 | J31: 14028.3 | K31: 3390 | M31: 1750 | N31: 4000 | O31: 2800 | P31: 444.18 | V31: 2500 | X31: 36912.48
A32: SOLUTEC | L32: 1843 | S32: 500 | X32: 2343
A33: PKS | L33: 3594.05 | X33: 3594.05
A34: SEMAN | C34: 90000 | D34: 3590.64 | E34: 10690.11 | F34: 6000 | G34: 1504.26 | J34: 7653.5 | L34: 2305 | N34: 51096.62 | O34: 18985.91 | P34: 1500 | Q34: 6500 | T34: 1995 | U34: 11733.39 | V34: 500 | W34: 2412.66 | X34: 216467.09
A35: Total Geral | B35: 1020 | C35: 101500 | D35: 3590.64 | E35: 10690.11 | F35: 7000 | G35: 1504.26 | H35: 4500 | I35: 3000 | J35: 21681.8 | K35: 3390 | L35: 10315.47 | M35: 6250 | N35: 55343.42 | O35: 21785.91 | P35: 1944.18 | Q35: 6500 | R35: 4500 | S35: 500 | T35: 5495 | U35: 11733.39 | V35: 3404.34 | W35: 2412.66 | X35: 288061.18
B38: =B4+B6-GETPIVOTDATA("Valor",$A$28,"Pagto.",DATE(2021,12,1)) -> -243413.87 | C38: =C4+C6-GETPIVOTDATA("Valor",$A$28,"Pagto.",DATE(2021,12,2)) -> -344913.87 | D38: =D4+D6-GETPIVOTDATA("Valor",$A$28,"Pagto.",DATE(2021,12,3)) -> -348504.51 | E38: =E4+E6-GETPIVOTDATA("Valor",$A$28,"Pagto.",DATE(2021,12,6)) -> -359194.62 | F38: =F4+F6-GETPIVOTDATA("Valor",$A$28,"Pagto.",DATE(2021,12,7)) -> -366194.62 | G38: =G4+G6-GETPIVOTDATA("Valor",$A$28,"Pagto.",DATE(2021,12,8)) -> -367698.88 | H38: =H4+H6-GETPIVOTDATA("Valor",$A$28,"Pagto.",DATE(2021,12,9)) -> -372198.88 | I38: =I4+I6-GETPIVOTDATA("Valor",$A$28,"Pagto.",DATE(2021,12,10)) -> -375198.88 | J38: =J4+J6-GETPIVOTDATA("Valor",$A$28,"Pagto.",DATE(2021,12,13)) -> -396880.68 | K38: =K4+K6-GETPIVOTDATA("Valor",$A$28,"Pagto.",DATE(2021,12,14)) -> -400270.68 | L38: =L4+L6-GETPIVOTDATA("Valor",$A$28,"Pagto.",DATE(2021,12,15)) -> -410586.15 | M38: =M4+M6-GETPIVOTDATA("Valor",$A$28,"Pagto.",DATE(2021,12,16)) -> -416836.15 | N38: =N4+N6-GETPIVOTDATA("Valor",$A$28,"Pagto.",DATE(2021,12,17)) -> -472179.57 | O38: =O4+O6-GETPIVOTDATA("Valor",$A$28,"Pagto.",DATE(2021,12,20)) -> -493965.48 | P38: =P4+P6-GETPIVOTDATA("Valor",$A$28,"Pagto.",DATE(2021,12,21)) -> -495909.66 | Q38: =Q4+Q6-GETPIVOTDATA("Valor",$A$28,"Pagto.",DATE(2021,12,22)) -> -502409.66 | R38: =R4+R6-GETPIVOTDATA("Valor",$A$28,"Pagto.",DATE(2021,12,23)) -> -506909.66 | S38: =S4+S6-GETPIVOTDATA("Valor",$A$28,"Pagto.",DATE(2021,12,24)) -> -507409.66 | T38: =T4+T6-GETPIVOTDATA("Valor",$A$28,"Pagto.",DATE(2021,12,27)) -> -512904.66 | U38: =U4+U6-GETPIVOTDATA("Valor",$A$28,"Pagto.",DATE(2021,12,28)) -> -524638.05 | V38: =V4+V6-GETPIVOTDATA("Valor",$A$28,"Pagto.",DATE(2021,12,29)) -> -528042.39 | W38: =W4+W6-GETPIVOTDATA("Valor",$A$28,"Pagto.",DATE(2021,12,30)) -> -530455.05

Sheet 11_21
A1: 0 | B1: tm | C1: CodCli | D1: Nome | E1: dtvcto | F1: Valor | G1: tipo | H1: Pagto.
C2: BANCOS | D2: JUROS E DESPESAS BANCARIAS | E2: 44501 | F2: =2193.19 -> 2193.19 | G2: Empresa 1 | H2: =VLOOKUP(E2,$E$2868:$H$2997,4,FALSE) -> 44501
C3: ENCARGOS | D3: FGTS - vcto 07/10 | E3: 44502 | F3: =10279.79 -> 10279.79 | G3: Empresa 2 | H3: =VLOOKUP(E3,$E$2868:$H$2997,4,FALSE) -> 44503
C4: COMBUSTIVEL | D4: CLEBER | E4: 44503 | F4: 200 | G4: Empresa 2 | H4: =VLOOKUP(E4,$E$2868:$H$2997,4,FALSE) -> 44503
C5: RESCISAO | D5: ANGELICA ALVANOZ - vcto 21/10 | E5: 44504 | F5: 569.3 | G5: Empresa 2 | H5: =VLOOKUP(E5,$E$2868:$H$2997,4,FALSE) -> 44504
C6: PARCELAMENTO | D6: EMPRESTIMO FOLHA BB - 11/30 | E6: 44504 | F6: 2262.99 | G6: Empresa 2 | H6: =VLOOKUP(E6,$E$2868:$H$2997,4,FALSE) -> 44504
C7: SEGURO | D7: ROGERIO - 01/07 - ultimo prazo | E7: 44504 | F7: 404.41 | G7: Distribuição de Lucros | H7: =VLOOKUP(E7,$E$2868:$H$2997,4,FALSE) -> 44504
C8: TRANSPORTE | D8: VAN | E8: 44505 | F8: 3000 | G8: Empresa 2 | H8: =VLOOKUP(E8,$E$2868:$H$2997,4,FALSE) -> 44505
C9: VIAGEM | D9: CAIXINHA MARCIO | E9: 44505 | F9: 300 | G9: Empresa 2 | H9: =VLOOKUP(E9,$E$2868:$H$2997,4,FALSE) -> 44505
C10: VIAGEM | D10: CAIXINHA JOEL | E10: 44505 | F10: 3000 | G10: Empresa 2 | H10: =VLOOKUP(E10,$E$2868:$H$2997,4,FALSE) -> 44505
C11: SALARIOS | D11: LIBRELATO | E11: 44505 | F11: 8594 | G11: Empresa 2 | H11: =VLOOKUP(E11,$E$2868:$H$2997,4,FALSE) -> 44505
C12: SALARIOS | D12: VOLARE | E12: 44505 | F12: 14345 | G12: Empresa 2 | H12: =VLOOKUP(E12,$E$2868:$H$2997,4,FALSE) -> 44505
C13: RESCISAO | D13: ROSANGELA PEDRO - Librelato - vcto 19/10 | E13: 44505 | F13: 356.93 | G13: Empresa 2 | H13: =VLOOKUP(E13,$E$2868:$H$2997,4,FALSE) -> 44505
C14: MATERIAL | D14: CELETRO - ZANOL - vcto 19/07 - já prorrogado duas vezes | E14: 44505 | F14: 940.68 | G14: Empresa 1 | H14: =VLOOKUP(E14,$E$2868:$H$2997,4,FALSE) -> 44505
C15: TRANSPORTE | D15: VISATE - 15 CARTOES | E15: 44505 | F15: 285 | G15: Empresa 2 | H15: =VLOOKUP(E15,$E$2868:$H$2997,4,FALSE) -> 44505
C16: SALARIOS | D16: CHEQUES SALARIOS | E16: 44506 | F16: =4218+470 -> 4688 | G16: Empresa 2 | H16: =VLOOKUP(E16,$E$2868:$H$2997,4,FALSE) -> 44508
C17: PARCELAMENTO | D17: SIMPLES - 02/60 - vcto 29/10 | E17: 44506 | F17: =12064.5+527.24 -> 12591.74 | G17: Empresa 2 | H17: =VLOOKUP(E17,$E$2868:$H$2997,4,FALSE) -> 44508
C18: SAUDE | D18: UNIMED - vcto 15/10 - REEMBOLSAR SR.RUBENS | E18: 44506 | F18: 3812.48 | G18: PKS | H18: =VLOOKUP(E18,$E$2868:$H$2997,4,FALSE) -> 44508
C19: PARCELAMENTO | D19: EMPRESTIMO FOLHA BB - 12/30 | E19: 44506 | F19: 2175.1 | G19: Empresa 2 | H19: =VLOOKUP(E19,$E$2868:$H$2997,4,FALSE) -> 44508
C20: FÉRIAS | D20: ALUISIO COSTA SALES - vcto 15/10 - metade | E20: 44506 | F20: 701 | G20: Empresa 2 | H20: =VLOOKUP(E20,$E$2868:$H$2997,4,FALSE) -> 44508
C21: SALARIOS | D21: SALARIOS | E21: 44506 | F21: 6251 | G21: Empresa 1 | H21: =VLOOKUP(E21,$E$2868:$H$2997,4,FALSE) -> 44508
C22: SALARIOS | D22: SALARIOS | E22: 44506 | F22: =88123-4218-14345-8594-5052 -> 55914 | G22: Empresa 2 | H22: =VLOOKUP(E22,$E$2868:$H$2997,4,FALSE) -> 44508
C23: SALARIOS | D23: PAULO EDUARDO | E23: 44506 | F23: 2800 | G23: Empresa 2 | H23: =VLOOKUP(E23,$E$2868:$H$2997,4,FALSE) -> 44508
C24: SALARIOS | D24: PENSAO ALIMENTICIA | E24: 44506 | F24: =693.62+738.04 -> 1431.66 | G24: Empresa 2 | H24: =VLOOKUP(E24,$E$2868:$H$2997,4,FALSE) -> 44508
C25: FÉRIAS | D25: FABIANA SANTOS RODRIGUES | E25: 44506 | F25: 690 | G25: Empresa 2 | H25: =VLOOKUP(E25,$E$2868:$H$2997,4,FALSE) -> 44508
C26: SALARIOS | D26: GEAN / IGOR - VOLARE (aguardar autorizacao Joel) | E26: 44506 | F26: =2848+2204 -> 5052 | G26: Empresa 2 | H26: =VLOOKUP(E26,$E$2868:$H$2997,4,FALSE) -> 44508
C27: ASSESSORIA | D27: OLIVEIRA E PERES - parte | E27: 44506 | F27: 3135 | G27: Empresa 1 | H27: =VLOOKUP(E27,$E$2868:$H$2997,4,FALSE) -> 44508
C28: EPI | D28: JUSTINA | E28: 44506 | F28: 675 | G28: Empresa 2 | H28: =VLOOKUP(E28,$E$2868:$H$2997,4,FALSE) -> 44508
C29: COMUNICACAO | D29: NET - vcto 20/10/21 | E29: 44506 | F29: 235.89 | G29: Empresa 2 | H29: =VLOOKUP(E29,$E$2868:$H$2997,4,FALSE) -> 44508
C30: SOCIOS | D30: PAGLIARIN - vcto 18/10 | E30: 44506 | F30: 1943.25 | G30: Distribuição de Lucros | H30: =VLOOKUP(E30,$E$2868:$H$2997,4,FALSE) -> 44508
C31: FÉRIAS | D31: GABRIEL - PARTE (vcto 01/10/21) | E31: 44506 | F31: 4000 | G31: Empresa 2 | H31: =VLOOKUP(E31,$E$2868:$H$2997,4,FALSE) -> 44508
C32: ACORDO | D32: SINDIASSEIO - 02/03 - vcto 28/08 - pedir para Joana novo boleto | E32: 44507 | F32: 304.96 | G32: Empresa 2 | H32: =VLOOKUP(E32,$E$2868:$H$2997,4,FALSE) -> 44508
C33: ACORDO | D33: BRUNO DE SOUZA - 02/04 | E33: 44507 | F33: 1504.26 | G33: Empresa 2 | H33: =VLOOKUP(E33,$E$2868:$H$2997,4,FALSE) -> 44508
C34: TERCEIROS | D34: DIGISERVE - 03/03 | E34: 44508 | F34: 473.91 | G34: Empresa 1 | H34: =VLOOKUP(E34,$E$2868:$H$2997,4,FALSE) -> 44508
C35: TERCEIROS | D35: CHAVEIRO CASA DE PEDRA - pagar em dinheiro | E35: 44508 | F35: 40 | G35: Empresa 1 | H35: =VLOOKUP(E35,$E$2868:$H$2997,4,FALSE) -> 44508
C36: ALIMENTACAO | D36: ZAPAROLLI - vcto 01/11 | E36: 44508 | F36: 5962 | G36: Empresa 2 | H36: =VLOOKUP(E36,$E$2868:$H$2997,4,FALSE) -> 44508
C37: EPI | D37: JUSTINA | E37: 44508 | F37: 900 | G37: Empresa 2 | H37: =VLOOKUP(E37,$E$2868:$H$2997,4,FALSE) -> 44508
C38: EPI | D38: M JU - vcto 13/10 (prorrogado duas vezes) | E38: 44509 | F38: 966.9 | G38: Empresa 2 | H38: =VLOOKUP(E38,$E$2868:$H$2997,4,FALSE) -> 44509
... C44: SOCIOS | D44: RETIRADA ROGERIO | E44: 44510 | F44: 3000 | G44: Distribuição de Lucros | H44: =VLOOKUP(E44,$E$2868:$H$2997,4,FALSE) -> 44510
C45: COMUNICACAO | D45: CLARO - vcto 20/10/21 (corte em 13/11) | E45: 44511 | F45: =189.16+42.98+1278.98 -> 1511.12 | G45: Empresa 1 | H45: =VLOOKUP(E45,$E$2868:$H$2997,4,FALSE) -> 44511
C46: EPI | D46: M JU - vcto 18/10 | E46: 44511 | F46: 214.8 | G46: Empresa 2 | H46: =VLOOKUP(E46,$E$2868:$H$2997,4,FALSE) -> 44511
C47: TERCEIROS | D47: DIGISERVE - 02/03 - vcto 18/08 | E47: 44511 | F47: 473.91 | G47: Empresa 1 | H47: =VLOOKUP(E47,$E$2868:$H$2997,4,FALSE) -> 44511
C48: FÉRIAS | D48: JOEL - parte | E48: 44511 | F48: 4053.5 | G48: Empresa 2 | H48: =VLOOKUP(E48,$E$2868:$H$2997,4,FALSE) -> 44511
C49: SOCIOS | D49: RETIRADA LUIS b | E49: 44511 | F49: 2500 | G49: Distribuição de Lucros | H49: =VLOOKUP(E49,$E$2868:$H$2997,4,FALSE) -> 44511
C50: SOCIOS | D50: RETIRADA PAULO d | E50: 44511 | F50: 2000 | G50: Distribuição de Lucros | H50: =VLOOKUP(E50,$E$2868:$H$2997,4,FALSE) -> 44511
C51: RESCISAO | D51: KARINE BARBIERI - LIBRELATO (vcto 22/10) | E51: 44512 | F51: 1877.25 | G51: Empresa 2 | H51: =VLOOKUP(E51,$E$2868:$H$2997,4,FALSE) -> 44512
C52: SOCIOS | D52: GUIA INSS LUIS b - MÊS 04/2021 - reembolsar Dalnir | E52: 44512 | F52: 1299.44 | G52: Distribuição de Lucros | H52: =VLOOKUP(E52,$E$2868:$H$2997,4,FALSE) -> 44512
C53: AGUA | D53: LUCHETTI GAS | E53: 44512 | F53: 120 | G53: Empresa 1 | H53: =VLOOKUP(E53,$E$2868:$H$2997,4,FALSE) -> 44512
C54: SEGURO | D54: WEG - previsao | E54: 44512 | F54: 2600 | G54: Empresa 2 | H54: =VLOOKUP(E54,$E$2868:$H$2997,4,FALSE) -> 44512
C55: EPI | D55: COM DE EQUIP ZAPA | E55: 44512 | F55: 589.8 | G55: Empresa 2 | H55: =VLOOKUP(E55,$E$2868:$H$2997,4,FALSE) -> 44512
C56: INFORMATICA | D56: DIGISAM | E56: 44512 | F56: 742 | G56: Empresa 1 | H56: =VLOOKUP(E56,$E$2868:$H$2997,4,FALSE) -> 44512
C57: VIAGEM | D57: JOEL - CAIXINHA | E57: 44512 | F57: 2100 | G57: Empresa 2 | H57: =VLOOKUP(E57,$E$2868:$H$2997,4,FALSE) -> 44512
... C119: ACORDO | D119: IZAAC - EMAIL JOEL - 06/06 - vcto 10/01/21 - não aceita mais renegociar | E119: 44524 | F119: 1643 | G119: Empresa 2 | H119: =VLOOKUP(E119,$E$2868:$H$2997,4,FALSE) -> 44524
C120: ACORDO | D120: BOX RAPIDO - parcelas 08 e 09 | E120: 44524 | F120: =444.18+444.18 -> 888.36 | G120: Empresa 1 | H120: =VLOOKUP(E120,$E$2868:$H$2997,4,FALSE) -> 44524
C121: INFORMATICA | D121: METADADOS | E121: 44525 | F121: 318.68 | G121: Empresa 1 | H121: =VLOOKUP(E121,$E$2868:$H$2997,4,FALSE) -> 44525
C122: INFORMATICA | D122: METADADOS - vcto 25/09 + mensalidade | E122: 44525 | F122: =318.68+318.68 -> 637.36 | G122: Empresa 1 | H122: =VLOOKUP(E122,$E$2868:$H$2997,4,FALSE) -> 44525
C123: INFORMATICA | D123: INFOCALL | E123: 44525 | F123: 120 | G123: Empresa 1 | H123: =VLOOKUP(E123,$E$2868:$H$2997,4,FALSE) -> 44525
C124: ASSESSORIA | D124: VISAO | E124: 44525 | F124: 3250 | G124: Empresa 2 | H124: =VLOOKUP(E124,$E$2868:$H$2997,4,FALSE) -> 44525
C125: ENCARGOS | D125: REEMBOLSAR AIRMAX - GUIA OLIVEIRA E PERES | E125: 44525 | F125: 1500 | G125: Empresa 1 | H125: =VLOOKUP(E125,$E$2868:$H$2997,4,FALSE) -> 44525
C126: SOCIOS | D126: RETIRADA LUIS b | E126: 44525 | F126: 2500 | G126: Distribuição de Lucros | H126: =VLOOKUP(E126,$E$2868:$H$2997,4,FALSE) -> 44525
C127: SOCIOS | D127: RETIRADA PAULO d | E127: 44525 | F127: 2000 | G127: Distribuição de Lucros | H127: =VLOOKUP(E127,$E$2868:$H$2997,4,FALSE) -> 44525
C128: SAUDE | D128: UNIMED - REEMBOLSAR RUBENS c - unimed paga em dezembro/2020 | E128: 44525 | F128: 3337.71 | G128: PKS | H128: =VLOOKUP(E128,$E$2868:$H$2997,4,FALSE) -> 44525
C129: SOCIOS | D129: RETIRADA ROGERIO | E129: 44525 | F129: 3500 | G129: Distribuição de Lucros | H129: =VLOOKUP(E129,$E$2868:$H$2997,4,FALSE) -> 44525
C130: EPI | D130: ZAPA | E130: 44525 | F130: 696.98 | G130: Empresa 2 | H130: =VLOOKUP(E130,$E$2868:$H$2997,4,FALSE) -> 44525
C131: ALUGUEL | D131: ALUGAMAQ - 30/09 - já prorrogado tres vezes | E131: 44526 | F131: 240 | G131: Empresa 2 | H131: =VLOOKUP(E131,$E$2868:$H$2997,4,FALSE) -> 44526
C132: CONVENIO | D132: PROMED - vcto 15/11 (enviar cheque) | E132: 44526 | F132: 2810.99 | G132: Empresa 2 | H132: =VLOOKUP(E132,$E$2868:$H$2997,4,FALSE) -> 44526
C133: ACORDO | D133: MARCELO QUIRINO - 03/06 | E133: 44526 | F133: 1758.2 | G133: Empresa 2 | H133: =VLOOKUP(E133,$E$2868:$H$2997,4,FALSE) -> 44526
C134: RESCISAO | D134: JANETE DA d - vcto 01/11 - cheque ainda não entregue | E134: 44527 | F134: 616.76 | G134: Empresa 2 | H134: =VLOOKUP(E134,$E$2868:$H$2997,4,FALSE) -> 44529
... C156: PARCELAMENTO | D156: CSLL - DEBITO BB | E156: 44530 | F156: 526.26 | G156: Empresa 2 | H156: =VLOOKUP(E156,$E$2868:$H$2997,4,FALSE) -> 44530
D2867: CALENDÁRIO A AJUSTAR | E2867: VCTO
A2868: RELAÇÃO DAS CONTAS DO FLUXO | D2868: DIAS CORRIDOS > | E2868: 44501 | G2868: A VERIFICAR | H2868: 44501 | I2868: >>Data de Pagto
A2869: (Preenchet até a linha 2.100) | D2869: DIAS CORRIDOS > | E2869: 44502 | G2869: ALUGUEIS DEPÓSITOS PFT/GUGELMIN - MATRIZ | H2869: 44503 | I2869: >>Data de Pagto
D2870: DIAS CORRIDOS > | E2870: 44503 | G2870: ALUGUEL EQUIPAMENTOS E MÁQUINAS | H2870: 44503 | I2870: >>Data de Pagto
D2871: DIAS CORRIDOS > | E2871: 44504 | G2871: COMBUSTÍVEIS E LUBRIFICANTES | H2871: 44504 | I2871: >>Data de Pagto
D2872: DIAS CORRIDOS > | E2872: 44505 | G2872: COMISSÕES COM VENDAS | H2872: 44505 | I2872: >>Data de Pagto
D2873: DIAS CORRIDOS > | E2873: 44506 | G2873: COMPRA DE MADEIRA | H2873: 44508 | I2873: >>Data de Pagto
D2874: DIAS CORRIDOS > | E2874: 44507 | G2874: COMPRA DE TORAS | H2874: 44508 | I2874: >>Data de Pagto
D2875: DIAS CORRIDOS > | E2875: 44508 | G2875: CONTROLADORIA - W-90X | H2875: 44508 | I2875: >>Data de Pagto
D2876: DIAS CORRIDOS > | E2876: 44509 | G2876: CONTROLADORIA - À VISTA | H2876: 44509 | I2876: >>Data de Pagto
D2877: DIAS CORRIDOS > | E2877: 44510 | G2877: CONTROLADORIA - ADIANTAMENTOS | H2877: 44510 | I2877: >>Data de Pagto
D2878: DIAS CORRIDOS > | E2878: 44511 | G2878: CONTROLADORIA - FRETES INTERNACIONAIS | H2878: 44511 | I2878: >>Data de Pagto
D2879: DIAS CORRIDOS > | E2879: 44512 | G2879: CONTROLADORIA - SILVEIRA | H2879: 44512 | I2879: >>Data de Pagto
D2880: DIAS CORRIDOS > | E2880: 44513 | G2880: CREDORES DIVERSOS | H2880: 44516 | I2880: >>Data de Pagto
D2881: DIAS CORRIDOS > | E2881: 44514 | G2881: DESPESAS ADUANEIRAS | H2881: 44516 | I2881: >>Data de Pagto
... D2897: DIAS CORRIDOS > | E2897: 44530 | G2897: OPERAÇÕES DE CRÉDITO/FORNECEDOR | H2897: 44530 | I2897: >>Data de Pagto
D2898: DIAS CORRIDOS > | I2898: >>Data de Pagto
D2899: SÁBADOS E DOMINGOS > | E2899: 44502 | G2899: OPERAÇÕES FINANCEIRAS DIVS. | H2899: 44502
D2900: SÁBADOS E DOMINGOS > | E2900: 44506 | G2900: PRESTAÇÃO DE SERVIÇOS E ASESSORIAS | H2900: 44506
D2901: SÁBADOS E DOMINGOS > | E2901: 44507 | G2901: PRIME RIBAS | H2901: 44507
D2902: SÁBADOS E DOMINGOS > | E2902: 44513 | G2902: PRIME RIBAS PREVISTO | H2902: 44513
D2903: SÁBADOS E DOMINGOS > | E2903: 44514 | G2903: PROGRAMAS ESPECIAIS | H2903: 44514
D2904: SÁBADOS E DOMINGOS > | E2904: 44520 | G2904: SALÁRIOS + ASSESSORIA DIRETA + BENEFÍCIOS | H2904: 44520
D2905: SÁBADOS E DOMINGOS > | E2905: 44521 | G2905: SERVIÇOS PÚBLICOS | H2905: 44521
D2906: SÁBADOS E DOMINGOS > | E2906: 44527 | H2906: 44527
D2907: SÁBADOS E DOMINGOS > | E2907: 44528 | H2907: 44528

Sheet Fluxo_11_21
B1: =IF(B5=1,"Domingo",IF(B5=2,"Segunda",IF(B5=3,"Terça",IF(B5=4,"Quarta",IF(B5=5,"Quinta",IF(B5=6,"Sexta",IF(B5=7,"Sábado",0))))))) -> Segunda | C1: =IF(C5=1,"Domingo",IF(C5=2,"Segunda",IF(C5=3,"Terça",IF(C5=4,"Quarta",IF(C5=5,"Quinta",IF(C5=6,"Sexta",IF(C5=7,"Sábado",0))))))) -> Quarta | D1: =IF(D5=1,"Domingo",IF(D5=2,"Segunda",IF(D5=3,"Terça",IF(D5=4,"Quarta",IF(D5=5,"Quinta",IF(D5=6,"Sexta",IF(D5=7,"Sábado",0))))))) -> Quinta | E1: =IF(E5=1,"Domingo",IF(E5=2,"Segunda",IF(E5=3,"Terça",IF(E5=4,"Quarta",IF(E5=5,"Quinta",IF(E5=6,"Sexta",IF(E5=7,"Sábado",0))))))) -> Sexta | F1: =IF(F5=1,"Domingo",IF(F5=2,"Segunda",IF(F5=3,"Terça",IF(F5=4,"Quarta",IF(F5=5,"Quinta",IF(F5=6,"Sexta",IF(F5=7,"Sábado",0))))))) -> Segunda | G1: =IF(G5=1,"Domingo",IF(G5=2,"Segunda",IF(G5=3,"Terça",IF(G5=4,"Quarta",IF(G5=5,"Quinta",IF(G5=6,"Sexta",IF(G5=7,"Sábado",0))))))) -> Terça | H1: =IF(H5=1,"Domingo",IF(H5=2,"Segunda",IF(H5=3,"Terça",IF(H5=4,"Quarta",IF(H5=5,"Quinta",IF(H5=6,"Sexta",IF(H5=7,"Sábado",0))))))) -> Quarta | I1: =IF(I5=1,"Domingo",IF(I5=2,"Segunda",IF(I5=3,"Terça",IF(I5=4,"Quarta",IF(I5=5,"Quinta",IF(I5=6,"Sexta",IF(I5=7,"Sábado",0))))))) -> Quinta | ... V1: =IF(V5=1,"Domingo",IF(V5=2,"Segunda",IF(V5=3,"Terça",IF(V5=4,"Quarta",IF(V5=5,"Quinta",IF(V5=6,"Sexta",IF(V5=7,"Sábado",0))))))) -> #VALUE!
A2: Localizado no banco | B2: =B29 -> 44501 | C2: =C29 -> 44503 | D2: =D29 -> 44504 | E2: =E29 -> 44505 | F2: =F29 -> 44508 | G2: =G29 -> 44509 | H2: =H29 -> 44510 | I2: =I29 -> 44511 | ... V2: =V29 -> Total Geral
A4: SALDO INICIAL | B4: =Fluxo_10_21!V38 -> -17062.182 | C4: =B38 -> -19255.372 | D4: =C38 -> -19619.482 | E4: =D38 -> 16045.168 | F4: =E38 -> -14776.442 | G4: =F38 -> -115327.81 | H4: =G38 -> -104115.15 | I4: =H38 -> -110649.78 | J4: =I38 -> -121403.11 | ... V4: =U38 -> -242393.87
B5: =WEEKDAY(B2) -> 2 | C5: =WEEKDAY(C2) -> 4 | D5: =WEEKDAY(D2) -> 5 | E5: =WEEKDAY(E2) -> 6 | F5: =WEEKDAY(F2) -> 2 | G5: =WEEKDAY(G2) -> 3 | H5: =WEEKDAY(H2) -> 4 | I5: =WEEKDAY(I2) -> 5 | ... V5: =WEEKDAY(V2) -> #VALUE!
A6: RECEBIMENTOS (OPERAÇÃO) | B6: =SUM(B7:B26) -> 0 | C6: =SUM(C7:C26) -> 10115.68 | D6: =SUM(D7:D26) -> 38901.35 | E6: =SUM(E7:E26) -> 0 | F6: =SUM(F7:F26) -> 14729.88 | G6: =SUM(G7:G26) -> 14579.56 | H6: =SUM(H7:H26) -> 0 | I6: =SUM(I7:I26) -> 0 | ... V6: =SUM(V7:V26) -> 0
A7: MARCOPOLO/SEMAN | D7: =6762.08+11747+14518.35 -> 33027.43 | G7: 14579.56 | K7: 14606.55
A8: MARCOPOLO | D8: =5873.92 -> 5873.92
A9: VOLARE | F9: =4850+4850 -> 9700 | K9: =648+2100+648 -> 3396 | L9: 12000
A10: HIDROVER | M10: 9172.8
A11: WSUL
A12: RUGERI | N12: 2185.89 | S12: 1749.12
A13: CIFERAL
A14: SAN MARINO | C14: =4252.83+5862.85 -> 10115.68 | F14: 5029.88 | K14: 6087.41
A15: LIBRELATO | K15: =6731.83+6201.84+5271.3 -> 18204.97 | T15: =5872.25+6946.83+5872.35+9583.14+9583.14 -> 37857.71
A27: PAGAMENTOS PROGRAMADOS
A28: Soma de Valor | B28: Pagto.
A29: tipo | B29: 44501 | C29: 44503 | D29: 44504 | E29: 44505 | F29: 44508 | G29: 44509 | H29: 44510 | I29: 44511 | J29: 44512 | K29: 44516 | L29: 44517 | M29: 44518 | N29: 44519 | O29: 44522 | P29: 44523 | Q29: 44524 | R29: 44525 | S29: 44526 | T29: 44529 | U29: 44530 | V29: Total Geral
A30: PARTICULAR | D30: 404.41 | F30: 1943.25 | H30: 3000 | I30: 4500 | J30: 1299.44 | K30: 1691.05 | M30: 4500 | N30: 246.8 | O30: 1286.71 | P30: 1020.5 | R30: 8000 | U30: 404.34 | V30: 28296.5
A31: VENTURE | B31: 2193.19 | E31: 940.68 | F31: 9899.91 | H31: 220 | I31: 1985.03 | J31: 862 | K31: 21950.79 | L31: 2369.85 | N31: 2105.8 | O31: 5084.62 | Q31: 888.36 | R31: 2576.04 | T31: 5612.5 | V31: 56688.77
A32: SOLUTEC | K32: 1476.38 | P32: 500 | V32: 1976.38
A33: PKS | F33: 3812.48 | M33: 3784.71 | R33: 3337.71 | V33: 10934.9
A34: SEMAN | C34: 10479.79 | D34: 2832.29 | E34: 29880.93 | F34: 99625.61 | G34: 3366.9 | H34: 3314.63 | I34: 4268.3 | J34: 7167.05 | K34: 10828.35 | L34: 8675.19 | M34: 3721.05 | N34: 8831.76 | O34: 27223.36 | Q34: 1643 | R34: 3946.98 | S34: 4809.19 | T34: 64072.76 | U34: 16334.92 | V34: 311022.06
A35: Total Geral | B35: 2193.19 | C35: 10479.79 | D35: 3236.7 | E35: 30821.61 | F35: 115281.25 | G35: 3366.9 | H35: 6534.63 | I35: 10753.33 | J35: 9328.49 | K35: 35946.57 | L35: 11045.04 | M35: 12005.76 | N35: 11184.36 | O35: 33594.69 | P35: 1520.5 | Q35: 2531.36 | R35: 17860.73 | S35: 4809.19 | T35: 69685.26 | U35: 16739.26 | V35: 408918.61
A38: SALDO FINAL | B38: =B4+B6-GETPIVOTDATA("Valor",$A$28,"Pagto.",DATE(2021,11,1)) -> -19255.372 | C38: =C4+C6-GETPIVOTDATA("Valor",$A$28,"Pagto.",DATE(2021,11,3)) -> -19619.482 | D38: =D4+D6-GETPIVOTDATA("Valor",$A$28,"Pagto.",DATE(2021,11,4)) -> 16045.168 | E38: =E4+E6-GETPIVOTDATA("Valor",$A$28,"Pagto.",DATE(2021,11,5)) -> -14776.442 | F38: =F4+F6-GETPIVOTDATA("Valor",$A$28,"Pagto.",DATE(2021,11,8)) -> -115327.81 | G38: =G4+G6-GETPIVOTDATA("Valor",$A$28,"Pagto.",DATE(2021,11,9)) -> -104115.15 | H38: =H4+H6-GETPIVOTDATA("Valor",$A$28,"Pagto.",DATE(2021,11,10)) -> -110649.78 | I38: =I4+I6-GETPIVOTDATA("Valor",$A$28,"Pagto.",DATE(2021,11,11)) -> -121403.11 | J38: =J4+J6-GETPIVOTDATA("Valor",$A$28,"Pagto.",DATE(2021,11,12)) -> -130731.6 | K38: =K4+K6-GETPIVOTDATA("Valor",$A$28,"Pagto.",DATE(2021,11,16)) -> -124383.24 | L38: =L4+L6-GETPIVOTDATA("Valor",$A$28,"Pagto.",DATE(2021,11,17)) -> -123428.28 | M38: =M4+M6-GETPIVOTDATA("Valor",$A$28,"Pagto.",DATE(2021,11,18)) -> -126261.24 | N38: =N4+N6-GETPIVOTDATA("Valor",$A$28,"Pagto.",DATE(2021,11,19)) -> -135259.71 | O38: =O4+O6-GETPIVOTDATA("Valor",$A$28,"Pagto.",DATE(2021,11,22)) -> -168854.4 | P38: =P4+P6-GETPIVOTDATA("Valor",$A$28,"Pagto.",DATE(2021,11,23)) -> -170374.9 | Q38: =Q4+Q6-GETPIVOTDATA("Valor",$A$28,"Pagto.",DATE(2021,11,24)) -> -172906.26 | R38: =R4+R6-GETPIVOTDATA("Valor",$A$28,"Pagto.",DATE(2021,11,25)) -> -190766.99 | S38: =S4+S6-GETPIVOTDATA("Valor",$A$28,"Pagto.",DATE(2021,11,26)) -> -193827.06 | T38: =T4+T6-GETPIVOTDATA("Valor",$A$28,"Pagto.",DATE(2021,11,29)) -> -225654.61 | U38: =U4+U6-GETPIVOTDATA("Valor",$A$28,"Pagto.",DATE(2021,11,30)) -> -242393.87

Sheet 10_21
A1: 0 | B1: tm | C1: CodCli | D1: Nome | E1: dtvcto | F1: Valor | G1: tipo | H1: Pagto.
C2: BANCOS | D2: JUROS E DESPESAS BANCARIAS | E2: 44470 | F2: =2145.17+157.32+234.5+82.75+945+430.4 -> 3995.14 | G2: Empresa 1 | H2: =VLOOKUP(E2,$E$2698:$H$3009,4,FALSE) -> 44470
C3: ASSESSORIA | D3: OLIVEIRA E PERES - parte | E3: 44470 | F3: 3135 | G3: Empresa 1 | H3: =VLOOKUP(E3,$E$2698:$H$3009,4,FALSE) -> 44470
C4: MANUTENCAO | D4: TECNOFAST | E4: 44470 | F4: 145.55 | G4: Empresa 1 | H4: =VLOOKUP(E4,$E$2698:$H$3009,4,FALSE) -> 44470
C5: SOCIOS | D5: LUIS b | E5: 44470 | F5: 1000 | G5: Distribuição de Lucros | H5: =VLOOKUP(E5,$E$2698:$H$3009,4,FALSE) -> 44470
C6: EPI | D6: M JU | E6: 44470 | F6: 184.6 | G6: Empresa 2 | H6: =VLOOKUP(E6,$E$2698:$H$3009,4,FALSE) -> 44470
C7: ENCARGOS | D7: JUNTA COML - livro diario - Visao | E7: 44470 | F7: 26.33 | G7: Empresa 2 | H7: =VLOOKUP(E7,$E$2698:$H$3009,4,FALSE) -> 44470
C8: ALIMENTACAO | D8: RODRIGO CARDOSO - IRMAOS DA FRONTEIRA - vcto 11/09 | E8: 44471 | F8: 170.9 | G8: Empresa 2 | H8: =VLOOKUP(E8,$E$2698:$H$3009,4,FALSE) -> 44473
C9: SOCIOS | D9: CASAS PAGLIARIN - VCTO 18/07 - sem falta cartorio | E9: 44472 | F9: 2046.92 | G9: Distribuição de Lucros | H9: =VLOOKUP(E9,$E$2698:$H$3009,4,FALSE) -> 44473
C10: PARCELAMENTO | D10: EMPRESTIMO FOLHA BB - 10/30 | E10: 44473 | F10: 2256.05 | G10: Empresa 2 | H10: =VLOOKUP(E10,$E$2698:$H$3009,4,FALSE) -> 44473
C11: TRANSPORTE | D11: VISATE- 20 cartoes | E11: 44473 | F11: 380 | G11: Empresa 2 | H11: =VLOOKUP(E11,$E$2698:$H$3009,4,FALSE) -> 44473
C12: EPI | D12: MAJUSEG | E12: 44474 | F12: 173.76 | G12: Empresa 2 | H12: =VLOOKUP(E12,$E$2698:$H$3009,4,FALSE) -> 44474
C13: SOCIOS | D13: LUIS b | E13: 44474 | F13: 500 | G13: Empresa 2 | H13: =VLOOKUP(E13,$E$2698:$H$3009,4,FALSE) -> 44474
C14: COMUNICACAO | D14: NET - vcto 20/09 (corte em 13/10) | E14: 44475 | F14: 206.95 | G14: Empresa 2 | H14: =VLOOKUP(E14,$E$2698:$H$3009,4,FALSE) -> 44475
... C20: ENCARGOS | D20: FGTS | E20: 44476 | F20: 783.61 | G20: Empresa 1 | H20: =VLOOKUP(E20,$E$2698:$H$3009,4,FALSE) -> 44476
C21: FÉRIAS | D21: PAOLA GOMES CAMINHA - vcto 09/09/21 - saldo | E21: 44476 | F21: =824-400 -> 424 | G21: Empresa 2 | H21: =VLOOKUP(E21,$E$2698:$H$3009,4,FALSE) -> 44476
C22: RESCISAO | D22: LUCINARA BENITES - SINDICATO | E22: 44476 | F22: 525.02 | G22: Empresa 2 | H22: =VLOOKUP(E22,$E$2698:$H$3009,4,FALSE) -> 44476
C23: COMBUSTIVEL | D23: FLAVIO | E23: 44476 | F23: 100 | G23: Empresa 2 | H23: =VLOOKUP(E23,$E$2698:$H$3009,4,FALSE) -> 44476
C24: VIAGEM | D24: JOEL - CAIXINHA - 01/03 | E24: 44476 | F24: 1811 | G24: Empresa 2 | H24: =VLOOKUP(E24,$E$2698:$H$3009,4,FALSE) -> 44476
C25: RESCISAO | D25: DANIEL TEIXEIRA - LIBRELATO | E25: 44476 | F25: 520.65 | G25: Empresa 2 | H25: =VLOOKUP(E25,$E$2698:$H$3009,4,FALSE) -> 44476
C26: VIAGEM | D26: VOB HOTEL - vcto 04/10 - já prorrogado (ultimo prazo antes do cartorio) | E26: 44477 | F26: 452 | G26: Empresa 2 | H26: =VLOOKUP(E26,$E$2698:$H$3009,4,FALSE) -> 44477
C27: SALARIOS | D27: SALARIOS - LIRANE e GUSTAVO (seguranca) | E27: 44477 | F27: =3625+3159 -> 6784 | G27: Empresa 2 | H27: =VLOOKUP(E27,$E$2698:$H$3009,4,FALSE) -> 44477
C28: SALARIOS | D28: SALARIOS - Antonio/ Volare - parte | E28: 44477 | F28: 1000 | G28: Empresa 2 | H28: =VLOOKUP(E28,$E$2698:$H$3009,4,FALSE) -> 44477
C29: ACORDO | D29: BRUNO DE SOUZA - 01/04 | E29: 44477 | F29: 1504.26 | G29: Empresa 2 | H29: =VLOOKUP(E29,$E$2698:$H$3009,4,FALSE) -> 44477
C30: EPI | D30: JUSTINA - vcto 19/09 - já prorrogado | E30: 44477 | F30: 787.5 | G30: Empresa 2 | H30: =VLOOKUP(E30,$E$2698:$H$3009,4,FALSE) -> 44477
C31: SOCIOS | D31: SEGURO LUIS b - STRADA | E31: 44477 | F31: 246.8 | G31: Distribuição de Lucros | H31: =VLOOKUP(E31,$E$2698:$H$3009,4,FALSE) -> 44477
C32: ALIMENTACAO | D32: ZAPAROLLI - PARTE (vcto 30/09) - não atende se não pagar | E32: 44477 | F32: 3000 | G32: Empresa 2 | H32: =VLOOKUP(E32,$E$2698:$H$3009,4,FALSE) -> 44477
C33: ALUGUEL | D33: MARCIO | E33: 44477 | F33: 950 | G33: Empresa 2 | H33: =VLOOKUP(E33,$E$2698:$H$3009,4,FALSE) -> 44477
C34: VIAGEM | D34: VOB HOTEL - vcto 13/09 | E34: 44477 | F34: =224+460 -> 684 | G34: Empresa 2 | H34: =VLOOKUP(E34,$E$2698:$H$3009,4,FALSE) -> 44477
C35: EPI | D35: MARCIO - 20 MASCARAS | E35: 44477 | F35: 90 | G35: Empresa 2 | H35: =VLOOKUP(E35,$E$2698:$H$3009,4,FALSE) -> 44477
C36: SALARIOS | D36: CHEQUES SALARIOS | E36: 44478 | F36: =658+629+91 -> 1378 | G36: Empresa 2 | H36: =VLOOKUP(E36,$E$2698:$H$3009,4,FALSE) -> 44480
C37: ENCARGOS | D37: GUIA SINDICATO - agendado | E37: 44480 | F37: 30 | G37: Empresa 2 | H37: =VLOOKUP(E37,$E$2698:$H$3009,4,FALSE) -> 44480
E38: 44481 | F38: 0 | G38: Empresa 2 | H38: =VLOOKUP(E38,$E$2698:$H$3009,4,FALSE) -> 44481
C39: SALARIOS | D39: CHEQUES SALARIOS | E39: 44482 | F39: =1288+424 -> 1712 | G39: Empresa 2 | H39: =VLOOKUP(E39,$E$2698:$H$3009,4,FALSE) -> 44482
C40: SALARIOS | D40: SALARIOS - Antonio (saldo)/Cristine/Romildo/Jose Luis/Joel (parte) - Volare | E40: 44482 | F40: =1075+1260+1876+2587+2000 -> 8798 | G40: Empresa 2 | H40: =VLOOKUP(E40,$E$2698:$H$3009,4,FALSE) -> 44482
C41: SALARIOS | D41: SALARIOS - Flavio/Nelci/Fabiana | E41: 44482 | F41: =3139+4550+3175 -> 10864 | G41: Empresa 2 | H41: =VLOOKUP(E41,$E$2698:$H$3009,4,FALSE) -> 44482
C42: COMUNICACAO | D42: CLARO - vcto 20/09 (corte em 14/10) | E42: 44482 | F42: =44.11+1283.39+189.39 -> 1516.89 | G42: Empresa 1 | H42: =VLOOKUP(E42,$E$2698:$H$3009,4,FALSE) -> 44482
C43: EPI | D43: MAJUSEG - vcto 04/10 | E43: 44482 | F43: 1037.97 | G43: Empresa 2 | H43: =VLOOKUP(E43,$E$2698:$H$3009,4,FALSE) -> 44482
C44: TERCEIROS | D44: GT3 - vcto 20/09 - já prorrogado | E44: 44482 | F44: 903.27 | G44: Empresa 2 | H44: =VLOOKUP(E44,$E$2698:$H$3009,4,FALSE) -> 44482
C45: ACORDO | D45: JURIDICO marco 01/03 | E45: 44482 | F45: 3390 | G45: Empresa 1 | H45: =VLOOKUP(E45,$E$2698:$H$3009,4,FALSE) -> 44482
C46: SALARIOS | D46: CLEBER | E46: 44483 | F46: 4143.9 | G46: Empresa 2 | H46: =VLOOKUP(E46,$E$2698:$H$3009,4,FALSE) -> 44483
C47: SALARIOS | D47: ESTER | E47: 44483 | F47: 1562 | G47: Empresa 2 | H47: =VLOOKUP(E47,$E$2698:$H$3009,4,FALSE) -> 44483
C48: SEGURO | D48: OUTLANDER - LUIS - 03/07 - ultimo prazo | E48: 44484 | F48: 415.09 | G48: Distribuição de Lucros | H48: =VLOOKUP(E48,$E$2698:$H$3009,4,FALSE) -> 44484
C49: TRANSPORTE | D49: VISATE - CARTAO ROBERTO CABRAL | E49: 44484 | F49: 92.95 | G49: Empresa 2 | H49: =VLOOKUP(E49,$E$2698:$H$3009,4,FALSE) -> 44484
C50: TRANSPORTE | D50: VISATE - 05 CARTOES | E50: 44484 | F50: 95 | G50: Empresa 2 | H50: =VLOOKUP(E50,$E$2698:$H$3009,4,FALSE) -> 44484
C51: RESCISAO | D51: ADAILSON DAMASCENO - FGTS RESCISORIO | E51: 44484 | F51: 16.72 | G51: Empresa 2 | H51: =VLOOKUP(E51,$E$2698:$H$3009,4,FALSE) -> 44484
C52: VIAGEM | D52: CITY HOTEL - MARCIO | E52: 44484 | F52: 158.16 | G52: Empresa 2 | H52: =VLOOKUP(E52,$E$2698:$H$3009,4,FALSE) -> 44484
C53: MATERIAL | D53: LF SILVEIRA | E53: 44484 | F53: 248 | G53: Empresa 2 | H53: =VLOOKUP(E53,$E$2698:$H$3009,4,FALSE) -> 44484
C54: SALARIOS | D54: CHEQUES SALARIOS | E54: 44484 | F54: 454 | G54: Empresa 2 | H54: =VLOOKUP(E54,$E$2698:$H$3009,4,FALSE) -> 44484
... C58: ALIMENTACAO | D58: CANTINA DELA COLINA - vcto agosto | E58: 44486 | F58: 1000 | G58: Empresa 2 | H58: =VLOOKUP(E58,$E$2698:$H$3009,4,FALSE) -> 44487
C59: RESCISAO | D59: FGTS RESCISORIO | E59: 44487 | F59: =25.31+32.64 -> 57.95 | G59: Empresa 2 | H59: =VLOOKUP(E59,$E$2698:$H$3009,4,FALSE) -> 44487
C60: SALARIOS | D60: PENSAO ALIMENTICIA | E60: 44488 | F60: =673.39+749.36 -> 1422.75 | G60: Empresa 2 | H60: =VLOOKUP(E60,$E$2698:$H$3009,4,FALSE) -> 44488
C61: IMPOSTOS | D61: IRF NF PROSALUTE | E61: 44489 | F61: 168.85 | G61: Empresa 2 | H61: =VLOOKUP(E61,$E$2698:$H$3009,4,FALSE) -> 44489
C62: SALARIOS | D62: SALARIOS - Joel-saldo | E62: 44489 | F62: 4078 | G62: Empresa 2 | H62: =VLOOKUP(E62,$E$2698:$H$3009,4,FALSE) -> 44489
C63: ACORDO | D63: TEONAS - 01/10 | E63: 44489 | F63: 1111.29 | G63: Empresa 2 | H63: =VLOOKUP(E63,$E$2698:$H$3009,4,FALSE) -> 44489
C64: VIAGEM | D64: REEMBOLSO MARCIO - em 30/09 | E64: 44489 | F64: 815 | G64: Empresa 2 | H64: =VLOOKUP(E64,$E$2698:$H$3009,4,FALSE) -> 44489
C65: INFORMATICA | D65: METADADOS - vcto 25/07 + 25/08 | E65: 44489 | F65: =318.68+318.68 -> 637.36 | G65: Empresa 1 | H65: =VLOOKUP(E65,$E$2698:$H$3009,4,FALSE) -> 44489
C66: SOCIOS | D66: VIVO - LUIS b | E66: 44489 | F66: 84.73 | G66: Distribuição de Lucros | H66: =VLOOKUP(E66,$E$2698:$H$3009,4,FALSE) -> 44489
C67: SALARIOS | D67: PAULO EDUARDO | E67: 44489 | F67: =2800-700-180+10+30 -> 1960 | G67: Empresa 1 | H67: =VLOOKUP(E67,$E$2698:$H$3009,4,FALSE) -> 44489
C68: ENCARGOS | D68: MENSAL SINDIASSEIO (desc funcionario) | E68: 44490 | F68: 33.41 | G68: Empresa 2 | H68: =VLOOKUP(E68,$E$2698:$H$3009,4,FALSE) -> 44490
C69: VIAGEM | D69: LUIS b - Criciuma | E69: 44490 | F69: 500 | G69: Empresa 2 | H69: =VLOOKUP(E69,$E$2698:$H$3009,4,FALSE) -> 44490
C70: EPI | D70: MAJUSEG | E70: 44490 | F70: 210 | G70: Empresa 2 | H70: =VLOOKUP(E70,$E$2698:$H$3009,4,FALSE) -> 44490
C71: COMBUSTIVEL | D71: FLAVIO/CLEBER | E71: 44490 | F71: 200 | G71: Empresa 2 | H71: =VLOOKUP(E71,$E$2698:$H$3009,4,FALSE) -> 44490
C72: ALIMENTACAO | D72: BISTRO LUCAS RAMOS | E72: 44490 | F72: 2010 | G72: Empresa 1 | H72: =VLOOKUP(E72,$E$2698:$H$3009,4,FALSE) -> 44490
C73: SALARIOS | D73: CHEQUES SALARIOS | E73: 44491 | F73: 112 | G73: Empresa 2 | H73: =VLOOKUP(E73,$E$2698:$H$3009,4,FALSE) -> 44491
C74: RESCISAO | D74: BENOIT VINCET - vcto 08/10 | E74: 44491 | F74: 394.16 | G74: Empresa 2 | H74: =VLOOKUP(E74,$E$2698:$H$3009,4,FALSE) -> 44491
C75: ALIMENTACAO | D75: ZAPAROLLI - parte | E75: 44491 | F75: 3000 | G75: Empresa 2 | H75: =VLOOKUP(E75,$E$2698:$H$3009,4,FALSE) -> 44491
C76: VIAGEM | D76: JOEL - CAIXINHA - 02/03 | E76: 44491 | F76: 1811 | G76: Empresa 2 | H76: =VLOOKUP(E76,$E$2698:$H$3009,4,FALSE) -> 44491
C77: RECLAMATORIA | D77: ANDRE MARQUES - 04/20 | E77: 44491 | F77: 3200 | G77: Empresa 2 | H77: =VLOOKUP(E77,$E$2698:$H$3009,4,FALSE) -> 44491
C78: SALARIOS | D78: EXTRAS EDMILSON - metade | E78: 44491 | F78: 1209 | G78: Empresa 2 | H78: =VLOOKUP(E78,$E$2698:$H$3009,4,FALSE) -> 44491
C79: RESCISAO | D79: FGTS - KARINE BARBIERI | E79: 44491 | F79: 520.05 | G79: Empresa 2 | H79: =VLOOKUP(E79,$E$2698:$H$3009,4,FALSE) -> 44491
... C93: RESCISAO | D93: ADAILSON DAMASCENO - vcto 15/10 | E93: 44494 | F93: 365.74 | G93: Empresa 2 | H93: =VLOOKUP(E93,$E$2698:$H$3009,4,FALSE) -> 44494
C94: ENCARGOS | D94: INSS - vcto 20/10 | E94: 44494 | F94: =12156.93+201.92 -> 12358.85 | G94: Empresa 2 | H94: =VLOOKUP(E94,$E$2698:$H$3009,4,FALSE) -> 44494
C95: SALARIOS | D95: SALARIOS - Gabriel (saldo) | E95: 44494 | F95: 2541 | G95: Empresa 2 | H95: =VLOOKUP(E95,$E$2698:$H$3009,4,FALSE) -> 44494
C96: PARCELAMENTO | D96: MONEO - vcto 15/08 - saldo | E96: 44494 | F96: 7587 | G96: Empresa 1 | H96: =VLOOKUP(E96,$E$2698:$H$3009,4,FALSE) -> 44494
C97: PARCELAMENTO | D97: MONEO - 15/09 | E97: 44494 | F97: =14028.3+985.75 -> 15014.05 | G97: Empresa 1 | H97: =VLOOKUP(E97,$E$2698:$H$3009,4,FALSE) -> 44494
C98: PARCELAMENTO | D98: MONEO - 15/10 | E98: 44494 | F98: 14028.3 | G98: Empresa 1 | H98: =VLOOKUP(E98,$E$2698:$H$3009,4,FALSE) -> 44494
C99: EPI | D99: ACORDO PONTO DAS SOLDAS - PARCELA FINAL (PIX 30.383.069/0001-02) | E99: 44495 | F99: 642.4 | G99: Empresa 2 | H99: =VLOOKUP(E99,$E$2698:$H$3009,4,FALSE) -> 44495
C100: CURSO | D100: RAFAEL SCOPEL | E100: 44495 | F100: 1000 | G100: Empresa 2 | H100: =VLOOKUP(E100,$E$2698:$H$3009,4,FALSE) -> 44495
E101: 44496 | F101: 0 | G101: Empresa 2 | H101: =VLOOKUP(E101,$E$2698:$H$3009,4,FALSE) -> 44496
C102: EMPRESTIMO | D102: DEVOLUCAO ANDREIA/OLIMPIA | E102: 44497 | F102: 20000 | G102: Empresa 2 | H102: =VLOOKUP(E102,$E$2698:$H$3009,4,FALSE) -> 44497
C103: TERCEIROS | D103: MARCIA PAIM - LIMPEZA DE 03 Empresa 2AS - cheque | E103: 44498 | F103: 210 | G103: Empresa 1 | H103: =VLOOKUP(E103,$E$2698:$H$3009,4,FALSE) -> 44498
C104: SALARIOS | D104: EMANUEL PF | E104: 44498 | F104: 120 | G104: Empresa 2 | H104: =VLOOKUP(E104,$E$2698:$H$3009,4,FALSE) -> 44498
C105: RESCISAO | D105: JEAN CHARLES | E105: 44498 | F105: 144.89 | G105: Empresa 2 | H105: =VLOOKUP(E105,$E$2698:$H$3009,4,FALSE) -> 44498
C106: SOCIOS | D106: IRF VERA KARLING - 06/08 | E106: 44498 | F106: 242.81 | G106: Empresa 2 | H106: =VLOOKUP(E106,$E$2698:$H$3009,4,FALSE) -> 44498
C107: SAUDE | D107: PLANO FUNCIONARIOS - já descontado (vencido em 18/10) | E107: 44498 | F107: 1088.78 | G107: Empresa 2 | H107: =VLOOKUP(E107,$E$2698:$H$3009,4,FALSE) -> 44498
C108: SALARIOS | D108: DIFERENCA MARCIO - vcto 20/09/21 - saldo | E108: 44498 | F108: 600 | G108: Empresa 2 | H108: =VLOOKUP(E108,$E$2698:$H$3009,4,FALSE) -> 44498
C109: ALIMENTACAO | D109: ZAPAROLLI - saldo | E109: 44498 | F109: 2276 | G109: Empresa 2 | H109: =VLOOKUP(E109,$E$2698:$H$3009,4,FALSE) -> 44498
C110: SOCIOS | D110: SEGURO DE VIDA RUBENS c - vcto 04/10 | E110: 44498 | F110: 1020.5 | G110: Distribuição de Lucros | H110: =VLOOKUP(E110,$E$2698:$H$3009,4,FALSE) -> 44498
C111: ENERGIA | D111: RGE - vcto 04/10/21 | E111: 44498 | F111: 1081.59 | G111: Empresa 1 | H111: =VLOOKUP(E111,$E$2698:$H$3009,4,FALSE) -> 44498
C112: SALARIOS | D112: BONUS (Caxias) | E112: 44498 | F112: 1560 | G112: Empresa 2 | H112: =VLOOKUP(E112,$E$2698:$H$3009,4,FALSE) -> 44498
C113: TRANSPORTE | D113: VAN - parte | E113: 44498 | F113: 2000 | G113: Empresa 2 | H113: =VLOOKUP(E113,$E$2698:$H$3009,4,FALSE) -> 44498
... C126: EPI | D126: ALSCO - vcto 22/10 | E126: 44501 | F126: 336.56 | G126: Empresa 2 | H126: =VLOOKUP(E126,$E$2698:$H$3009,4,FALSE) -> #N/A
C127: SALARIOS | D127: EXTRAS VOLARE - setembro (confirmar se Edmilson esta no valor) | E127: 44501 | F127: =5166+5166-1209-1209 -> 7914 | G127: Empresa 2 | H127: =VLOOKUP(E127,$E$2698:$H$3009,4,FALSE) -> #N/A
C128: ACORDO | D128: MARCELO QUIRINO - 02/06 | E128: 44501 | F128: 1758.2 | G128: Empresa 2 | H128: =VLOOKUP(E128,$E$2698:$H$3009,4,FALSE) -> #N/A
C129: ACORDO | D129: ARISTIDES FAGUNDES - 06/07 (vcto 26/03/21) - sem falta já prorrogado em agosto | E129: 44501 | F129: 1350 | G129: Empresa 2 | H129: =VLOOKUP(E129,$E$2698:$H$3009,4,FALSE) -> #N/A
C130: ACORDO | D130: SAMUEL - CIFERAL - 09/09 - vcto 05/10 | E130: 44501 | F130: 1500 | G130: Empresa 2 | H130: =VLOOKUP(E130,$E$2698:$H$3009,4,FALSE) -> #N/A
C131: ACORDO | D131: IZAAC - EMAIL JOEL - 05/06 - vcto 10/01/21 - não aceita mais renegociar | E131: 44501 | F131: 1643 | G131: Empresa 2 | H131: =VLOOKUP(E131,$E$2698:$H$3009,4,FALSE) -> #N/A
C132: SALARIOS | D132: BONUS (Librelato) | E132: 44501 | F132: 500 | G132: Empresa 2 | H132: =VLOOKUP(E132,$E$2698:$H$3009,4,FALSE) -> #N/A
C133: ALIMENTACAO | D133: BAR E REST TIO JOAO - vcto 18/10/21 | E133: 44501 | F133: 3241 | G133: Empresa 2 | H133: =VLOOKUP(E133,$E$2698:$H$3009,4,FALSE) -> #N/A
...

Sheet Fluxo_10_21
B1: =IF(B5=1,"Domingo",IF(B5=2,"Segunda",IF(B5=3,"Terça",IF(B5=4,"Quarta",IF(B5=5,"Quinta",IF(B5=6,"Sexta",IF(B5=7,"Sábado",0))))))) -> Sexta | C1: =IF(C5=1,"Domingo",IF(C5=2,"Segunda",IF(C5=3,"Terça",IF(C5=4,"Quarta",IF(C5=5,"Quinta",IF(C5=6,"Sexta",IF(C5=7,"Sábado",0))))))) -> Segunda | D1: =IF(D5=1,"Domingo",IF(D5=2,"Segunda",IF(D5=3,"Terça",IF(D5=4,"Quarta",IF(D5=5,"Quinta",IF(D5=6,"Sexta",IF(D5=7,"Sábado",0))))))) -> Terça | E1: =IF(E5=1,"Domingo",IF(E5=2,"Segunda",IF(E5=3,"Terça",IF(E5=4,"Quarta",IF(E5=5,"Quinta",IF(E5=6,"Sexta",IF(E5=7,"Sábado",0))))))) -> Quarta | F1: =IF(F5=1,"Domingo",IF(F5=2,"Segunda",IF(F5=3,"Terça",IF(F5=4,"Quarta",IF(F5=5,"Quinta",IF(F5=6,"Sexta",IF(F5=7,"Sábado",0))))))) -> Quinta | G1: =IF(G5=1,"Domingo",IF(G5=2,"Segunda",IF(G5=3,"Terça",IF(G5=4,"Quarta",IF(G5=5,"Quinta",IF(G5=6,"Sexta",IF(G5=7,"Sábado",0))))))) -> Sexta | H1: =IF(H5=1,"Domingo",IF(H5=2,"Segunda",IF(H5=3,"Terça",IF(H5=4,"Quarta",IF(H5=5,"Quinta",IF(H5=6,"Sexta",IF(H5=7,"Sábado",0))))))) -> Segunda | I1: =IF(I5=1,"Domingo",IF(I5=2,"Segunda",IF(I5=3,"Terça",IF(I5=4,"Quarta",IF(I5=5,"Quinta",IF(I5=6,"Sexta",IF(I5=7,"Sábado",0))))))) -> Terça | ... V1: =IF(V5=1,"Domingo",IF(V5=2,"Segunda",IF(V5=3,"Terça",IF(V5=4,"Quarta",IF(V5=5,"Quinta",IF(V5=6,"Sexta",IF(V5=7,"Sábado",0))))))) -> Sexta
A2: Localizado no banco | B2: =B29 -> 44470 | C2: =C29 -> 44473 | D2: =D29 -> 44474 | E2: =E29 -> 44475 | F2: =F29 -> 44476 | G2: =G29 -> 44477 | H2: =H29 -> 44480 | I2: =I29 -> 44481 | ... V2: =V29 -> 44498
A4: SALDO INICIAL | B4: =Fluxo_09_21!W38 -> -19248.832 | C4: =B38 -> -1729.892 | D4: =C38 -> -4625.792 | E4: =D38 -> -5299.552 | F4: =E38 -> -21425.812 | G4: =F38 -> -21369.282 | H4: =G38 -> -21931.592 | I4: =H38 -> 11806.548 | J4: =I38 -> 11806.548 | ... V4: =U38 -> -13130.702
B5: =WEEKDAY(B2) -> 6 | C5: =WEEKDAY(C2) -> 2 | D5: =WEEKDAY(D2) -> 3 | E5: =WEEKDAY(E2) -> 4 | F5: =WEEKDAY(F2) -> 5 | G5: =WEEKDAY(G2) -> 6 | H5: =WEEKDAY(H2) -> 2 | I5: =WEEKDAY(I2) -> 3 | ... V5: =WEEKDAY(V2) -> 6
A6: RECEBIMENTOS (OPERAÇÃO) | B6: =SUM(B7:B26) -> 26005.56 | C6: =SUM(C7:C26) -> 1957.97 | D6: =SUM(D7:D26) -> 0 | E6: =SUM(E7:E26) -> 43000 | F6: =SUM(F7:F26) -> 4220.81 | G6: =SUM(G7:G26) -> 14936.25 | H6: =SUM(H7:H26) -> 35146.14 | I6: =SUM(I7:I26) -> 0 | ... V6: =SUM(V7:V26) -> 9111
A7: MARCOPOLO/SEMAN | B7: =2254.02+9664.2+11747.84-370.5 -> 23295.56 | C7: =1957.97 -> 1957.97 | G7: 5215.35 | H7: =24319.05 -> 24319.05 | R7: 13063.05 | V7: =9681-570 -> 9111
A8: MARCOPOLO | G8: 9720.9
A9: VOLARE | H9: =3300+1583 -> 4883 | P9: 1736 | R9: 45058
A10: HIDROVER | J10: =7338.24+1834.56 -> 9172.8 | R10: 2800
A11: WSUL
A12: RUGERI | B12: 2710 | J12: 2878.38
A13: CIFERAL
A14: SAN MARINO | F14: 4220.81 | H14: 5944.09 | R14: 6416.88
A15: LIBRELATO | J15: =2258.82+3822.62+5903.14+6693.45+2258.14+6050.14 -> 26986.31 | T15: 14588.44
A16: FLORENSE | J16: 4789.85
A17: OLIMPIA | E17: 43000 | J17: -43000 | L17: 4000 | O17: 10010 | Q17: 20000
A18: RENOVAR | N18: 1500 | U18: 3200
A27: PAGAMENTOS PROGRAMADOS
A28: Soma de Valor | B28: Pagto.
A29: tipo | B29: 44470 | C29: 44473 | D29: 44474 | E29: 44475 | F29: 44476 | G29: 44477 | H29: 44480 | I29: 44481 | J29: 44482 | K29: 44483 | L29: 44484 | M29: 44487 | N29: 44488 | O29: 44489 | P29: 44490 | Q29: 44491 | R29: 44494 | S29: 44495 | T29: 44496 | U29: 44497 | V29: 44498 | W29: Total Geral
A30: PARTICULAR | B30: 1000 | C30: 2046.92 | E30: 2032.81 | G30: 246.8 | L30: 415.09 | M30: 2505 | O30: 84.73 | R30: 300 | V30: 1020.5 | W30: 9651.85
A31: VENTURE | B31: 7275.69 | F31: 783.61 | J31: 4906.89 | O31: 2597.36 | P31: 2010 | Q31: 265.57 | R31: 36629.35 | V31: 1291.59 | W31: 55760.06
A32: PKS | Q32: 91.05 | W32: 91.05
A33: SEMAN | B33: 210.93 | C33: 2806.95 | D33: 673.76 | E33: 57093.45 | F33: 3380.67 | G33: 15251.76 | H33: 1408 | I33: 0 | J33: 23315.24 | K33: 5705.9 | L33: 1664.83 | M33: 1057.95 | N33: 1422.75 | O33: 6173.14 | P33: 943.41 | Q33: 17905.71 | R33: 18500.59 | S33: 1642.4 | T33: 0 | U33: 20000 | V33: 10730.39 | W33: 189887.83
A34: Total Geral | B34: 8486.62 | C34: 4853.87 | D34: 673.76 | E34: 59126.26 | F34: 4164.28 | G34: 15498.56 | H34: 1408 | I34: 0 | J34: 28222.13 | K34: 5705.9 | L34: 2079.92 | M34: 3562.95 | N34: 1422.75 | O34: 8855.23 | P34: 2953.41 | Q34: 18262.33 | R34: 55429.94 | S34: 1642.4 | T34: 0 | U34: 20000 | V34: 13042.48 | W34: 255390.79
A38: SALDO FINAL | B38: =B4+B6-GETPIVOTDATA("Valor",$A$28,"Pagto.",DATE(2021,10,1)) -> -1729.892 | C38: =C4+C6-GETPIVOTDATA("Valor",$A$28,"Pagto.",DATE(2021,10,4)) -> -4625.792 | D38: =D4+D6-GETPIVOTDATA("Valor",$A$28,"Pagto.",DATE(2021,10,5)) -> -5299.552 | E38: =E4+E6-GETPIVOTDATA("Valor",$A$28,"Pagto.",DATE(2021,10,6)) -> -21425.812 | F38: =F4+F6-GETPIVOTDATA("Valor",$A$28,"Pagto.",DATE(2021,10,7)) -> -21369.282 | G38: =G4+G6-GETPIVOTDATA("Valor",$A$28,"Pagto.",DATE(2021,10,8)) -> -21931.592 | H38: =H4+H6-GETPIVOTDATA("Valor",$A$28,"Pagto.",DATE(2021,10,11)) -> 11806.548 | I38: =I4+I6-GETPIVOTDATA("Valor",$A$28,"Pagto.",DATE(2021,10,12)) -> 11806.548 | J38: =J4+J6-GETPIVOTDATA("Valor",$A$28,"Pagto.",DATE(2021,10,13)) -> -15588.242 | K38: =K4+K6-GETPIVOTDATA("Valor",$A$28,"Pagto.",DATE(2021,10,14)) -> -21294.142 | L38: =L4+L6-GETPIVOTDATA("Valor",$A$28,"Pagto.",DATE(2021,10,15)) -> -19374.062 | M38: =M4+M6-GETPIVOTDATA("Valor",$A$28,"Pagto.",DATE(2021,10,18)) -> -22937.012 | N38: =N4+N6-GETPIVOTDATA("Valor",$A$28,"Pagto.",DATE(2021,10,19)) -> -22859.762 | O38: =O4+O6-GETPIVOTDATA("Valor",$A$28,"Pagto.",DATE(2021,10,20)) -> -21704.992 | P38: =P4+P6-GETPIVOTDATA("Valor",$A$28,"Pagto.",DATE(2021,10,21)) -> -22922.402 | Q38: =Q4+Q6-GETPIVOTDATA("Valor",$A$28,"Pagto.",DATE(2021,10,22)) -> -21184.732 | R38: =R4+R6-GETPIVOTDATA("Valor",$A$28,"Pagto.",DATE(2021,10,25)) -> -9276.742 | S38: =S4+S6-GETPIVOTDATA("Valor",$A$28,"Pagto.",DATE(2021,10,26)) -> -10919.142 | T38: =T4+T6-GETPIVOTDATA("Valor",$A$28,"Pagto.",DATE(2021,10,27)) -> 3669.298 | U38: =U4+U6-GETPIVOTDATA("Valor",$A$28,"Pagto.",DATE(2021,10,28)) -> -13130.702 | V38: =V4+V6-GETPIVOTDATA("Valor",$A$28,"Pagto.",DATE(2021,10,29)) -> -17062.182

Sheet 09_21
A1: 0 | B1: tm | C1: CodCli | D1: Nome | E1: dtvcto | F1: Valor | G1: tipo | H1: Pagto.
C2: BANCOS | D2: JUROS E DESP BANCARIAS | E2: 44440 | F2: =2197.64+250+485+200.64 -> 3133.28 | G2: Empresa 1 | H2: =VLOOKUP(E2,$E$2760:$H$2817,4,FALSE) -> 44440
C3: EPI | D3: ZAPA - vcto 17/08 - sem falta - boleto já prorrogado | E3: 44440 | F3: 589.88 | G3: Empresa 2 | H3: =VLOOKUP(E3,$E$2760:$H$2817,4,FALSE) -> 44440
C4: EPI | D4: ZAPA - vcto 19/08 - sem falta - boleto já prorrogado | E4: 44440 | F4: 251.83 | G4: Empresa 2 | H4: =VLOOKUP(E4,$E$2760:$H$2817,4,FALSE) -> 44440
C5: SALARIOS | D5: ARQUIVO - parte | E5: 44440 | F5: =26842+154+578+2000 -> 29574 | G5: Empresa 2 | H5: =VLOOKUP(E5,$E$2760:$H$2817,4,FALSE) -> 44440
C6: RESCISAO | D6: FGTS RESCISORIO ALISSON FRANCISCONI - LIBRELATO | E6: 44440 | F6: 26.82 | G6: Empresa 2 | H6: =VLOOKUP(E6,$E$2760:$H$2817,4,FALSE) -> 44440
C7: ALIMENTACAO | D7: ZAPAROLI - vcto 30/08 - parcelado em 3 vezes (01/03) | E7: 44440 | F7: 2000 | G7: Empresa 2 | H7: =VLOOKUP(E7,$E$2760:$H$2817,4,FALSE) -> 44440
C8: COMBUSTIVEL | D8: UNO FLAVIO | E8: 44441 | F8: 50 | G8: Empresa 2 | H8: =VLOOKUP(E8,$E$2760:$H$2817,4,FALSE) -> 44441
C9: COMBUSTIVEL | D9: UNO CLEBER | E9: 44441 | F9: 50 | G9: Empresa 2 | H9: =VLOOKUP(E9,$E$2760:$H$2817,4,FALSE) -> 44441
C10: MATERIAL | D10: PERINI | E10: 44441 | F10: 92 | G10: Empresa 2 | H10: =VLOOKUP(E10,$E$2760:$H$2817,4,FALSE) -> 44441
C11: SALARIOS | D11: ARQUIVO - parte | E11: 44441 | F11: =7939+2110 -> 10049 | G11: Empresa 2 | H11: =VLOOKUP(E11,$E$2760:$H$2817,4,FALSE) -> 44441
C12: EPI | D12: CORSUL | E12: 44441 | F12: 97.2 | G12: Empresa 2 | H12: =VLOOKUP(E12,$E$2760:$H$2817,4,FALSE) -> 44441
C13: SOCIOS | D13: VIVO - LUIS - vcto 26/08 | E13: 44442 | F13: 80.99 | G13: Distribuição de Lucros | H13: =VLOOKUP(E13,$E$2760:$H$2817,4,FALSE) -> 44442
C14: VIAGEM | D14: JOEL - CAIXINHA | E14: 44442 | F14: 3000 | G14: Empresa 2 | H14: =VLOOKUP(E14,$E$2760:$H$2817,4,FALSE) -> 44442
C15: VIAGEM | D15: FLAVIO | E15: 44442 | F15: 415 | G15: Empresa 2 | H15: =VLOOKUP(E15,$E$2760:$H$2817,4,FALSE) -> 44442
C16: COMBUSTIVEL | D16: CLEBER | E16: 44442 | F16: 150 | G16: Empresa 2 | H16: =VLOOKUP(E16,$E$2760:$H$2817,4,FALSE) -> 44442
C17: SOCIOS | D17: LUIS b | E17: 44442 | F17: 1000 | G17: Distribuição de Lucros | H17: =VLOOKUP(E17,$E$2760:$H$2817,4,FALSE) -> 44442
C18: SALARIOS | D18: SALARIOS - ARQUIVO | E18: 44442 | F18: =13092-2110 -> 10982 | G18: Empresa 2 | H18: =VLOOKUP(E18,$E$2760:$H$2817,4,FALSE) -> 44442
C19: EMPRESTIMO | D19: MONEO - parte | E19: 44442 | F19: 3000 | G19: Empresa 2 | H19: =VLOOKUP(E19,$E$2760:$H$2817,4,FALSE) -> 44442
C20: TRANSPORTE | D20: VAN - saldo - pagar em cheque | E20: 44442 | F20: =3863.5+1863.5-1000 -> 4727 | G20: Empresa 2 | H20: =VLOOKUP(E20,$E$2760:$H$2817,4,FALSE) -> 44442
C21: PARCELAMENTO | D21: EMPRESTIMO FOLHA BB - 09/30 e 10/30 | E21: 44443 | F21: 4465.85 | G21: Empresa 2 | H21: =VLOOKUP(E21,$E$2760:$H$2817,4,FALSE) -> 44445
C22: ENCARGOS | D22: FGTS (combinado com Geise, não atrasar) | E22: 44445 | F22: 793.15 | G22: Empresa 1 | H22: =VLOOKUP(E22,$E$2760:$H$2817,4,FALSE) -> 44445
C23: SALARIOS | D23: GEAN e IGOR (VOLARE) | E23: 44445 | F23: =2222+2848 -> 5070 | G23: Empresa 2 | H23: =VLOOKUP(E23,$E$2760:$H$2817,4,FALSE) -> 44445
C24: FÉRIAS | D24: ADRIANA DA d - vcto 17/08 (saldo) | E24: 44446 | F24: 594 | G24: Empresa 2 | H24: =VLOOKUP(E24,$E$2760:$H$2817,4,FALSE) -> 44446
C25: FÉRIAS | D25: RUTIELI VIEIRA - vcto 30/07 | E25: 44447 | F25: 1032 | G25: Empresa 2 | H25: =VLOOKUP(E25,$E$2760:$H$2817,4,FALSE) -> 44447
C26: COMUNICACAO | D26: NET - vcto 20/08 (corte em 13/09) | E26: 44448 | F26: 215.85 | G26: Empresa 2 | H26: =VLOOKUP(E26,$E$2760:$H$2817,4,FALSE) -> 44448
C27: FÉRIAS | D27: KARINE BARBIERI - vcto 26/08 | E27: 44448 | F27: 843 | G27: Empresa 2 | H27: =VLOOKUP(E27,$E$2760:$H$2817,4,FALSE) -> 44448
C28: RESCISAO | D28: INGRIDI MACIEL DOS SANTOS | E28: 44448 | F28: 262.59 | G28: Empresa 2 | H28: =VLOOKUP(E28,$E$2760:$H$2817,4,FALSE) -> 44448
C29: SALARIOS | D29: SALARIOS - VOLARE | E29: 44448 | F29: 10835 | G29: Empresa 2 | H29: =VLOOKUP(E29,$E$2760:$H$2817,4,FALSE) -> 44448
C30: SALARIOS | D30: SALARIOS - secretaria Joel | E30: 44448 | F30: 928 | G30: Empresa 2 | H30: =VLOOKUP(E30,$E$2760:$H$2817,4,FALSE) -> 44448
C31: SALARIOS | D31: SALARIOS - CHEQUES | E31: 44448 | F31: =692+441+630 -> 1763 | G31: Empresa 2 | H31: =VLOOKUP(E31,$E$2760:$H$2817,4,FALSE) -> 44448
C32: INFORMATICA | D32: INFOCALL - vcto 10/08 | E32: 44449 | F32: 200 | G32: Empresa 1 | H32: =VLOOKUP(E32,$E$2760:$H$2817,4,FALSE) -> 44449
C33: VIAGEM | D33: FLAVIO | E33: 44449 | F33: 400 | G33: Empresa 2 | H33: =VLOOKUP(E33,$E$2760:$H$2817,4,FALSE) -> 44449
C34: RESCISAO | D34: RAFAEL SCARSI - FGTS RESCISORIO | E34: 44449 | F34: 9.25 | G34: Empresa 2 | H34: =VLOOKUP(E34,$E$2760:$H$2817,4,FALSE) -> 44449
C35: COMBUSTIVEL | D35: REEMBOLSAR RUBENS c (julho/agosto) | E35: 44449 | F35: 400 | G35: Distribuição de Lucros | H35: =VLOOKUP(E35,$E$2760:$H$2817,4,FALSE) -> 44449
C36: SALARIOS | D36: ADMIN - PARCIAL | E36: 44449 | F36: =1000+2673+2114+1000+1444+1000+1000+2000 -> 12231 | G36: Empresa 2 | H36: =VLOOKUP(E36,$E$2760:$H$2817,4,FALSE) -> 44449
C37: EPI | D37: JUSTINA - vcto 29/08 | E37: 44449 | F37: 900 | G37: Empresa 2 | H37: =VLOOKUP(E37,$E$2760:$H$2817,4,FALSE) -> 44449
C38: RESCISAO | D38: TIAGO DA d - Joel (vcto 18/08) | E38: 44449 | F38: =1555.98 -> 1555.98 | G38: Empresa 2 | H38: =VLOOKUP(E38,$E$2760:$H$2817,4,FALSE) -> 44449
C39: VIAGEM | D39: JOEL - CIFERAL | E39: 44449 | F39: 3000 | G39: Empresa 2 | H39: =VLOOKUP(E39,$E$2760:$H$2817,4,FALSE) -> 44449
C40: EXPEDIENTE | D40: LICEIS SUPRIMENTOS - vcto 26/08 | E40: 44449 | F40: 248.71 | G40: Empresa 2 | H40: =VLOOKUP(E40,$E$2760:$H$2817,4,FALSE) -> 44449
C41: ALIMENTACAO | D41: BOM TEMPERO - VOLARE - 02/02 (vcto 26/08) | E41: 44449 | F41: 742.51 | G41: Empresa 2 | H41: =VLOOKUP(E41,$E$2760:$H$2817,4,FALSE) -> 44449
C42: ALIMENTACAO | D42: ZAPAROLI - vcto 30/08 - parcelado em 3 vezes (02/03) | E42: 44449 | F42: 3120 | G42: Empresa 2 | H42: =VLOOKUP(E42,$E$2760:$H$2817,4,FALSE) -> 44449
C43: TERCEIROS | D43: GT3 - vcto 20/08 - prazo maximo (Iracema) | E43: 44449 | F43: 853.65 | G43: Empresa 2 | H43: =VLOOKUP(E43,$E$2760:$H$2817,4,FALSE) -> 44449
C44: EPI | D44: M JU - UNIFORMES JOEL - 01/02 | E44: 44449 | F44: 495.25 | G44: Empresa 2 | H44: =VLOOKUP(E44,$E$2760:$H$2817,4,FALSE) -> 44449
C45: ASSESSORIA | D45: VISAO - 01/02 - PESQUISA IBGE | E45: 44449 | F45: 100 | G45: Empresa 2 | H45: =VLOOKUP(E45,$E$2760:$H$2817,4,FALSE) -> 44449
C46: FÉRIAS | D46: LIRANE - 02/03 | E46: 44449 | F46: 1380 | G46: Empresa 2 | H46: =VLOOKUP(E46,$E$2760:$H$2817,4,FALSE) -> 44449
C47: COMUNICACAO | D47: CLARO - vcto 20/08 (corte em 13/09) | E47: 44449 | F47: =1283.16+54.76+189.41 -> 1527.33 | G47: Empresa 1 | H47: =VLOOKUP(E47,$E$2760:$H$2817,4,FALSE) -> 44449
C48: SALARIOS | D48: PENSAO ALIMENTICIA | E48: 44449 | F48: =740.56+750.11+693.64 -> 2184.31 | G48: Empresa 2 | H48: =VLOOKUP(E48,$E$2760:$H$2817,4,FALSE) -> 44449
C49: EPI | D49: FERRAGEM IMPERIO - vcto 04/09 | E49: 44449 | F49: 728.94 | G49: Empresa 2 | H49: =VLOOKUP(E49,$E$2760:$H$2817,4,FALSE) -> 44449
C50: TERCEIROS | D50: MARCIA - LIMPEZA - DUAS Empresa 2AS | E50: 44450 | F50: 140 | G50: Empresa 2 | H50: =VLOOKUP(E50,$E$2760:$H$2817,4,FALSE) -> 44452
C51: SEGURO | D51: OUTLANDER - LUIS - 02/07 - ultimo vcto 13/09 | E51: 44451 | F51: 404.34 | G51: Distribuição de Lucros | H51: =VLOOKUP(E51,$E$2760:$H$2817,4,FALSE) -> 44452
C52: ASSESSORIA | D52: LAVOROLAB - vcto 10/09 | E52: 44452 | F52: 892.29 | G52: Empresa 2 | H52: =VLOOKUP(E52,$E$2760:$H$2817,4,FALSE) -> 44452
C53: SOCIOS | D53: LUIS b | E53: 44452 | F53: 200 | G53: Distribuição de Lucros | H53: =VLOOKUP(E53,$E$2760:$H$2817,4,FALSE) -> 44452
C54: SALARIOS | D54: SALARIOS - CHEQUES | E54: 44452 | F54: =498+629+518+434+630 -> 2709 | G54: Empresa 2 | H54: =VLOOKUP(E54,$E$2760:$H$2817,4,FALSE) -> 44452
C55: RESCISAO | D55: FGTS RESCISORIO | E55: 44452 | F55: 14.18 | G55: Empresa 2 | H55: =VLOOKUP(E55,$E$2760:$H$2817,4,FALSE) -> 44452
C56: PARCELAMENTO | D56: IRPJ - vcto 31/08 | E56: 44452 | F56: 622.42 | G56: Empresa 2 | H56: =VLOOKUP(E56,$E$2760:$H$2817,4,FALSE) -> 44452
C57: PARCELAMENTO | D57: INSS - vcto 31/08 | E57: 44452 | F57: 1284.04 | G57: Empresa 2 | H57: =VLOOKUP(E57,$E$2760:$H$2817,4,FALSE) -> 44452
C58: PARCELAMENTO | D58: ENTRADA PGFN | E58: 44452 | F58: 522.01 | G58: Empresa 2 | H58: =VLOOKUP(E58,$E$2760:$H$2817,4,FALSE) -> 44452
C59: RESCISAO | D59: WATSON SAINTILUS | E59: 44452 | F59: 302.46 | G59: Empresa 2 | H59: =VLOOKUP(E59,$E$2760:$H$2817,4,FALSE) -> 44452
C60: EPI | D60: MAJUSEG - vcto 03/09 - já prorrogado | E60: 44452 | F60: 440.74 | G60: Empresa 2 | H60: =VLOOKUP(E60,$E$2760:$H$2817,4,FALSE) -> 44452
C61: EPI | D61: M JU - vcto 03/09 - já prorrogado | E61: 44452 | F61: 145 | G61: Empresa 2 | H61: =VLOOKUP(E61,$E$2760:$H$2817,4,FALSE) -> 44452
C62: PARCELAMENTO | D62: SIMPLES - 01/60 | E62: 44452 | F62: 176189.58 | G62: Empresa 2 | H62: =VLOOKUP(E62,$E$2760:$H$2817,4,FALSE) -> 44452
C63: RESCISAO | D63: ROGER VENANCIO - LIBRELATO | E63: 44452 | F63: 96.86 | G63: Empresa 2 | H63: =VLOOKUP(E63,$E$2760:$H$2817,4,FALSE) -> 44452
C64: VIAGEM | D64: MARCIO - despesas | E64: 44453 | F64: 523 | G64: Empresa 2 | H64: =VLOOKUP(E64,$E$2760:$H$2817,4,FALSE) -> 44453
C65: FÉRIAS | D65: PAOLA GOMES CAMINHA - vcto 09/09/21 - parte | E65: 44453 | F65: 400 | G65: Empresa 2 | H65: =VLOOKUP(E65,$E$2760:$H$2817,4,FALSE) -> 44453
C66: SOCIOS | D66: RUBENS c - reembolso juros cheque especial | E66: 44453 | F66: 460 | G66: Distribuição de Lucros | H66: =VLOOKUP(E66,$E$2760:$H$2817,4,FALSE) -> 44453
... C76: SAUDE | D76: PROMED | E76: 44454 | F76: 92.25 | G76: Empresa 1 | H76: =VLOOKUP(E76,$E$2760:$H$2817,4,FALSE) -> 44454
C77: SALARIOS | D77: FLAVIO/CLEBER/NELCI/FABIANA- saldo final | E77: 44454 | F77: =2263+3505+1232+3366 -> 10366 | G77: Empresa 2 | H77: =VLOOKUP(E77,$E$2760:$H$2817,4,FALSE) -> 44454
C78: SALARIOS | D78: JOEL - parte | E78: 44454 | F78: 2000 | G78: Empresa 2 | H78: =VLOOKUP(E78,$E$2760:$H$2817,4,FALSE) -> 44454
C79: SALARIOS | D79: PAULO EDUARDO + reembolso NF Polimeros Sul - almocos paulo e ester | E79: 44454 | F79: =2800+10.5-200 -> 2610.5 | G79: Empresa 2 | H79: =VLOOKUP(E79,$E$2760:$H$2817,4,FALSE) -> 44454
C80: RESCISAO | D80: ZAGALO LORMOND | E80: 44454 | F80: 273.952 | G80: Empresa 2 | H80: =VLOOKUP(E80,$E$2760:$H$2817,4,FALSE) -> 44454
C81: COMBUSTIVEL | D81: ROGERIO | E81: 44454 | F81: 370 | G81: Distribuição de Lucros | H81: =VLOOKUP(E81,$E$2760:$H$2817,4,FALSE) -> 44454
C82: PARCELAMENTO | D82: VISAO - PARCELAMENTO | E82: 44454 | F82: 1100 | G82: Empresa 2 | H82: =VLOOKUP(E82,$E$2760:$H$2817,4,FALSE) -> 44454
C83: ENCARGOS | D83: INSS | E83: 44454 | F83: 624.19 | G83: Empresa 1 | H83: =VLOOKUP(E83,$E$2760:$H$2817,4,FALSE) -> 44454
C84: ALIMENTACAO | D84: BISTRO LUCAS RAMOS - vcto 02/09 - já prorrogado | E84: 44454 | F84: 2322 | G84: Empresa 1 | H84: =VLOOKUP(E84,$E$2760:$H$2817,4,FALSE) -> 44454
C85: ENCARGOS | D85: TAXA CERTIDAO JUNTA COML - WEG | E85: 44454 | F85: 51.78 | G85: Empresa 2 | H85: =VLOOKUP(E85,$E$2760:$H$2817,4,FALSE) -> 44454
C86: RESCISAO | D86: ALISSON FRANCISCONI - LIBRELATO - 25/08 | E86: 44454 | F86: 331.43 | G86: Empresa 2 | H86: =VLOOKUP(E86,$E$2760:$H$2817,4,FALSE) -> 44454
C87: SALARIOS | D87: SALARIOS - CHEQUES | E87: 44454 | F87: =196+448+484 -> 1128 | G87: Empresa 2 | H87: =VLOOKUP(E87,$E$2760:$H$2817,4,FALSE) -> 44454
C88: AGUA | D88: SAMAE | E88: 44455 | F88: 81.99 | G88: Empresa 1 | H88: =VLOOKUP(E88,$E$2760:$H$2817,4,FALSE) -> 44455
C89: COMBUSTIVEL | D89: PAULO EDUARDO | E89: 44456 | F89: 50 | G89: Empresa 2 | H89: =VLOOKUP(E89,$E$2760:$H$2817,4,FALSE) -> 44456
C90: VIAGEM | D90: FLAVIO | E90: 44456 | F90: 400 | G90: Empresa 2 | H90: =VLOOKUP(E90,$E$2760:$H$2817,4,FALSE) -> 44456
C91: EMPRESTIMO | D91: VERA KARLING - 12/17 | E91: 44456 | F91: 1750 | G91: Empresa 1 | H91: =VLOOKUP(E91,$E$2760:$H$2817,4,FALSE) -> 44456
C92: SOCIOS | D92: RETIRADA LUIS b | E92: 44456 | F92: 600 | G92: Distribuição de Lucros | H92: =VLOOKUP(E92,$E$2760:$H$2817,4,FALSE) -> 44456
C93: TRANSPORTE | D93: VISATE - 10 CARTOES | E93: 44456 | F93: 190 | G93: Empresa 2 | H93: =VLOOKUP(E93,$E$2760:$H$2817,4,FALSE) -> 44456
C94: ALUGUEL | D94: ALUGAMAQ - vcto 12/07 | E94: 44456 | F94: =130 -> 130 | G94: Empresa 1 | H94: =VLOOKUP(E94,$E$2760:$H$2817,4,FALSE) -> 44456
C95: TERCEIROS | D95: HOLUS - vcto 20/08 | E95: 44456 | F95: 244.2 | G95: Empresa 1 | H95: =VLOOKUP(E95,$E$2760:$H$2817,4,FALSE) -> 44456
C96: VIAGEM | D96: VOB HOTEL - vcto 09/09 - já prorrogado | E96: 44456 | F96: 460 | G96: Empresa 2 | H96: =VLOOKUP(E96,$E$2760:$H$2817,4,FALSE) -> 44456
C97: IMPOSTOS | D97: DARF RETENCAO NF | E97: 44456 | F97: =142.95+46.12 -> 189.07 | G97: Empresa 2 | H97: =VLOOKUP(E97,$E$2760:$H$2817,4,FALSE) -> 44456
C98: SALARIOS | D98: SALARIOS - CHEQUES | E98: 44456 | F98: =699+609 -> 1308 | G98: Empresa 2 | H98: =VLOOKUP(E98,$E$2760:$H$2817,4,FALSE) -> 44456
C99: ALIMENTACAO | D99: ZAPAROLI - vcto 30/08 - parcelado em 3vezes (03/03) | E99: 44456 | F99: 3120 | G99: Empresa 2 | H99: =VLOOKUP(E99,$E$2760:$H$2817,4,FALSE) -> 44456
C100: SOCIOS | D100: RETIRADA ROGERIO | E100: 44456 | F100: 1000 | G100: Distribuição de Lucros | H100: =VLOOKUP(E100,$E$2760:$H$2817,4,FALSE) -> 44456
C101: SOCIOS | D101: RETIRADA PAULO d - cartao | E101: 44456 | F101: 2500 | G101: Distribuição de Lucros | H101: =VLOOKUP(E101,$E$2760:$H$2817,4,FALSE) -> 44456
C102: EPI | D102: JUSTINA - vcto 06/09 - já prorrogado | E102: 44456 | F102: 787.5 | G102: Empresa 2 | H102: =VLOOKUP(E102,$E$2760:$H$2817,4,FALSE) -> 44456
C103: SALARIOS | D103: GABRIEL - combinado com ele | E103: 44456 | F103: 5037 | G103: Empresa 2 | H103: =VLOOKUP(E103,$E$2760:$H$2817,4,FALSE) -> 44456
C104: SALARIOS | D104: EXTRAS VOLARE - agosto - metade | E104: 44456 | F104: 5166 | G104: Empresa 2 | H104: =VLOOKUP(E104,$E$2760:$H$2817,4,FALSE) -> 44456
C105: TRANSPORTE | D105: VAN -01/04 | E105: 44456 | F105: 1000 | G105: Empresa 2 | H105: =VLOOKUP(E105,$E$2760:$H$2817,4,FALSE) -> 44456
E106: 44457 | F106: 0 | G106: Empresa 2 | H106: =VLOOKUP(E106,$E$2760:$H$2817,4,FALSE) -> 44459
E107: 44458 | F107: 0 | G107: Empresa 2 | H107: =VLOOKUP(E107,$E$2760:$H$2817,4,FALSE) -> 44459
E108: 44459 | F108: 0 | G108: Empresa 2 | H108: =VLOOKUP(E108,$E$2760:$H$2817,4,FALSE) -> 44459
C109: VIAGEM | D109: VOB HOTEL - vcto 17/09 - já prorrogado | E109: 44460 | F109: 664 | G109: Empresa 2 | H109: =VLOOKUP(E109,$E$2760:$H$2817,4,FALSE) -> 44460
...

Sheet Fluxo_09_21
B1: =IF(B5=1,"Domingo",IF(B5=2,"Segunda",IF(B5=3,"Terça",IF(B5=4,"Quarta",IF(B5=5,"Quinta",IF(B5=6,"Sexta",IF(B5=7,"Sábado",0))))))) -> Quarta | C1: =IF(C5=1,"Domingo",IF(C5=2,"Segunda",IF(C5=3,"Terça",IF(C5=4,"Quarta",IF(C5=5,"Quinta",IF(C5=6,"Sexta",IF(C5=7,"Sábado",0))))))) -> Quinta | D1: =IF(D5=1,"Domingo",IF(D5=2,"Segunda",IF(D5=3,"Terça",IF(D5=4,"Quarta",IF(D5=5,"Quinta",IF(D5=6,"Sexta",IF(D5=7,"Sábado",0))))))) -> Sexta | E1: =IF(E5=1,"Domingo",IF(E5=2,"Segunda",IF(E5=3,"Terça",IF(E5=4,"Quarta",IF(E5=5,"Quinta",IF(E5=6,"Sexta",IF(E5=7,"Sábado",0))))))) -> Segunda | F1: =IF(F5=1,"Domingo",IF(F5=2,"Segunda",IF(F5=3,"Terça",IF(F5=4,"Quarta",IF(F5=5,"Quinta",IF(F5=6,"Sexta",IF(F5=7,"Sábado",0))))))) -> Terça | G1: =IF(G5=1,"Domingo",IF(G5=2,"Segunda",IF(G5=3,"Terça",IF(G5=4,"Quarta",IF(G5=5,"Quinta",IF(G5=6,"Sexta",IF(G5=7,"Sábado",0))))))) -> Quarta | H1: =IF(H5=1,"Domingo",IF(H5=2,"Segunda",IF(H5=3,"Terça",IF(H5=4,"Quarta",IF(H5=5,"Quinta",IF(H5=6,"Sexta",IF(H5=7,"Sábado",0))))))) -> Quinta | I1: =IF(I5=1,"Domingo",IF(I5=2,"Segunda",IF(I5=3,"Terça",IF(I5=4,"Quarta",IF(I5=5,"Quinta",IF(I5=6,"Sexta",IF(I5=7,"Sábado",0))))))) -> Sexta | ... W1: =IF(W5=1,"Domingo",IF(W5=2,"Segunda",IF(W5=3,"Terça",IF(W5=4,"Quarta",IF(W5=5,"Quinta",IF(W5=6,"Sexta",IF(W5=7,"Sábado",0))))))) -> Quinta
A2: Localizado no banco | B2: =B29 -> 44440 | C2: =C29 -> 44441 | D2: =D29 -> 44442 | E2: =E29 -> 44445 | F2: =F29 -> 44446 | G2: =G29 -> 44447 | H2: =H29 -> 44448 | I2: =I29 -> 44449 | ... W2: =W29 -> 44469
A4: SALDO INICIAL | B4: =Fluxo_08_21!W38 -> -6812.36 | C4: =B38 -> -11416.67 | D4: =C38 -> -3181.92 | E4: =D38 -> -8217.99 | F4: =E38 -> -18546.99 | G4: =F38 -> -19140.99 | H4: =G38 -> -20172.99 | I4: =H38 -> -10020.43 | J4: =I38 -> -6850.11 | ... W4: =V38 -> -14905.562
B5: =WEEKDAY(B2) -> 4 | C5: =WEEKDAY(C2) -> 5 | D5: =WEEKDAY(D2) -> 6 | E5: =WEEKDAY(E2) -> 2 | F5: =WEEKDAY(F2) -> 3 | G5: =WEEKDAY(G2) -> 4 | H5: =WEEKDAY(H2) -> 5 | I5: =WEEKDAY(I2) -> 6 | ... W5: =WEEKDAY(W2) -> 5
A6: RECEBIMENTOS (OPERAÇÃO) | B6: =SUM(B7:B26) -> 30971.5 | C6: =SUM(C7:C26) -> 18572.95 | D6: =SUM(D7:D26) -> 18318.92 | E6: =SUM(E7:E26) -> 0 | F6: =SUM(F7:F26) -> 0 | G6: =SUM(G7:G26) -> 0 | H6: =SUM(H7:H26) -> 25000 | I6: =SUM(I7:I26) -> 33247.25 | ... W6: =SUM(W7:W26) -> 0
A7: MARCOPOLO/SEMAN | B7: =11747+6318-125.08 -> 17939.92 | C7: 18572.95 | J7: 6526.1
A8: MARCOPOLO | B8: =13031.58 -> 13031.58
A9: VOLARE | D9: 4320.44 | T9: =4300+20200 -> 24500
A10: HIDROVER | L10: =7338.24+1834.56 -> 9172.8
A11: WSUL | I11: 2300
A12: RUGERI
A13: CIFERAL | I13: 30947.25 | N13: 20365.96
A14: SAN MARINO | D14: 9912.48
A15: LIBRELATO | J15: =5485.5+5372.25+6270.64+5372.25+5903.14 -> 28403.78 | T15: =3822.62+3974.81+4473.18+4473.18+6693.45 -> 23437.24
A16: ERZINGER - ES | D16: 1086
A17: CABEÇA | D17: 3000 | H17: =17000+8000 -> 25000 | J17: =130000-17000+35000 -> 148000 | K17: =8000 -> 8000
A18: FLORENSE | L18: =1764+5059.43+1628.39+2327.01 -> 10778.83
A19: RENOVAR | R19: 27000 | S19: 7000 | V19: 30000
A27: PAGAMENTOS PROGRAMADOS
A28: Soma de Valor | B28: Pagto.
A29: tipo | B29: 44440 | C29: 44441 | D29: 44442 | E29: 44445 | F29: 44446 | G29: 44447 | H29: 44448 | I29: 44449 | J29: 44452 | K29: 44453 | L29: 44454 | M29: 44455 | N29: 44456 | O29: 44459 | P29: 44460 | Q29: 44461 | R29: 44462 | S29: 44463 | T29: 44466 | U29: 44467 | V29: 44468 | W29: 44469 | X29: Total Geral
A30: PARTICULAR | D30: 1080.99 | I30: 400 | J30: 604.34 | K30: 460 | L30: 370 | N30: 4100 | T30: 4520 | V30: 2000 | X30: 13535.33
A31: VENTURE | B31: 3133.28 | E31: 793.15 | I31: 1727.33 | K31: 4200 | L31: 3038.44 | M31: 81.99 | N31: 2124.2 | Q31: 177 | R31: 110 | T31: 2925.03 | V31: 5834.71 | X31: 24145.13
A32: SOLUTEC | V32: 1283.09 | X32: 1283.09
A33: PKS | K33: 534.69 | T33: 3710.47 | X33: 4245.16
A34: SEMAN | B34: 32442.53 | C34: 10338.2 | D34: 22274 | E34: 9535.85 | F34: 594 | G34: 1032 | H34: 14847.44 | I34: 27949.6 | J34: 183358.58 | K34: 11259.3 | L34: 17945.662 | N34: 17707.57 | O34: 0 | P34: 664 | Q34: 380 | R34: 27119.32 | S34: 3541.22 | T34: 31955.81 | U34: 6350 | V34: 14884.74 | W34: 4343.27 | X34: 438523.09
A35: Total Geral | B35: 35575.81 | C35: 10338.2 | D35: 23354.99 | E35: 10329 | F35: 594 | G35: 1032 | H35: 14847.44 | I35: 30076.93 | J35: 183962.92 | K35: 16453.99 | L35: 21354.102 | M35: 81.99 | N35: 23931.77 | O35: 0 | P35: 664 | Q35: 557 | R35: 27229.32 | S35: 3541.22 | T35: 43111.31 | U35: 6350 | V35: 24002.54 | W35: 4343.27 | X35: 481731.8
A38: SALDO FINAL | B38: =B4+B6-GETPIVOTDATA("Valor",$A$28,"Pagto.",DATE(2021,9,1)) -> -11416.67 | C38: =C4+C6-GETPIVOTDATA("Valor",$A$28,"Pagto.",DATE(2021,9,2)) -> -3181.92 | D38: =D4+D6-GETPIVOTDATA("Valor",$A$28,"Pagto.",DATE(2021,9,3)) -> -8217.99 | E38: =E4+E6-GETPIVOTDATA("Valor",$A$28,"Pagto.",DATE(2021,9,6)) -> -18546.99 | F38: =F4+F6-GETPIVOTDATA("Valor",$A$28,"Pagto.",DATE(2021,9,7)) -> -19140.99 | G38: =G4+G6-GETPIVOTDATA("Valor",$A$28,"Pagto.",DATE(2021,9,8)) -> -20172.99 | H38: =H4+H6-GETPIVOTDATA("Valor",$A$28,"Pagto.",DATE(2021,9,9)) -> -10020.43 | I38: =I4+I6-GETPIVOTDATA("Valor",$A$28,"Pagto.",DATE(2021,9,10)) -> -6850.11 | J38: =J4+J6-GETPIVOTDATA("Valor",$A$28,"Pagto.",DATE(2021,9,13)) -> -7883.15 | K38: =K4+K6-GETPIVOTDATA("Valor",$A$28,"Pagto.",DATE(2021,9,14)) -> -16337.14 | L38: =L4+L6-GETPIVOTDATA("Valor",$A$28,"Pagto.",DATE(2021,9,15)) -> -17739.612 | M38: =M4+M6-GETPIVOTDATA("Valor",$A$28,"Pagto.",DATE(2021,9,16)) -> -17821.602 | N38: =N4+N6-GETPIVOTDATA("Valor",$A$28,"Pagto.",DATE(2021,9,17)) -> -21387.412 | O38: =O4+O6-GETPIVOTDATA("Valor",$A$28,"Pagto.",DATE(2021,9,20)) -> -21387.412 | P38: =P4+P6-GETPIVOTDATA("Valor",$A$28,"Pagto.",DATE(2021,9,21)) -> -22051.412 | Q38: =Q4+Q6-GETPIVOTDATA("Valor",$A$28,"Pagto.",DATE(2021,9,22)) -> -22608.412 | R38: =R4+R6-GETPIVOTDATA("Valor",$A$28,"Pagto.",DATE(2021,9,23)) -> -22837.732 | S38: =S4+S6-GETPIVOTDATA("Valor",$A$28,"Pagto.",DATE(2021,9,24)) -> -19378.952 | T38: =T4+T6-GETPIVOTDATA("Valor",$A$28,"Pagto.",DATE(2021,9,27)) -> -14553.022 | U38: =U4+U6-GETPIVOTDATA("Valor",$A$28,"Pagto.",DATE(2021,9,28)) -> -20903.022 | V38: =V4+V6-GETPIVOTDATA("Valor",$A$28,"Pagto.",DATE(2021,9,29)) -> -14905.562 | W38: =W4+W6-GETPIVOTDATA("Valor",$A$28,"Pagto.",DATE(2021,9,30)) -> -19248.832

Sheet 08_21
A1: 0 | B1: tm | C1: CodCli | D1: Nome | E1: dtvcto | F1: Valor | G1: tipo | H1: Pagto.
C2: BANCOS | D2: JUROS E DESP BANCARIAS | E2: 44409 | F2: =2821.88+125+950+200+144+200+250+153+150 -> 4993.88 | G2: Empresa 1 | H2: =VLOOKUP(E2,$E$2588:$H$2910,4,FALSE) -> 44410
C3: VIAGEM | D3: VOB HOTEL | E3: 44409 | F3: 456 | G3: Empresa 2 | H3: =VLOOKUP(E3,$E$2588:$H$2910,4,FALSE) -> 44410
C4: COMBUSTIVEL | D4: TEONAS - MENSAL | E4: 44410 | F4: 150 | G4: Empresa 2 | H4: =VLOOKUP(E4,$E$2588:$H$2910,4,FALSE) -> 44410
C5: COMBUSTIVEL | D5: GENILSON - MENSAL | E5: 44410 | F5: 250 | G5: Empresa 2 | H5: =VLOOKUP(E5,$E$2588:$H$2910,4,FALSE) -> 44410
C6: CONSUMO | D6: DE TONI | E6: 44410 | F6: 32 | G6: Empresa 2 | H6: =VLOOKUP(E6,$E$2588:$H$2910,4,FALSE) -> 44410
C7: CONSUMO | D7: TONER FINANCEIRO | E7: 44410 | F7: 52 | G7: Empresa 2 | H7: =VLOOKUP(E7,$E$2588:$H$2910,4,FALSE) -> 44410
C8: TERCEIROS | D8: MARCIA - LIMPEZA | E8: 44411 | F8: 70 | G8: Empresa 2 | H8: =VLOOKUP(E8,$E$2588:$H$2910,4,FALSE) -> 44411
C9: RESCISAO | D9: FGTS RESCISORIO VALTER MUNHOZ | E9: 44411 | F9: 22.3 | G9: Empresa 2 | H9: =VLOOKUP(E9,$E$2588:$H$2910,4,FALSE) -> 44411
C10: CONSUMO | D10: DE TONI | E10: 44411 | F10: 243.67 | G10: Empresa 2 | H10: =VLOOKUP(E10,$E$2588:$H$2910,4,FALSE) -> 44411
C11: SALARIOS | D11: JAQUELINE NASCIMENTO (em dinheiro) | E11: 44411 | F11: 90 | G11: Empresa 2 | H11: =VLOOKUP(E11,$E$2588:$H$2910,4,FALSE) -> 44411
C12: PARCELAMENTO | D12: EMPRESTIMO FOLHA BB - 08/30 | E12: 44412 | F12: 2277.79 | G12: Empresa 2 | H12: =VLOOKUP(E12,$E$2588:$H$2910,4,FALSE) -> 44412
C13: SALARIOS | D13: EDUARDA CRISTINE - Librelato | E13: 44412 | F13: =12255-806-1609-200-1849-1843-429-1266-492-480-620-304-342-717-500-593 -> 205 | G13: Empresa 2 | H13: =VLOOKUP(E13,$E$2588:$H$2910,4,FALSE) -> 44412
C14: RESCISAO | D14: EDUARDA CRISTINE | E14: 44412 | F14: =219.15 -> 219.15 | G14: Empresa 2 | H14: =VLOOKUP(E14,$E$2588:$H$2910,4,FALSE) -> 44412
C15: TRANSPORTE | D15: 10 CARTOES | E15: 44413 | F15: 190 | G15: Empresa 1 | H15: =VLOOKUP(E15,$E$2588:$H$2910,4,FALSE) -> 44413
C16: COMUNICACAO | D16: NET - vcto 20/07 | E16: 44413 | F16: 194.02 | G16: Empresa 2 | H16: =VLOOKUP(E16,$E$2588:$H$2910,4,FALSE) -> 44413
C17: SALARIOS | D17: SALARIOS - ARQUIVO | E17: 44413 | F17: =52272-3607-556 -> 48109 | G17: Empresa 2 | H17: =VLOOKUP(E17,$E$2588:$H$2802,4,FALSE) -> 44413
C18: SALARIOS | D18: SALARIOS - volare (sem conta) | E18: 44413 | F18: 13730 | G18: Empresa 2 | H18: =VLOOKUP(E18,$E$2588:$H$2802,4,FALSE) -> 44413
C19: SALARIOS | D19: RUTIELE VIEIRA | E19: 44413 | F19: 851 | G19: Empresa 2 | H19: =VLOOKUP(E19,$E$2588:$H$2802,4,FALSE) -> 44413
C20: ENCARGOS | D20: FGTS | E20: 44414 | F20: 793.14 | G20: Empresa 1 | H20: =VLOOKUP(E20,$E$2588:$H$2802,4,FALSE) -> 44414
C21: SALARIOS | D21: FABIANE RODRIGUES | E21: 44414 | F21: 611 | G21: Empresa 2 | H21: =VLOOKUP(E21,$E$2588:$H$2802,4,FALSE) -> 44414
C22: PARCELAMENTO | D22: EMPRESTIMO FOLHA BB - 09/30 | E22: 44414 | F22: 2186.46 | G22: Empresa 2 | H22: =VLOOKUP(E22,$E$2588:$H$2802,4,FALSE) -> 44414
C23: COMBUSTIVEL | D23: CLEBER | E23: 44414 | F23: 150 | G23: Empresa 2 | H23: =VLOOKUP(E23,$E$2588:$H$2802,4,FALSE) -> 44414
C24: VIAGEM | D24: FLAVIO | E24: 44414 | F24: 640.73 | G24: Empresa 2 | H24: =VLOOKUP(E24,$E$2588:$H$2802,4,FALSE) -> 44414
C25: EXPEDIENTE | D25: KIPONTO | E25: 44414 | F25: 100 | G25: Empresa 1 | H25: =VLOOKUP(E25,$E$2588:$H$2802,4,FALSE) -> 44414
C26: SALARIOS | D26: GEAN SOARES DA d - VOLARE | E26: 44414 | F26: 2848 | G26: Empresa 2 | H26: =VLOOKUP(E26,$E$2588:$H$2802,4,FALSE) -> 44414
C27: SALARIOS | D27: DIF SALARIO RAFAEL | E27: 44414 | F27: 179 | G27: Empresa 2 | H27: =VLOOKUP(E27,$E$2588:$H$2802,4,FALSE) -> 44414
C28: EPI | D28: MAJUSEG - CHEQUE 08/07 | E28: 44414 | F28: 575.36 | G28: Empresa 2 | H28: =VLOOKUP(E28,$E$2588:$H$2802,4,FALSE) -> 44414
C29: IMPOSTOS | D29: ART ROGERIO MACEDO - ESTUFA marco | E29: 44415 | F29: 88.78 | G29: Empresa 1 | H29: =VLOOKUP(E29,$E$2588:$H$2802,4,FALSE) -> 44417
... C33: EPI | D33: MAJUSEG - vcto 05/08 | E33: 44417 | F33: 784.1 | G33: Empresa 2 | H33: =VLOOKUP(E33,$E$2588:$H$2802,4,FALSE) -> 44417
C34: SALARIOS | D34: SALARIOS - cheques | E34: 44417 | F34: =152+559+1811+564+991 -> 4077 | G34: Empresa 2 | H34: =VLOOKUP(E34,$E$2588:$H$2802,4,FALSE) -> 44417
C35: VIAGEM | D35: JOEL - CAIXINHA (fazer sem falta - troca pelo salario) | E35: 44417 | F35: 3000 | G35: Empresa 2 | H35: =VLOOKUP(E35,$E$2588:$H$2802,4,FALSE) -> 44417
C36: EPI | D36: MAJUSEG - CHEQUE 25/06 | E36: 44417 | F36: 895.48 | G36: Empresa 2 | H36: =VLOOKUP(E36,$E$2588:$H$2802,4,FALSE) -> 44417
C37: ALIMENTACAO | D37: RESTAURANTE ZAPAROLLI - saldo | E37: 44418 | F37: 3025 | G37: Empresa 2 | H37: =VLOOKUP(E37,$E$2588:$H$2802,4,FALSE) -> 44418
C38: ALIMENTACAO | D38: ALIMENTAR - NEOBUS - vcto 07/07 - sem falta, já prorrogado por duas vezes | E38: 44418 | F38: 1860.75 | G38: Empresa 2 | H38: =VLOOKUP(E38,$E$2588:$H$2802,4,FALSE) -> 44418
C39: SALARIOS | D39: SALARIOS - cheques | E39: 44418 | F39: =1300+468+556+152+265+374+525+435+158+333+333 -> 4899 | G39: Empresa 2 | H39: =VLOOKUP(E39,$E$2588:$H$2802,4,FALSE) -> 44418
C40: CURSO | D40: RAFAEL SCOPEL - parte entrada acordo | E40: 44418 | F40: 500 | G40: Empresa 2 | H40: =VLOOKUP(E40,$E$2588:$H$2802,4,FALSE) -> 44418
C41: SALARIOS | D41: CLEBER - parte (em dinheiro) | E41: 44418 | F41: 500 | G41: Empresa 2 | H41: =VLOOKUP(E41,$E$2588:$H$2802,4,FALSE) -> 44418
C42: SALARIOS | D42: GENILSON MENEZES | E42: 44418 | F42: 3607 | G42: Empresa 2 | H42: =VLOOKUP(E42,$E$2588:$H$2802,4,FALSE) -> 44418
C43: SALARIOS | D43: SALARIOS - cheques | E43: 44419 | F43: =167+167+160+601+505 -> 1600 | G43: Empresa 2 | H43: =VLOOKUP(E43,$E$2588:$H$2802,4,FALSE) -> 44419
C44: CONSUMO | D44: LUCHETTI - AGUAS | E44: 44419 | F44: 90 | G44: Empresa 1 | H44: =VLOOKUP(E44,$E$2588:$H$2802,4,FALSE) -> 44419
C45: EPI | D45: ZAPA - vcto 05/08 - já prorrogado | E45: 44420 | F45: 312.34 | G45: Empresa 2 | H45: =VLOOKUP(E45,$E$2588:$H$2802,4,FALSE) -> 44420
C46: FÉRIAS | D46: ERIVELTO (JOEL) - vcto 16/07 - parcela 02/02 | E46: 44420 | F46: 1243 | G46: Empresa 2 | H46: =VLOOKUP(E46,$E$2588:$H$2802,4,FALSE) -> 44420
C47: SALARIOS | D47: SALARIOS - cheques | E47: 44420 | F47: =497+597 -> 1094 | G47: Empresa 2 | H47: =VLOOKUP(E47,$E$2588:$H$2802,4,FALSE) -> 44420
C48: SALARIOS | D48: SALARIOS - supervisores e adm | E48: 44420 | F48: 26932.8 | G48: Empresa 2 | H48: =VLOOKUP(E48,$E$2588:$H$2802,4,FALSE) -> 44420
C49: COMUNICACAO | D49: CLARO - vcto 20/07 (corte em 13/08) | E49: 44420 | F49: =189.22+42.93+1407.45 -> 1639.6 | G49: Empresa 1 | H49: =VLOOKUP(E49,$E$2588:$H$2802,4,FALSE) -> 44420
C50: MANUTENCAO | D50: DIGISERVE - vcto 04/08 - prorrogado | E50: 44420 | F50: 699.3 | G50: Empresa 1 | H50: =VLOOKUP(E50,$E$2588:$H$2802,4,FALSE) -> 44420
C51: SALARIOS | D51: PENSAO ALIMENTICIA (já avisado) | E51: 44420 | F51: =693.63+750.08+736.5 -> 2180.21 | G51: Empresa 2 | H51: =VLOOKUP(E51,$E$2588:$H$2802,4,FALSE) -> 44420
C52: EPI | D52: ZAPA - vcto 09/08 | E52: 44420 | F52: 161.58 | G52: Empresa 2 | H52: =VLOOKUP(E52,$E$2588:$H$2802,4,FALSE) -> 44420
C53: COMBUSTIVEL | D53: CLEBER | E53: 44420 | F53: 150 | G53: Empresa 2 | H53: =VLOOKUP(E53,$E$2588:$H$2802,4,FALSE) -> 44420
C54: VIAGEM | D54: FLAVIO | E54: 44420 | F54: 408.8 | G54: Empresa 2 | H54: =VLOOKUP(E54,$E$2588:$H$2802,4,FALSE) -> 44420
C55: VIAGEM | D55: MARCIO - LIBRELATO (levou em dinheiro) | E55: 44420 | F55: 450 | G55: Empresa 2 | H55: =VLOOKUP(E55,$E$2588:$H$2802,4,FALSE) -> 44420 | I55: 174.64
C56: VIAGEM | D56: MARCIO - LIBRELATO (gastos RIO/CAXIAS) - deposito | E56: 44420 | F56: =465.05+165 -> 630.05 | G56: Empresa 2 | H56: =VLOOKUP(E56,$E$2588:$H$2802,4,FALSE) -> 44420
C57: EPI | D57: MAJUSEG - cheque 16/07 | E57: 44420 | F57: 1129.25 | G57: Empresa 2 | H57: =VLOOKUP(E57,$E$2588:$H$2802,4,FALSE) -> 44420
C58: MANUTENCAO | D58: STEDILE | E58: 44421 | F58: 240.86 | G58: Empresa 2 | H58: =VLOOKUP(E58,$E$2588:$H$2802,4,FALSE) -> 44421
C59: SALARIOS | D59: PAULO EDUARDO + reembolso Fusopar | E59: 44421 | F59: =2800+38.12 -> 2838.12 | G59: Empresa 2 | H59: =VLOOKUP(E59,$E$2588:$H$2802,4,FALSE) -> 44421
C60: SOCIOS | D60: LUIS b | E60: 44421 | F60: 2000 | G60: Distribuição de Lucros | H60: =VLOOKUP(E60,$E$2588:$H$2802,4,FALSE) -> 44421
C61: RESCISAO | D61: MARCIO FERNANDES (depositar na conta do Joel) | E61: 44421 | F61: 727.95 | G61: Empresa 2 | H61: =VLOOKUP(E61,$E$2588:$H$2802,4,FALSE) -> 44421
C62: ACORDO | D62: SAMUEL - CIFERAL - 07/09 - vcto 05/08 | E62: 44421 | F62: 1500 | G62: Empresa 2 | H62: =VLOOKUP(E62,$E$2588:$H$2802,4,FALSE) -> 44421
C63: ACORDO | D63: ARTHUR - CIFERAL - 07/08 - vcto 05/08 | E63: 44421 | F63: 1500 | G63: Empresa 2 | H63: =VLOOKUP(E63,$E$2588:$H$2802,4,FALSE) -> 44421
C64: ACORDO | D64: LEONARDO - CIFERAL - 07/14 - vcto 05/08 | E64: 44421 | F64: 1500 | G64: Empresa 2 | H64: =VLOOKUP(E64,$E$2588:$H$2802,4,FALSE) -> 44421
C65: RECLAMATORIA | D65: GUIA PROCESSO JOSE MELO | E65: 44421 | F65: 911.08 | G65: Empresa 2 | H65: =VLOOKUP(E65,$E$2588:$H$2802,4,FALSE) -> 44421
C66: MATERIAL | D66: PERINI - vcto em 30/07 - prorrogado | E66: 44421 | F66: 564.56 | G66: Empresa 1 | H66: =VLOOKUP(E66,$E$2588:$H$2802,4,FALSE) -> 44421
C67: COMBUSTIVEL | D67: ROGERIO | E67: 44421 | F67: 300 | G67: Distribuição de Lucros | H67: =VLOOKUP(E67,$E$2588:$H$2802,4,FALSE) -> 44421
C68: VIAGEM | D68: LUIS b/GABRIEL | E68: 44421 | F68: 1498.68 | G68: Empresa 2 | H68: =VLOOKUP(E68,$E$2588:$H$2802,4,FALSE) -> 44421
C69: SALARIOS | D69: SALARIOS - cheques | E69: 44421 | F69: =433+769 -> 1202 | G69: Empresa 2 | H69: =VLOOKUP(E69,$E$2588:$H$2802,4,FALSE) -> 44421
C70: EPI | D70: JUSTINA - boleto | E70: 44421 | F70: 1125 | G70: Empresa 2 | H70: =VLOOKUP(E70,$E$2588:$H$2802,4,FALSE) -> 44421
C71: RESCISAO | D71: FGTS RESCISORIO TIAGO FERNANDES | E71: 44421 | F71: 84.18 | G71: Empresa 2 | H71: =VLOOKUP(E71,$E$2588:$H$2802,4,FALSE) -> 44421
C72: COMUNICACAO | D72: VIVO - vcto 28/07 (corte em 17/08) | E72: 44422 | F72: 534.69 | G72: PKS | H72: =VLOOKUP(E72,$E$2588:$H$2802,4,FALSE) -> 44424
C73: TERCEIROS | D73: MARCIA - LIMPEZA - DUAS Empresa 2AS | E73: 44423 | F73: 140 | G73: Empresa 2 | H73: =VLOOKUP(E73,$E$2588:$H$2802,4,FALSE) -> 44424
C74: COMBUSTIVEL | D74: GENILSON | E74: 44424 | F74: 250 | G74: Empresa 2 | H74: =VLOOKUP(E74,$E$2588:$H$2802,4,FALSE) -> 44424
C75: SALARIOS | D75: EXTRAS TIAGO (Joel) - demitido | E75: 44424 | F75: 613 | G75: Empresa 2 | H75: =VLOOKUP(E75,$E$2588:$H$2802,4,FALSE) -> 44424
C76: SAUDE | D76: PROMED | E76: 44424 | F76: 92.25 | G76: Empresa 1 | H76: =VLOOKUP(E76,$E$2588:$H$2802,4,FALSE) -> 44424
C77: ASSESSORIA | D77: VISAO - parcelamento | E77: 44424 | F77: 1100 | G77: Empresa 2 | H77: =VLOOKUP(E77,$E$2588:$H$2802,4,FALSE) -> 44424
C78: CONVENIO | D78: MICROEMPA | E78: 44424 | F78: 84 | G78: Empresa 2 | H78: =VLOOKUP(E78,$E$2588:$H$2802,4,FALSE) -> 44424
C79: AGUA | D79: SAMAE | E79: 44424 | F79: 83.7 | G79: Empresa 1 | H79: =VLOOKUP(E79,$E$2588:$H$2802,4,FALSE) -> 44424
C80: FÉRIAS | D80: ADRIANA DA d - PARTE | E80: 44424 | F80: 1000 | G80: Empresa 2 | H80: =VLOOKUP(E80,$E$2588:$H$2802,4,FALSE) -> 44424
C81: SALARIOS | D81: SALARIOS - cheques | E81: 44424 | F81: =1379+444 -> 1823 | G81: Empresa 2 | H81: =VLOOKUP(E81,$E$2588:$H$2802,4,FALSE) -> 44424
C82: INFORMATICA | D82: NIC.BR - DOMINIO Empresa 1 | E82: 44425 | F82: 76 | G82: Empresa 1 | H82: =VLOOKUP(E82,$E$2588:$H$2802,4,FALSE) -> 44425
C83: ENCARGOS | D83: INSS | E83: 44425 | F83: 326.38 | G83: Empresa 1 | H83: =VLOOKUP(E83,$E$2588:$H$2802,4,FALSE) -> 44425
C84: EPI | D84: ZAPA - vcto 03/08 - já prorrogado | E84: 44425 | F84: 389.65 | G84: Empresa 2 | H84: =VLOOKUP(E84,$E$2588:$H$2802,4,FALSE) -> 44425
C85: TERCEIROS | D85: CHAVEIRO CASA DE PEDRA - pagar em dinheiro | E85: 44425 | F85: 77 | G85: Empresa 1 | H85: =VLOOKUP(E85,$E$2588:$H$2802,4,FALSE) -> 44425
C86: COMBUSTIVEL | D86: UNO (Gabriel vai usar) | E86: 44425 | F86: 50 | G86: Empresa 2 | H86: =VLOOKUP(E86,$E$2588:$H$2802,4,FALSE) -> 44425
C87: CURSO | D87: RAFAEL SCOPEL - saldo entrada (acordo) | E87: 44425 | F87: 500 | G87: Empresa 2 | H87: =VLOOKUP(E87,$E$2588:$H$2802,4,FALSE) -> 44425
C88: SOCIOS | D88: RETIRADA PAULO d - cartao | E88: 44425 | F88: 2500 | G88: Distribuição de Lucros | H88: =VLOOKUP(E88,$E$2588:$H$2802,4,FALSE) -> 44425
C89: SAUDE | D89: PLANO DE SAUDE FUNCIONARIOS | E89: 44425 | F89: 949.71 | G89: Empresa 2 | H89: =VLOOKUP(E89,$E$2588:$H$2802,4,FALSE) -> 44425
C90: TRANSPORTE | D90: VAN - parte | E90: 44425 | F90: 2000 | G90: Empresa 2 | H90: =VLOOKUP(E90,$E$2588:$H$2802,4,FALSE) -> 44425
C91: EPI | D91: MAJUSEG | E91: 44425 | F91: 209.9 | G91: Empresa 2 | H91: =VLOOKUP(E91,$E$2588:$H$2802,4,FALSE) -> 44425
C92: VIAGEM | D92: VOB HOTEL | E92: 44425 | F92: =456+460 -> 916 | G92: Empresa 2 | H92: =VLOOKUP(E92,$E$2588:$H$2802,4,FALSE) -> 44425
C93: SAUDE | D93: PROMED - VCTO 15/06 (negociado para não cortar) - cheque | E93: 44425 | F93: 2813.47 | G93: Empresa 2 | H93: =VLOOKUP(E93,$E$2588:$H$2802,4,FALSE) -> 44425
C94: ALIMENTACAO | D94: BISTRO LUCAS RAMOS - vcto 03/08 - já prorrogado - cheque | E94: 44425 | F94: 1635 | G94: Empresa 1 | H94: =VLOOKUP(E94,$E$2588:$H$2802,4,FALSE) -> 44425
C95: RESCISAO | D95: ALEXANDRE DE VASCONCELOS | E95: 44426 | F95: 42.65 | G95: Empresa 2 | H95: =VLOOKUP(E95,$E$2588:$H$2802,4,FALSE) -> 44426
C96: ALIMENTACAO | D96: CANTINA DELA COLINA - cheque entregue em 27/07 | E96: 44427 | F96: 1000 | G96: Empresa 2 | H96: =VLOOKUP(E96,$E$2588:$H$2802,4,FALSE) -> 44427
C97: TRANSPORTE | D97: VISATE - 20 CARTOES | E97: 44427 | F97: 380 | G97: Empresa 2 | H97: =VLOOKUP(E97,$E$2588:$H$2802,4,FALSE) -> 44427
C98: RESCISAO | D98: FGTS RESCISORIO ROGER | E98: 44428 | F98: 4.3 | G98: Empresa 2 | H98: =VLOOKUP(E98,$E$2588:$H$2802,4,FALSE) -> 44428
C99: RESCISAO | D99: FGTS RESCISORIO MAICON | E99: 44428 | F99: 5.53 | G99: Empresa 2 | H99: =VLOOKUP(E99,$E$2588:$H$2802,4,FALSE) -> 44428
C100: COMBUSTIVEL | D100: CLEBER | E100: 44428 | F100: 150 | G100: Empresa 2 | H100: =VLOOKUP(E100,$E$2588:$H$2802,4,FALSE) -> 44428
C101: VIAGEM | D101: FLAVIO | E101: 44428 | F101: 378.8 | G101: Empresa 2 | H101: =VLOOKUP(E101,$E$2588:$H$2802,4,FALSE) -> 44428
C102: MANUTENCAO | D102: BT5 - VALVULA E TAMPAO LAVAJATO CLEBER | E102: 44428 | F102: 50 | G102: Empresa 2 | H102: =VLOOKUP(E102,$E$2588:$H$2802,4,FALSE) -> 44428
C103: EPI | D103: ALSCO | E103: 44428 | F103: 75.34 | G103: Empresa 2 | H103: =VLOOKUP(E103,$E$2588:$H$2802,4,FALSE) -> 44428
...

Sheet Fluxo_08_21
B1: =IF(B5=1,"Domingo",IF(B5=2,"Segunda",IF(B5=3,"Terça",IF(B5=4,"Quarta",IF(B5=5,"Quinta",IF(B5=6,"Sexta",IF(B5=7,"Sábado",0))))))) -> Segunda | C1: =IF(C5=1,"Domingo",IF(C5=2,"Segunda",IF(C5=3,"Terça",IF(C5=4,"Quarta",IF(C5=5,"Quinta",IF(C5=6,"Sexta",IF(C5=7,"Sábado",0))))))) -> Terça | D1: =IF(D5=1,"Domingo",IF(D5=2,"Segunda",IF(D5=3,"Terça",IF(D5=4,"Quarta",IF(D5=5,"Quinta",IF(D5=6,"Sexta",IF(D5=7,"Sábado",0))))))) -> Quarta | E1: =IF(E5=1,"Domingo",IF(E5=2,"Segunda",IF(E5=3,"Terça",IF(E5=4,"Quarta",IF(E5=5,"Quinta",IF(E5=6,"Sexta",IF(E5=7,"Sábado",0))))))) -> Quinta | F1: =IF(F5=1,"Domingo",IF(F5=2,"Segunda",IF(F5=3,"Terça",IF(F5=4,"Quarta",IF(F5=5,"Quinta",IF(F5=6,"Sexta",IF(F5=7,"Sábado",0))))))) -> Sexta | G1: =IF(G5=1,"Domingo",IF(G5=2,"Segunda",IF(G5=3,"Terça",IF(G5=4,"Quarta",IF(G5=5,"Quinta",IF(G5=6,"Sexta",IF(G5=7,"Sábado",0))))))) -> Segunda | H1: =IF(H5=1,"Domingo",IF(H5=2,"Segunda",IF(H5=3,"Terça",IF(H5=4,"Quarta",IF(H5=5,"Quinta",IF(H5=6,"Sexta",IF(H5=7,"Sábado",0))))))) -> Terça | I1: =IF(I5=1,"Domingo",IF(I5=2,"Segunda",IF(I5=3,"Terça",IF(I5=4,"Quarta",IF(I5=5,"Quinta",IF(I5=6,"Sexta",IF(I5=7,"Sábado",0))))))) -> Quarta | ... W1: =IF(W5=1,"Domingo",IF(W5=2,"Segunda",IF(W5=3,"Terça",IF(W5=4,"Quarta",IF(W5=5,"Quinta",IF(W5=6,"Sexta",IF(W5=7,"Sábado",0))))))) -> Terça
A2: Localizado no banco | B2: =B29 -> 44410 | C2: =C29 -> 44411 | D2: =D29 -> 44412 | E2: =E29 -> 44413 | F2: =F29 -> 44414 | G2: =G29 -> 44417 | H2: =H29 -> 44418 | I2: =I29 -> 44419 | ... W2: =W29 -> 44439
A4: SALDO INICIAL | B4: =Fluxo_07_21!W38 -> -1710.84 | C4: =B38 -> -2323.44 | D4: =C38 -> 29175.31 | E4: =D38 -> 26473.37 | F4: =E38 -> -17952.29 | G4: =F38 -> -24716.75 | H4: =G38 -> -21034.38 | I4: =H38 -> -16601.52 | J4: =I38 -> -18291.52 | ... W4: =V38 -> -5631.99
B5: =WEEKDAY(B2) -> 2 | C5: =WEEKDAY(C2) -> 3 | D5: =WEEKDAY(D2) -> 4 | E5: =WEEKDAY(E2) -> 5 | F5: =WEEKDAY(F2) -> 6 | G5: =WEEKDAY(G2) -> 2 | H5: =WEEKDAY(H2) -> 3 | I5: =WEEKDAY(I2) -> 4 | ... W5: =WEEKDAY(W2) -> 3
A6: RECEBIMENTOS (OPERAÇÃO) | B6: =SUM(B7:B26) -> 5321.28 | C6: =SUM(C7:C26) -> 31924.72 | D6: =SUM(D7:D26) -> 0 | E6: =SUM(E7:E26) -> 18648.36 | F6: =SUM(F7:F26) -> 1319.23 | G6: =SUM(G7:G26) -> 13296.57 | H6: =SUM(H7:H26) -> 18824.61 | I6: =SUM(I7:I26) -> 0 | ... W6: =SUM(W7:W26) -> 0
A7: MARCOPOLO/SEMAN | B7: =5873.92-836 -> 5037.92 | C7: =13414.8+11747.84+6762.08 -> 31924.72 | E7: =12534.9-256.54 -> 12278.36 | G7: =11826.15 -> 11826.15 | J7: 2630.35 | K7: =1564+1936 -> 3500 | M7: 12627.03
A8: MARCOPOLO | F8: 1319.23 | L8: 968.1 | O8: 5799.63
A9: VOLARE | E9: =590+5780 -> 6370 | J9: 33251.91 | R9: 29145.19
A10: HIDROVER | T10: =7338.24+1834.56 -> 9172.8
A11: WSUL
A12: RUGERI | B12: 283.36 | G12: 1470.42 | K12: =1600.07 -> 1600.07 | Q12: 530.18 | V12: 1859.27
A13: CIFERAL
A14: SAN MARINO | K14: 4996.98 | M14: 4210.55 | V14: 6850.35
A15: LIBRELATO | K15: =3853.14+4473.18+3271.14+3853.14 -> 15450.6 | U15: =5782.25+5903.14 -> 11685.39
A16: FLORENSE | H16: =1607.81+4233.6+12983.2 -> 18824.61
A17: Previsao Estufa | Q17: 1320 | R17: -1320 | U17: 11587.18
A18: RENOVAR
A27: PAGAMENTOS PROGRAMADOS
A28: Soma de Valor | B28: Pagto.
A29: tipo | B29: 44410 | C29: 44411 | D29: 44412 | E29: 44413 | F29: 44414 | G29: 44417 | H29: 44418 | I29: 44419 | J29: 44420 | K29: 44421 | L29: 44424 | M29: 44425 | N29: 44426 | O29: 44427 | P29: 44428 | Q29: 44431 | R29: 44432 | S29: 44433 | T29: 44434 | U29: 44435 | V29: 44438 | W29: 44439 | X29: Total Geral
A30: PARTICULAR | K30: 2300 | M30: 2500 | T30: 3550 | U30: 1120 | X30: 9470
A31: VENTURE | B31: 4993.88 | E31: 190 | F31: 893.14 | G31: 308.78 | I31: 90 | J31: 2338.9 | K31: 564.56 | L31: 175.95 | M31: 2114.38 | Q31: 63.8 | R31: 9821 | U31: 1907.48 | X31: 23461.87
A32: SOLUTEC | U32: 1283.09 | X32: 1283.09
A33: PKS | L33: 534.69 | U33: 3710.47 | X33: 4245.16
A34: SEMAN | B34: 940 | C34: 425.97 | D34: 2701.94 | E34: 62884.02 | F34: 7190.55 | G34: 9305.42 | H34: 14391.75 | I34: 1600 | J34: 34692.03 | K34: 13127.87 | L34: 5010 | M34: 7828.73 | N34: 42.65 | O34: 1380 | P34: 15395.08 | Q34: 2000.88 | R34: 3534 | S34: 13775.75 | T34: 4179.33 | U34: 9627 | V34: 628.41 | W34: 1180.37 | X34: 211841.75
A35: Total Geral | B35: 5933.88 | C35: 425.97 | D35: 2701.94 | E35: 63074.02 | F35: 8083.69 | G35: 9614.2 | H35: 14391.75 | I35: 1690 | J35: 37030.93 | K35: 15992.43 | L35: 5720.64 | M35: 12443.11 | N35: 42.65 | O35: 1380 | P35: 15395.08 | Q35: 2064.68 | R35: 13355 | S35: 13775.75 | T35: 7729.33 | U35: 17648.04 | V35: 628.41 | W35: 1180.37 | X35: 250301.87
A38: SALDO FINAL | B38: =B4+B6-GETPIVOTDATA("Valor",$A$28,"Pagto.",DATE(2021,8,2)) -> -2323.44 | C38: =C4+C6-GETPIVOTDATA("Valor",$A$28,"Pagto.",DATE(2021,8,3)) -> 29175.31 | D38: =D4+D6-GETPIVOTDATA("Valor",$A$28,"Pagto.",DATE(2021,8,4)) -> 26473.37 | E38: =E4+E6-GETPIVOTDATA("Valor",$A$28,"Pagto.",DATE(2021,8,5)) -> -17952.29 | F38: =F4+F6-GETPIVOTDATA("Valor",$A$28,"Pagto.",DATE(2021,8,6)) -> -24716.75 | G38: =G4+G6-GETPIVOTDATA("Valor",$A$28,"Pagto.",DATE(2021,8,9)) -> -21034.38 | H38: =H4+H6-GETPIVOTDATA("Valor",$A$28,"Pagto.",DATE(2021,8,10)) -> -16601.52 | I38: =I4+I6-GETPIVOTDATA("Valor",$A$28,"Pagto.",DATE(2021,8,11)) -> -18291.52 | J38: =J4+J6-GETPIVOTDATA("Valor",$A$28,"Pagto.",DATE(2021,8,12)) -> -19440.19 | K38: =K4+K6-GETPIVOTDATA("Valor",$A$28,"Pagto.",DATE(2021,8,13)) -> -9884.97 | L38: =L4+L6-GETPIVOTDATA("Valor",$A$28,"Pagto.",DATE(2021,8,16)) -> -14637.51 | M38: =M4+M6-GETPIVOTDATA("Valor",$A$28,"Pagto.",DATE(2021,8,17)) -> -10243.04 | N38: =N4+N6-GETPIVOTDATA("Valor",$A$28,"Pagto.",DATE(2021,8,18)) -> -10285.69 | O38: =O4+O6-GETPIVOTDATA("Valor",$A$28,"Pagto.",DATE(2021,8,19)) -> -5866.06 | P38: =P4+P6-GETPIVOTDATA("Valor",$A$28,"Pagto.",DATE(2021,8,20)) -> -21261.14 | Q38: =Q4+Q6-GETPIVOTDATA("Valor",$A$28,"Pagto.",DATE(2021,8,23)) -> -21475.64 | R38: =R4+R6-GETPIVOTDATA("Valor",$A$28,"Pagto.",DATE(2021,8,24)) -> -7005.45 | S38: =S4+S6-GETPIVOTDATA("Valor",$A$28,"Pagto.",DATE(2021,8,25)) -> -20781.2 | T38: =T4+T6-GETPIVOTDATA("Valor",$A$28,"Pagto.",DATE(2021,8,26)) -> -19337.73 | U38: =U4+U6-GETPIVOTDATA("Valor",$A$28,"Pagto.",DATE(2021,8,27)) -> -13713.2 | V38: =V4+V6-GETPIVOTDATA("Valor",$A$28,"Pagto.",DATE(2021,8,30)) -> -5631.99 | W38: =W4+W6-GETPIVOTDATA("Valor",$A$28,"Pagto.",DATE(2021,8,31)) -> -6812.36

Sheet 07_21
A1: 0 | B1: tm | C1: CodCli | D1: Nome | E1: dtvcto | F1: Valor | G1: tipo | H1: Pagto.
C2: BANCOS | D2: JUROS E DESPESAS BANCARIAS | E2: 44378 | F2: =2489.38+153+200+314.8+508.45 -> 3665.63 | G2: Empresa 1 | H2: =VLOOKUP(E2,$E$2723:$H$2937,4,FALSE) -> 44378
C3: ALIMENTACAO | D3: CRISTINE LANCHES - saldo (já prorrogado) | E3: 44379 | F3: 722.11 | G3: Empresa 2 | H3: =VLOOKUP(E3,$E$2723:$H$2937,4,FALSE) -> 44379
C4: EPI | D4: CORSUL | E4: 44379 | F4: 179.1 | G4: Empresa 2 | H4: =VLOOKUP(E4,$E$2723:$H$2937,4,FALSE) -> 44379
C5: INFORMATICA | D5: DIGISAM - vcto 14/07/20 (sem falta) | E5: 44379 | F5: 577 | G5: Empresa 1 | H5: =VLOOKUP(E5,$E$2723:$H$2937,4,FALSE) -> 44379
C6: ALIMENTACAO | D6: TIO JOAO - vcto 17/06 | E6: 44379 | F6: 1501.65 | G6: Empresa 2 | H6: =VLOOKUP(E6,$E$2723:$H$2937,4,FALSE) -> 44379
C7: EXPEDIENTE | D7: KIPONTO - cartao ponto - vcto 30/06 | E7: 44379 | F7: 102 | G7: Empresa 1 | H7: =VLOOKUP(E7,$E$2723:$H$2937,4,FALSE) -> 44379
C8: SOCIOS | D8: CASAS PAGLIARIN - VCTO 18/06 - TITULO JÁ PRORROGADO | E8: 44379 | F8: 1858.18 | G8: Distribuição de Lucros | H8: =VLOOKUP(E8,$E$2723:$H$2937,4,FALSE) -> 44379
C9: COMBUSTIVEL | D9: TEONAS - MENSAL (descontado dias de atestado) | E9: 44379 | F9: 60 | G9: Empresa 2 | H9: =VLOOKUP(E9,$E$2723:$H$2937,4,FALSE) -> 44379
C10: COMBUSTIVEL | D10: GENILSON - MENSAL (incluido o reembolso de 03 cartoes de 04 passagens) | E10: 44379 | F10: 300 | G10: Empresa 2 | H10: =VLOOKUP(E10,$E$2723:$H$2937,4,FALSE) -> 44379
C11: COMBUSTIVEL | D11: ROGERIO - REEMBOLSO | E11: 44379 | F11: 150 | G11: Empresa 2 | H11: =VLOOKUP(E11,$E$2723:$H$2937,4,FALSE) -> 44379
C12: COMBUSTIVEL | D12: CLEBER | E12: 44379 | F12: 100 | G12: Empresa 2 | H12: =VLOOKUP(E12,$E$2723:$H$2937,4,FALSE) -> 44379
C13: VIAGEM | D13: FLAVIO (reembolsar 12,00) | E13: 44379 | F13: 412 | G13: Empresa 2 | H13: =VLOOKUP(E13,$E$2723:$H$2937,4,FALSE) -> 44379
C14: SOCIOS | D14: RETIRADA RUBENS c | E14: 44379 | F14: 1500 | G14: Distribuição de Lucros | H14: =VLOOKUP(E14,$E$2723:$H$2937,4,FALSE) -> 44379
... C16: ALIMENTACAO | D16: BISTRO LUCAS RAMOS -cheque em 03/06/21 | E16: 44381 | F16: 1560 | G16: Empresa 1 | H16: =VLOOKUP(E16,$E$2723:$H$2937,4,FALSE) -> 44382
C17: TERCEIROS | D17: ZANOL - novo trabalho na plasticos - confirmar valor exato - descontado valor da passagem RJ | E17: 44382 | F17: =4500-1352.21 -> 3147.79 | G17: Empresa 2 | H17: =VLOOKUP(E17,$E$2723:$H$2937,4,FALSE) -> 44382
C18: RESCISAO | D18: EMANOEL DE SOUZA | E18: 44382 | F18: 299.85 | G18: Empresa 2 | H18: =VLOOKUP(E18,$E$2723:$H$2937,4,FALSE) -> 44382
C19: SALARIOS | D19: SALARIOS - arquivo | E19: 44382 | F19: =53438+741+530+2207 -> 56916 | G19: Empresa 2 | H19: =VLOOKUP(E19,$E$2723:$H$2937,4,FALSE) -> 44382
C20: SALARIOS | D20: SALARIOS - cheques | E20: 44382 | F20: =2415+200+1849 -> 4464 | G20: Empresa 2 | H20: =VLOOKUP(E20,$E$2723:$H$2937,4,FALSE) -> 44382
C21: SALARIOS | D21: SALARIOS | E21: 44383 | F21: 8441 | G21: Empresa 1 | H21: =VLOOKUP(E21,$E$2723:$H$2937,4,FALSE) -> 44383
C22: PARCELAMENTO | D22: EMPRESTIMO FOLHA BB - 08/30 | E22: 44383 | F22: 2183.32 | G22: Empresa 2 | H22: =VLOOKUP(E22,$E$2723:$H$2937,4,FALSE) -> 44383
C23: SALARIOS | D23: SALARIOS - depositos | E23: 44383 | F23: 32783 | G23: Empresa 2 | H23: =VLOOKUP(E23,$E$2723:$H$2937,4,FALSE) -> 44383
C24: VIAGEM | D24: LIRANE - VOLARE | E24: 44383 | F24: 1532.04 | G24: Empresa 2 | H24: =VLOOKUP(E24,$E$2723:$H$2937,4,FALSE) -> 44383
C25: COMBUSTIVEL | D25: FLAVIO - combustivel + pedagio (vai levar Lirane ao aeroporto) | E25: 44383 | F25: 200 | G25: Empresa 2 | H25: =VLOOKUP(E25,$E$2723:$H$2937,4,FALSE) -> 44383
C26: COMBUSTIVEL | D26: TEONAS - SALDO MENSAL | E26: 44383 | F26: 90 | G26: Empresa 2 | H26: =VLOOKUP(E26,$E$2723:$H$2937,4,FALSE) -> 44383
C27: ENCARGOS | D27: FGTS - vcto 07/06/21 | E27: 44383 | F27: 958.8 | G27: Empresa 1 | H27: =VLOOKUP(E27,$E$2723:$H$2937,4,FALSE) -> 44383
C28: SALARIOS | D28: PAULO EDUARDO | E28: 44384 | F28: 2800 | G28: Empresa 2 | H28: =VLOOKUP(E28,$E$2723:$H$2937,4,FALSE) -> 44384
C29: SALARIOS | D29: CLEBER - sacar em dinheiro - já descontado plano de saude (R$ 4.549,00 - R$ 315,00) | E29: 44384 | F29: 4234 | G29: Empresa 2 | H29: =VLOOKUP(E29,$E$2723:$H$2937,4,FALSE) -> 44384
C30: SALARIOS | D30: PENSAO ALIMENTICIA | E30: 44384 | F30: =673.38+750.09+726.59 -> 2150.06 | G30: Empresa 2 | H30: =VLOOKUP(E30,$E$2723:$H$2937,4,FALSE) -> 44384
C31: EPI | D31: CORSUL | E31: 44384 | F31: 149.53 | G31: Empresa 2 | H31: =VLOOKUP(E31,$E$2723:$H$2937,4,FALSE) -> 44384
C32: VIAGEM | D32: VOB HOTEL - vcto 30/06 - JÁ PRORROGADO | E32: 44385 | F32: 718 | G32: Empresa 2 | H32: =VLOOKUP(E32,$E$2723:$H$2937,4,FALSE) -> 44385
C33: MATERIAL | D33: MARCARINI TINTAS - vcto 06/07 | E33: 44385 | F33: 240.16 | G33: Empresa 1 | H33: =VLOOKUP(E33,$E$2723:$H$2937,4,FALSE) -> 44385
C34: MATERIAL | D34: CELETRO - material comprado por Zanol em 02/07 | E34: 44385 | F34: 612.6 | G34: Empresa 1 | H34: =VLOOKUP(E34,$E$2723:$H$2937,4,FALSE) -> 44385
C35: VEICULOS | D35: MOLAS UNO FLAVIO | E35: 44385 | F35: 195 | G35: Empresa 2 | H35: =VLOOKUP(E35,$E$2723:$H$2937,4,FALSE) -> 44385
C36: COMBUSTIVEL | D36: ROGERIO | E36: 44385 | F36: =110+100 -> 210 | G36: Distribuição de Lucros | H36: =VLOOKUP(E36,$E$2723:$H$2937,4,FALSE) -> 44385
C37: COMBUSTIVEL | D37: LUIS b | E37: 44385 | F37: =300+100 -> 400 | G37: Distribuição de Lucros | H37: =VLOOKUP(E37,$E$2723:$H$2937,4,FALSE) -> 44385
C38: COMBUSTIVEL | D38: CLEBER | E38: 44385 | F38: 120 | G38: Empresa 2 | H38: =VLOOKUP(E38,$E$2723:$H$2937,4,FALSE) -> 44385
C39: COMBUSTIVEL | D39: REEMBOLSO GABRIEL - abasteceu Uno Cleber | E39: 44385 | F39: 60 | G39: Empresa 2 | H39: =VLOOKUP(E39,$E$2723:$H$2937,4,FALSE) -> 44385
C40: VIAGEM | D40: FLAVIO | E40: 44385 | F40: 443.87 | G40: Empresa 2 | H40: =VLOOKUP(E40,$E$2723:$H$2937,4,FALSE) -> 44385
C41: SALARIOS | D41: SALARIOS - cheques | E41: 44385 | F41: =424+664+755+429+1266+492+480+620+304+342+717+500 -> 6993 | G41: Empresa 2 | H41: =VLOOKUP(E41,$E$2723:$H$2937,4,FALSE) -> 44385
C42: EPI | D42: JUSTINA - CHEQUE 25/06 | E42: 44385 | F42: 1350 | G42: Empresa 2 | H42: =VLOOKUP(E42,$E$2723:$H$2937,4,FALSE) -> 44385
C43: ACORDO | D43: SAMUEL - CIFERAL - 06/09 - já prorrogado venceu em 06/07 | E43: 44386 | F43: 1500 | G43: Empresa 2 | H43: =VLOOKUP(E43,$E$2723:$H$2937,4,FALSE) -> 44386
C44: ACORDO | D44: ARTHUR - CIFERAL - 06/08 - já prorrogado venceu em 06/07 | E44: 44386 | F44: 1500 | G44: Empresa 2 | H44: =VLOOKUP(E44,$E$2723:$H$2937,4,FALSE) -> 44386
C45: ACORDO | D45: LEONARDO - CIFERAL - 06/14 - já prorrogado venceu em 06/07 | E45: 44386 | F45: 1500 | G45: Empresa 2 | H45: =VLOOKUP(E45,$E$2723:$H$2937,4,FALSE) -> 44386
C46: MATERIAL | D46: LF MAQUINAS - estilete Flavio | E46: 44386 | F46: 135 | G46: Empresa 2 | H46: =VLOOKUP(E46,$E$2723:$H$2937,4,FALSE) -> 44386
C47: ALIMENTACAO | D47: ZAPAROLLI - vcto 30/06 - sem falta - já prorrogado | E47: 44386 | F47: 7749.12 | G47: Empresa 2 | H47: =VLOOKUP(E47,$E$2723:$H$2937,4,FALSE) -> 44386
C48: ALIMENTACAO | D48: RESTAURANTE BOM TEMPERO - vcto 17/06 - já prorrogado | E48: 44386 | F48: 1889.71 | G48: Empresa 2 | H48: =VLOOKUP(E48,$E$2723:$H$2937,4,FALSE) -> 44386
C49: CURSO | D49: JOAO VITOR - TREINAMENTO VOLARE - 01/02 | E49: 44386 | F49: 1322.5 | G49: Empresa 2 | H49: =VLOOKUP(E49,$E$2723:$H$2937,4,FALSE) -> 44386
C50: FÉRIAS | D50: MARCELO DOS SANTOS - vcto 18/06 - saldo | E50: 44386 | F50: 1230 | G50: Empresa 2 | H50: =VLOOKUP(E50,$E$2723:$H$2937,4,FALSE) -> 44386
C51: SOCIOS | D51: RETIRADA PAULO d | E51: 44386 | F51: 1000 | G51: Distribuição de Lucros | H51: =VLOOKUP(E51,$E$2723:$H$2937,4,FALSE) -> 44386
C52: COMUNICACAO | D52: NET - vcto 20/06 (corte em 14/07) | E52: 44386 | F52: 206.79 | G52: Empresa 2 | H52: =VLOOKUP(E52,$E$2723:$H$2937,4,FALSE) -> 44386
C53: SOCIOS | D53: RETIRADA LUIS b - troca sr.rubens | E53: 44386 | F53: 2500 | G53: Distribuição de Lucros | H53: =VLOOKUP(E53,$E$2723:$H$2937,4,FALSE) -> 44386
C54: VIAGEM | D54: JOEL - CAIXINHA | E54: 44387 | F54: 2626 | G54: Empresa 2 | H54: =VLOOKUP(E54,$E$2723:$H$2937,4,FALSE) -> 44389
C55: COMUNICACAO | D55: CLARO - vcto 20/06 (corte em 14/07) | E55: 44388 | F55: =189.45+1408.66+43.01 -> 1641.12 | G55: Empresa 1 | H55: =VLOOKUP(E55,$E$2723:$H$2937,4,FALSE) -> 44389
C56: MATERIAL | D56: FUSOPAR - vcto 09/06 - falta boleto (falado com Laura) | E56: 44389 | F56: 163.98 | G56: Empresa 2 | H56: =VLOOKUP(E56,$E$2723:$H$2937,4,FALSE) -> 44389
C57: MATERIAL | D57: VALVULA - POLIMATIQ | E57: 44389 | F57: 1400 | G57: Empresa 1 | H57: =VLOOKUP(E57,$E$2723:$H$2937,4,FALSE) -> 44389
C58: SOCIOS | D58: CARTEIRA PAULO EDUARDO - 02/02 | E58: 44390 | F58: 750 | G58: Distribuição de Lucros | H58: =VLOOKUP(E58,$E$2723:$H$2937,4,FALSE) -> 44390
C59: MATERIAL | D59: FERRAGEM DO TONINHO - DISCO DE CORTE - DEVOLVER P/ PAULO EDUARDO | E59: 44390 | F59: 30 | G59: Empresa 2 | H59: =VLOOKUP(E59,$E$2723:$H$2937,4,FALSE) -> 44390
C60: AGUA | D60: LUCHETTI | E60: 44390 | F60: 60 | G60: Empresa 1 | H60: =VLOOKUP(E60,$E$2723:$H$2937,4,FALSE) -> 44390
C61: RECLAMATORIA | D61: ACAO ADEMAR - guias | E61: 44391 | F61: =5029.58+426.49 -> 5456.07 | G61: Empresa 2 | H61: =VLOOKUP(E61,$E$2723:$H$2937,4,FALSE) -> 44391
C62: COMBUSTIVEL | D62: CLEBER - Florense | E62: 44391 | F62: 100 | G62: Empresa 2 | H62: =VLOOKUP(E62,$E$2723:$H$2937,4,FALSE) -> 44391
C63: MATERIAL | D63: REEMBOLSO ROGERIO PROJETISTA (Dosso e Fusopar) | E63: 44391 | F63: =150+15.99 -> 165.99 | G63: Empresa 2 | H63: =VLOOKUP(E63,$E$2723:$H$2937,4,FALSE) -> 44391
C64: VIAGEM | D64: VOB HOTEL - vcto 08/07 - sem falta (já prorrogado) | E64: 44391 | F64: 564 | G64: Empresa 2 | H64: =VLOOKUP(E64,$E$2723:$H$2937,4,FALSE) -> 44391
C65: COMUNICACAO | D65: VIVO - vcto 28/06 (corte em 16/07) | E65: 44391 | F65: 380.65 | G65: PKS | H65: =VLOOKUP(E65,$E$2723:$H$2937,4,FALSE) -> 44391
C66: ASSESSORIA | D66: ROGERIO - PROJETISTA - WSUL - 06/06 (Já prorrogado - vcto 02/07) | E66: 44391 | F66: 3100 | G66: Empresa 2 | H66: =VLOOKUP(E66,$E$2723:$H$2937,4,FALSE) -> 44391
C67: RECLAMATORIA | D67: ANDRE MARQUES - 01/20 | E67: 44391 | F67: 3200 | G67: Empresa 2 | H67: =VLOOKUP(E67,$E$2723:$H$2937,4,FALSE) -> 44391
C68: TRANSPORTE | D68: VISATE - 15 CARTOES | E68: 44392 | F68: 285 | G68: Empresa 2 | H68: =VLOOKUP(E68,$E$2723:$H$2937,4,FALSE) -> 44392
C69: COMBUSTIVEL | D69: REEMBOLSO LUIS b | E69: 44393 | F69: 200 | G69: Empresa 2 | H69: =VLOOKUP(E69,$E$2723:$H$2937,4,FALSE) -> 44393
C70: COMBUSTIVEL | D70: REEMBOLSO ROGERIO | E70: 44393 | F70: 200 | G70: Empresa 2 | H70: =VLOOKUP(E70,$E$2723:$H$2937,4,FALSE) -> 44393
C71: COMBUSTIVEL | D71: CLEBER | E71: 44393 | F71: 100 | G71: Empresa 2 | H71: =VLOOKUP(E71,$E$2723:$H$2937,4,FALSE) -> 44393
C72: COMBUSTIVEL | D72: GENILSON - MENSAL (parte) | E72: 44393 | F72: 100 | G72: Empresa 2 | H72: =VLOOKUP(E72,$E$2723:$H$2937,4,FALSE) -> 44393
C73: VIAGEM | D73: FLAVIO | E73: 44393 | F73: 400 | G73: Empresa 2 | H73: =VLOOKUP(E73,$E$2723:$H$2937,4,FALSE) -> 44393
C74: EPI | D74: OTICA LAURO - NFs marco e abril | E74: 44393 | F74: 360 | G74: Empresa 2 | H74: =VLOOKUP(E74,$E$2723:$H$2937,4,FALSE) -> 44393
C75: FÉRIAS | D75: ALGACIR MULLER - 03/03 | E75: 44394 | F75: 941 | G75: Empresa 2 | H75: =VLOOKUP(E75,$E$2723:$H$2937,4,FALSE) -> 44396
... C143: ALIMENTACAO | D143: BOM TEMPERO - vcto 13/06 - já prorrogado | E143: 44400 | F143: 1326 | G143: Empresa 2 | H143: =VLOOKUP(E143,$E$2723:$H$2937,4,FALSE) -> 44400
C144: COMBUSTIVEL | D144: LUIS b | E144: 44401 | F144: =100+100 -> 200 | G144: Distribuição de Lucros | H144: =VLOOKUP(E144,$E$2723:$H$2937,4,FALSE) -> 44403
C145: TERCEIROS | D145: MARCIA | E145: 44402 | F145: 70 | G145: Empresa 2 | H145: =VLOOKUP(E145,$E$2723:$H$2937,4,FALSE) -> 44403
C146: INFORMATICA | D146: METADADOS - VCTO 25/06 | E146: 44403 | F146: 318.68 | G146: Empresa 1 | H146: =VLOOKUP(E146,$E$2723:$H$2937,4,FALSE) -> 44403
C147: CURSO | D147: JOAO VITOR - TREINAMENTO VOLARE - 02/02 | E147: 44403 | F147: 1322.5 | G147: Empresa 2 | H147: =VLOOKUP(E147,$E$2723:$H$2937,4,FALSE) -> 44403
C148: SOCIOS | D148: RETIRADA PAULO d - cartao vcto 27/07 | E148: 44403 | F148: 3270 | G148: Distribuição de Lucros | H148: =VLOOKUP(E148,$E$2723:$H$2937,4,FALSE) -> 44403
C149: VIAGEM | D149: VOB HOTEL - vcto 15/07 - já prorrogado | E149: 44403 | F149: 684 | G149: Empresa 2 | H149: =VLOOKUP(E149,$E$2723:$H$2937,4,FALSE) -> 44403
C150: TRANSPORTE | D150: VAN - saldo | E150: 44403 | F150: 3955.5 | G150: Empresa 2 | H150: =VLOOKUP(E150,$E$2723:$H$2937,4,FALSE) -> 44403
C151: TERCEIROS | D151: AKRON - cabos internet salas Nelci e Ester - deposito dados nf | E151: 44403 | F151: 980 | G151: Empresa 1 | H151: =VLOOKUP(E151,$E$2723:$H$2937,4,FALSE) -> 44403
C152: EPI | D152: ZAPA | E152: 44403 | F152: 308.93 | G152: Empresa 2 | H152: =VLOOKUP(E152,$E$2723:$H$2937,4,FALSE) -> 44403
C153: MATERIAL | D153: MARCARINI TINTAS - 02/02 - vcto 18/07 - prorrogado com Priscila | E153: 44403 | F153: 2191 | G153: Empresa 1 | H153: =VLOOKUP(E153,$E$2723:$H$2937,4,FALSE) -> 44403
C154: VIAGEM | D154: JOEL - CAIXINHA | E154: 44403 | F154: 2626 | G154: Empresa 2 | H154: =VLOOKUP(E154,$E$2723:$H$2937,4,FALSE) -> 44403
C155: EPI | D155: ZAPA (solicitado prorrogacao p/27/07) | E155: 44404 | F155: 623.97 | G155: Empresa 2 | H155: =VLOOKUP(E155,$E$2723:$H$2937,4,FALSE) -> 44404
C156: EPI | D156: ZAPA (solicitado prorrogacao p/27/07) | E156: 44404 | F156: 189.96 | G156: Empresa 2 | H156: =VLOOKUP(E156,$E$2723:$H$2937,4,FALSE) -> 44404
... C162: SALARIOS | D162: EXTRAS - VOLARE/CIFERAL | E162: 44405 | F162: 11876 | G162: Empresa 2 | H162: =VLOOKUP(E162,$E$2723:$H$2937,4,FALSE) -> 44405
C163: SALARIOS | D163: EXTRAS - LIMPEZA/MECANICA | E163: 44405 | F163: =2893+2068+796 -> 5757 | G163: Empresa 2 | H163: =VLOOKUP(E163,$E$2723:$H$2937,4,FALSE) -> 44405
C164: COMBUSTIVEL | D164: CLEBER - Florense | E164: 44405 | F164: 80 | G164: Empresa 2 | H164: =VLOOKUP(E164,$E$2723:$H$2937,4,FALSE) -> 44405
C165: ACORDO | D165: SINDIASSEIO - 01/03 | E165: 44405 | F165: 304.96 | G165: Empresa 2 | H165: =VLOOKUP(E165,$E$2723:$H$2937,4,FALSE) -> 44405
C166: EPI | D166: CORSUL | E166: 44405 | F166: 134.36 | G166: Empresa 2 | H166: =VLOOKUP(E166,$E$2723:$H$2937,4,FALSE) -> 44405
C167: EPI | D167: ACORDO PONTO DAS SOLDAS - 1.PARCELA (PIX 30.383.069/0001-02) | E167: 44406 | F167: 584 | G167: Empresa 2 | H167: =VLOOKUP(E167,$E$2723:$H$2937,4,FALSE) -> 44406
C168: SOCIOS | D168: IRF VERA KARLING - 03/08 | E168: 44406 | F168: 239.9 | G168: Empresa 2 | H168: =VLOOKUP(E168,$E$2723:$H$2937,4,FALSE) -> 44406
C169: SEGURO | D169: OUTLANDER - LUIS | E169: 44406 | F169: 404.35 | G169: Distribuição de Lucros | H169: =VLOOKUP(E169,$E$2723:$H$2937,4,FALSE) -> 44406
C170: BONUS | D170: 18 PESSOAS | E170: 44406 | F170: 2160 | G170: Empresa 2 | H170: =VLOOKUP(E170,$E$2723:$H$2937,4,FALSE) -> 44406
C171: VEICULOS | D171: ARNILDO - UNO FLAVIO - prorrogado | E171: 44406 | F171: 250 | G171: Empresa 1 | H171: =VLOOKUP(E171,$E$2723:$H$2937,4,FALSE) -> 44406
C172: COMBUSTIVEL | D172: CLEBER | E172: 44406 | F172: 150 | G172: Empresa 2 | H172: =VLOOKUP(E172,$E$2723:$H$2937,4,FALSE) -> 44406
C173: VIAGEM | D173: FLAVIO | E173: 44406 | F173: 400 | G173: Empresa 2 | H173: =VLOOKUP(E173,$E$2723:$H$2937,4,FALSE) -> 44406
...

Sheet Fluxo_07_21
B1: =IF(B5=1,"Domingo",IF(B5=2,"Segunda",IF(B5=3,"Terça",IF(B5=4,"Quarta",IF(B5=5,"Quinta",IF(B5=6,"Sexta",IF(B5=7,"Sábado",0))))))) -> Quinta | C1: =IF(C5=1,"Domingo",IF(C5=2,"Segunda",IF(C5=3,"Terça",IF(C5=4,"Quarta",IF(C5=5,"Quinta",IF(C5=6,"Sexta",IF(C5=7,"Sábado",0))))))) -> Sexta | D1: =IF(D5=1,"Domingo",IF(D5=2,"Segunda",IF(D5=3,"Terça",IF(D5=4,"Quarta",IF(D5=5,"Quinta",IF(D5=6,"Sexta",IF(D5=7,"Sábado",0))))))) -> Segunda | E1: =IF(E5=1,"Domingo",IF(E5=2,"Segunda",IF(E5=3,"Terça",IF(E5=4,"Quarta",IF(E5=5,"Quinta",IF(E5=6,"Sexta",IF(E5=7,"Sábado",0))))))) -> Terça | F1: =IF(F5=1,"Domingo",IF(F5=2,"Segunda",IF(F5=3,"Terça",IF(F5=4,"Quarta",IF(F5=5,"Quinta",IF(F5=6,"Sexta",IF(F5=7,"Sábado",0))))))) -> Quarta | G1: =IF(G5=1,"Domingo",IF(G5=2,"Segunda",IF(G5=3,"Terça",IF(G5=4,"Quarta",IF(G5=5,"Quinta",IF(G5=6,"Sexta",IF(G5=7,"Sábado",0))))))) -> Quinta | H1: =IF(H5=1,"Domingo",IF(H5=2,"Segunda",IF(H5=3,"Terça",IF(H5=4,"Quarta",IF(H5=5,"Quinta",IF(H5=6,"Sexta",IF(H5=7,"Sábado",0))))))) -> Sexta | I1: =IF(I5=1,"Domingo",IF(I5=2,"Segunda",IF(I5=3,"Terça",IF(I5=4,"Quarta",IF(I5=5,"Quinta",IF(I5=6,"Sexta",IF(I5=7,"Sábado",0))))))) -> Segunda | ... W1: =IF(W5=1,"Domingo",IF(W5=2,"Segunda",IF(W5=3,"Terça",IF(W5=4,"Quarta",IF(W5=5,"Quinta",IF(W5=6,"Sexta",IF(W5=7,"Sábado",0))))))) -> Sexta
A2: Localizado no banco | B2: =B29 -> 44378 | C2: =C29 -> 44379 | D2: =D29 -> 44382 | E2: =E29 -> 44383 | F2: =F29 -> 44384 | G2: =G29 -> 44385 | H2: =H29 -> 44386 | I2: =I29 -> 44389 | ... W2: =W29 -> 44407
A4: SALDO INICIAL | B4: =Fluxo_06_21!W38 -> -19015.48 | C4: =B38 -> -20273.51 | D4: =C38 -> -8546.17 | E4: =D38 -> -11082.44 | F4: =E38 -> -21265.2 | G4: =F38 -> -4284.95 | H4: =G38 -> -15627.58 | I4: =H38 -> -14082.21 | J4: =I38 -> -18369.81 | ... W4: =V38 -> -4364.14
B5: =WEEKDAY(B2) -> 5 | C5: =WEEKDAY(C2) -> 6 | D5: =WEEKDAY(D2) -> 2 | E5: =WEEKDAY(E2) -> 3 | F5: =WEEKDAY(F2) -> 4 | G5: =WEEKDAY(G2) -> 5 | H5: =WEEKDAY(H2) -> 6 | I5: =WEEKDAY(I2) -> 2 | ... W5: =WEEKDAY(W2) -> 6
A6: RECEBIMENTOS (OPERAÇÃO) | B6: =SUM(B7:B26) -> 2407.6 | C6: =SUM(C7:C26) -> 19189.38 | D6: =SUM(D7:D26) -> 66141.03 | E6: =SUM(E7:E26) -> 36005.4 | F6: =SUM(F7:F26) -> 26313.84 | G6: =SUM(G7:G26) -> 0 | H6: =SUM(H7:H26) -> 22078.49 | I6: =SUM(I7:I26) -> 1543.5 | ... W6: =SUM(W7:W26) -> 8738.83
A7: MARCOPOLO/SEMAN | B7: =1600-950 -> 650 | D7: =11513.78+14054.25 -> 25568.03 | F7: =11747.84+12636 -> 24383.84 | H7: =13007.4 -> 13007.4 | N7: =15433.45 -> 15433.45 | P7: 1600 | Q7: =2910 -> 2910 | S7: =11862.9+962.85+395.85 -> 13221.6 | W7: 2250.15
A8: MARCOPOLO | D8: 5822.67 | E8: =1003.9+6714.46 -> 7718.36 | H8: 6123.04
A9: VOLARE | B9: 1757.6 | C9: 19189.38 | D9: 34750.33 | O9: 21720.36 | P9: 51581.47 | Q9: 11592.06 | R9: =8686.32+306-160.72 -> 8831.6 | U9: 6260.36 | V9: =4845+1802 -> 6647 | W9: 2220.97
A10: HIDROVER | N10: =7338.24+1834.56 -> 9172.8
A11: WSUL | E11: 5280 | F11: 1930
A12: RUGERI | O12: 2604.97
A13: CIFERAL
A14: SAN MARINO | H14: 2948.05 | K14: 5871.6 | R14: 1942.16 | W14: 4267.71
A15: LIBRELATO | J15: =3853.14+5372.25 -> 9225.39 | T15: =5372.25+3853.14+4724.16 -> 13949.55
A16: Previsao Estufa | E16: =11503.52+11503.52 -> 23007.04
A17: FLORENSE | I17: =1543.5 -> 1543.5
A27: PAGAMENTOS PROGRAMADOS
A28: Soma de Valor | B28: Pagto.
A29: tipo | B29: 44378 | C29: 44379 | D29: 44382 | E29: 44383 | F29: 44384 | G29: 44385 | H29: 44386 | I29: 44389 | J29: 44390 | K29: 44391 | L29: 44392 | M29: 44393 | N29: 44396 | O29: 44397 | P29: 44398 | Q29: 44399 | R29: 44400 | S29: 44403 | T29: 44404 | U29: 44405 | V29: 44406 | W29: 44407 | X29: Total Geral
A30: PARTICULAR | C30: 3358.18 | G30: 610 | H30: 3500 | J30: 750 | N30: 5000 | R30: 3270.5 | S30: 3470 | T30: 1500 | V30: 404.35 | W30: 2000 | X30: 23863.03
A31: VENTURE | B31: 3665.63 | C31: 679 | D31: 1560 | E31: 9399.8 | G31: 852.76 | I31: 3041.12 | J31: 60 | N31: 8488.15 | O31: 1805.17 | P31: 1125 | Q31: 72.95 | R31: 619 | S31: 3489.68 | T31: 1490.3 | U31: 1482 | V31: 4015 | X31: 41845.56
A32: SOLUTEC | N32: 1278.47 | X32: 1278.47
A33: PKS | K33: 380.65 | N33: 3670.73 | X33: 4051.38
A34: SEMAN | C34: 3424.86 | D34: 67117.3 | E34: 36788.36 | F34: 9333.59 | G34: 9879.87 | H34: 17033.12 | I34: 2789.98 | J34: 30 | K34: 12586.06 | L34: 285 | M34: 1360 | N34: 9072.58 | O34: 16218.55 | P34: 23902.03 | Q34: 5949.02 | R34: 5202.07 | S34: 8966.93 | T34: 1637.41 | U34: 18152.32 | V34: 22824.78 | W34: 4085.53 | X34: 276639.36
A35: Total Geral | B35: 3665.63 | C35: 7462.04 | D35: 68677.3 | E35: 46188.16 | F35: 9333.59 | G35: 11342.63 | H35: 20533.12 | I35: 5831.1 | J35: 840 | K35: 12966.71 | L35: 285 | M35: 1360 | N35: 27509.93 | O35: 18023.72 | P35: 25027.03 | Q35: 6021.97 | R35: 9091.57 | S35: 15926.61 | T35: 4627.71 | U35: 19634.32 | V35: 27244.13 | W35: 6085.53 | X35: 347677.8
A38: SALDO FINAL | B38: =B4+B6-GETPIVOTDATA("Valor",$A$28,"Pagto.",DATE(2021,7,1)) -> -20273.51 | C38: =C4+C6-GETPIVOTDATA("Valor",$A$28,"Pagto.",DATE(2021,7,2)) -> -8546.17 | D38: =D4+D6-GETPIVOTDATA("Valor",$A$28,"Pagto.",DATE(2021,7,5)) -> -11082.44 | E38: =E4+E6-GETPIVOTDATA("Valor",$A$28,"Pagto.",DATE(2021,7,6)) -> -21265.2 | F38: =F4+F6-GETPIVOTDATA("Valor",$A$28,"Pagto.",DATE(2021,7,7)) -> -4284.95 | G38: =G4+G6-GETPIVOTDATA("Valor",$A$28,"Pagto.",DATE(2021,7,8)) -> -15627.58 | H38: =H4+H6-GETPIVOTDATA("Valor",$A$28,"Pagto.",DATE(2021,7,9)) -> -14082.21 | I38: =I4+I6-GETPIVOTDATA("Valor",$A$28,"Pagto.",DATE(2021,7,12)) -> -18369.81 | J38: =J4+J6-GETPIVOTDATA("Valor",$A$28,"Pagto.",DATE(2021,7,13)) -> -9984.42 | K38: =K4+K6-GETPIVOTDATA("Valor",$A$28,"Pagto.",DATE(2021,7,14)) -> -17079.53 | L38: =L4+L6-GETPIVOTDATA("Valor",$A$28,"Pagto.",DATE(2021,7,15)) -> -17364.53 | M38: =M4+M6-GETPIVOTDATA("Valor",$A$28,"Pagto.",DATE(2021,7,16)) -> -18724.53 | N38: =N4+N6-GETPIVOTDATA("Valor",$A$28,"Pagto.",DATE(2021,7,19)) -> -21628.21 | O38: =O4+O6-GETPIVOTDATA("Valor",$A$28,"Pagto.",DATE(2021,7,20)) -> -15326.6 | P38: =P4+P6-GETPIVOTDATA("Valor",$A$28,"Pagto.",DATE(2021,7,21)) -> 12827.84 | Q38: =Q4+Q6-GETPIVOTDATA("Valor",$A$28,"Pagto.",DATE(2021,7,22)) -> 21307.93 | R38: =R4+R6-GETPIVOTDATA("Valor",$A$28,"Pagto.",DATE(2021,7,23)) -> 22990.12 | S38: =S4+S6-GETPIVOTDATA("Valor",$A$28,"Pagto.",DATE(2021,7,26)) -> 20285.11 | T38: =T4+T6-GETPIVOTDATA("Valor",$A$28,"Pagto.",DATE(2021,7,27)) -> 29606.95 | U38: =U4+U6-GETPIVOTDATA("Valor",$A$28,"Pagto.",DATE(2021,7,28)) -> 16232.99 | V38: =V4+V6-GETPIVOTDATA("Valor",$A$28,"Pagto.",DATE(2021,7,29)) -> -4364.14 | W38: =W4+W6-GETPIVOTDATA("Valor",$A$28,"Pagto.",DATE(2021,7,30)) -> -1710.84

Sheet 06_21
A1: 0 | B1: tm | C1: CodCli | D1: Nome | E1: dtvcto | F1: Valor | G1: tipo | H1: Pagto.
C2: BANCOS | D2: JUROS E DESPESAS BANCARIAS | E2: 44348 | F2: =2100.14+111.36+24+353+321+790 -> 3699.5 | G2: Distribuição de Lucros | H2: =VLOOKUP(E2,$E$2892:$H$2947,4,FALSE) -> 44348
C3: COMBUSTIVEL | D3: TEONAS - MENSAL | E3: 44348 | F3: 150 | G3: Empresa 2 | H3: =VLOOKUP(E3,$E$2892:$H$2947,4,FALSE) -> 44348
C4: COMBUSTIVEL | D4: GENILSON - MENSAL | E4: 44348 | F4: 250 | G4: Empresa 2 | H4: =VLOOKUP(E4,$E$2892:$H$2947,4,FALSE) -> 44348
C5: CONSUMO | D5: SIMOQUIMICA | E5: 44348 | F5: 164.05 | G5: Empresa 2 | H5: =VLOOKUP(E5,$E$2892:$H$2947,4,FALSE) -> 44348
C6: ASSESSORIA | D6: GERENCIAL/PKS - VCTO 21/12/20 | E6: 44348 | F6: 1045 | G6: Empresa 1 | H6: =VLOOKUP(E6,$E$2892:$H$2947,4,FALSE) -> 44348
C7: ASSESSORIA | D7: ROGERIO - PROJETISTA - WSUL - 03/06 | E7: 44348 | F7: 2500 | G7: Empresa 1 | H7: =VLOOKUP(E7,$E$2892:$H$2947,4,FALSE) -> 44348
E8: 44349 | F8: 0 | G8: Empresa 1 | H8: =VLOOKUP(E8,$E$2892:$H$2947,4,FALSE) -> 44349
E9: 44350 | F9: 0 | G9: Empresa 1 | H9: =VLOOKUP(E9,$E$2892:$H$2947,4,FALSE) -> 44350
C10: SOCIOS | D10: RETIRADA LUIS b | E10: 44351 | F10: 2500 | G10: Distribuição de Lucros | H10: =VLOOKUP(E10,$E$2892:$H$2947,4,FALSE) -> 44351
C11: TRANSPORTE | D11: VISATE - SMART | E11: 44351 | F11: 190 | G11: Empresa 1 | H11: =VLOOKUP(E11,$E$2892:$H$2947,4,FALSE) -> 44351
C12: SOCIOS | D12: RETIRADA PAULO d | E12: 44351 | F12: 1500 | G12: Distribuição de Lucros | H12: =VLOOKUP(E12,$E$2892:$H$2947,4,FALSE) -> 44351
C13: SEGURO | D13: ROGERIO d - 06/06 - sem falta - ultima data | E13: 44351 | F13: 678.5 | G13: Distribuição de Lucros | H13: =VLOOKUP(E13,$E$2892:$H$2947,4,FALSE) -> 44351
C14: PARCELAMENTO | D14: EMPRESTIMO FOLHA BB - 06/30 | E14: 44351 | F14: 2296.34 | G14: Empresa 2 | H14: =VLOOKUP(E14,$E$2892:$H$2947,4,FALSE) -> 44351
C15: SALARIOS | D15: ARQUIVO PRODUCAO | E15: 44351 | F15: =42004+85+720+1039+2201 -> 46049 | G15: Empresa 2 | H15: =VLOOKUP(E15,$E$2892:$H$2947,4,FALSE) -> 44351
C16: FRETE | D16: BRASSPRESS | E16: 44351 | F16: 94.55 | G16: Empresa 1 | H16: =VLOOKUP(E16,$E$2892:$H$2947,4,FALSE) -> 44351
C17: TERCEIROS | D17: EA COMUNICACAO - JORNAL CRICIUMA | E17: 44351 | F17: 200 | G17: Empresa 2 | H17: =VLOOKUP(E17,$E$2892:$H$2947,4,FALSE) -> 44351
C18: EPI | D18: ZAPA | E18: 44351 | F18: 233.14 | G18: Empresa 2 | H18: =VLOOKUP(E18,$E$2892:$H$2947,4,FALSE) -> 44351
C19: EPI | D19: MAJUSEG | E19: 44351 | F19: 743.78 | G19: Empresa 2 | H19: =VLOOKUP(E19,$E$2892:$H$2947,4,FALSE) -> 44351
C20: COMBUSTIVEL | D20: PAULO EDURDO | E20: 44351 | F20: 100 | G20: Empresa 2 | H20: =VLOOKUP(E20,$E$2892:$H$2947,4,FALSE) -> 44351
C21: COMBUSTIVEL | D21: CLEBER | E21: 44351 | F21: 150 | G21: Empresa 2 | H21: =VLOOKUP(E21,$E$2892:$H$2947,4,FALSE) -> 44351
C22: VIAGEM | D22: FLAVIO | E22: 44351 | F22: 453.54 | G22: Empresa 2 | H22: =VLOOKUP(E22,$E$2892:$H$2947,4,FALSE) -> 44351
C23: ALIMENTACAO | D23: BOM TEMPERO - VOLARE - vcto 17/05 | E23: 44351 | F23: 2818.66 | G23: Empresa 2 | H23: =VLOOKUP(E23,$E$2892:$H$2947,4,FALSE) -> 44351
C24: SALARIOS | D24: SALARIOS | E24: 44351 | F24: 10613 | G24: Empresa 1 | H24: =VLOOKUP(E24,$E$2892:$H$2947,4,FALSE) -> 44351
C25: TRANSPORTE | D25: VISATE - 25 CARTOES | E25: 44352 | F25: 475 | G25: Empresa 2 | H25: =VLOOKUP(E25,$E$2892:$H$2947,4,FALSE) -> 44354
C26: ALIMENTACAO | D26: CANTINA DELA COLINA - nf 066 | E26: 44353 | F26: 972 | G26: Empresa 2 | H26: =VLOOKUP(E26,$E$2892:$H$2947,4,FALSE) -> 44354
C27: EPI | D27: JUSTINA - 28/05 | E27: 44354 | F27: 900 | G27: Empresa 2 | H27: =VLOOKUP(E27,$E$2892:$H$2947,4,FALSE) -> 44354
... C29: TRANSPORTE | D29: VISATE - 15 CARTOES | E29: 44354 | F29: 285 | G29: Empresa 2 | H29: =VLOOKUP(E29,$E$2892:$H$2947,4,FALSE) -> 44354
C30: SALARIOS | D30: SALARIOS COM CHEQUE - FUNC.SEM CONTA | E30: 44354 | F30: =13142+6600+824+371 -> 20937 | G30: Empresa 2 | H30: =VLOOKUP(E30,$E$2892:$H$2947,4,FALSE) -> 44354
C31: PARCELAMENTO | D31: EMPRESTIMO FOLHA BB - 07/30 | E31: 44354 | F31: 2204.25 | G31: Empresa 2 | H31: =VLOOKUP(E31,$E$2892:$H$2947,4,FALSE) -> 44354
C32: MATERIAL | D32: PERINI EQUIPAMENTOS - vcto 26/05 | E32: 44354 | F32: 366.5 | G32: Empresa 1 | H32: =VLOOKUP(E32,$E$2892:$H$2947,4,FALSE) -> 44354
C33: SALARIOS | D33: SALARIOS - saldo | E33: 44354 | F33: =109395-13142-42089-6600-1039-720-824-374-2201 -> 42406 | G33: Empresa 2 | H33: =VLOOKUP(E33,$E$2892:$H$2947,4,FALSE) -> 44354
C34: ACORDO | D34: SAMUEL - CIFERAL - 05/09 | E34: 44354 | F34: 1500 | G34: Empresa 2 | H34: =VLOOKUP(E34,$E$2892:$H$2947,4,FALSE) -> 44354
C35: ACORDO | D35: ARTHUR - CIFERAL - 05/08 | E35: 44354 | F35: 1500 | G35: Empresa 2 | H35: =VLOOKUP(E35,$E$2892:$H$2947,4,FALSE) -> 44354
C36: ACORDO | D36: LEONARDO - CIFERAL - 05/14 | E36: 44354 | F36: 1500 | G36: Empresa 2 | H36: =VLOOKUP(E36,$E$2892:$H$2947,4,FALSE) -> 44354
C37: ALIMENTACAO | D37: RESTAURANTE ZAPAROLLI - vcto 30/05 | E37: 44354 | F37: 7403 | G37: Empresa 2 | H37: =VLOOKUP(E37,$E$2892:$H$2947,4,FALSE) -> 44354
C38: SOCIOS | D38: FELIPE BALLICO - RETIRADA PAULO d | E38: 44354 | F38: 500 | G38: Distribuição de Lucros | H38: =VLOOKUP(E38,$E$2892:$H$2947,4,FALSE) -> 44354
C39: SALARIOS | D39: PAULO EDUARDO (salario + uber + dev.comb.Rogerio) | E39: 44354 | F39: =2900+12.12+13.01 -> 2925.13 | G39: Empresa 1 | H39: =VLOOKUP(E39,$E$2892:$H$2947,4,FALSE) -> 44354
C40: SALARIOS | D40: PENSAO ALIMENTICIA | E40: 44354 | F40: =712.64+750.08+121.8 -> 1584.52 | G40: Empresa 2 | H40: =VLOOKUP(E40,$E$2892:$H$2947,4,FALSE) -> 44354
C41: TERCEIROS | D41: MARCIA - LIMPEZA - 2 Empresa 2AS | E41: 44354 | F41: 140 | G41: Empresa 2 | H41: =VLOOKUP(E41,$E$2892:$H$2947,4,FALSE) -> 44354
C42: COMISSAO | D42: TIAGO - NF 1585 - Volare - R$ 86.228,00 | E42: 44354 | F42: 8622.8 | G42: Empresa 2 | H42: =VLOOKUP(E42,$E$2892:$H$2947,4,FALSE) -> 44354
C43: SALARIOS | D43: ADTO BRUNO - devolver para Sr.Paulo | E43: 44354 | F43: 100 | G43: Empresa 2 | H43: =VLOOKUP(E43,$E$2892:$H$2947,4,FALSE) -> 44354
C44: SOCIOS | D44: VIVO - LUIS | E44: 44354 | F44: 74.99 | G44: Distribuição de Lucros | H44: =VLOOKUP(E44,$E$2892:$H$2947,4,FALSE) -> 44354
C45: VIAGEM | D45: PAULO d - CIFERAL | E45: 44355 | F45: 1000 | G45: Empresa 1 | H45: =VLOOKUP(E45,$E$2892:$H$2947,4,FALSE) -> 44355
C46: INFORMATICA | D46: CORPORATIVA TI - dominio (Empresa 2 e Empresa 1) - sem falta | E46: 44355 | F46: 315 | G46: Empresa 2 | H46: =VLOOKUP(E46,$E$2892:$H$2947,4,FALSE) -> 44355
C47: COMBUSTIVEL | D47: UNO CLEBER - ENTREGUE PARA GABRIEL | E47: 44355 | F47: 50 | G47: Empresa 2 | H47: =VLOOKUP(E47,$E$2892:$H$2947,4,FALSE) -> 44355
C48: COMBUSTIVEL | D48: LUIS b | E48: 44355 | F48: 100 | G48: Empresa 2 | H48: =VLOOKUP(E48,$E$2892:$H$2947,4,FALSE) -> 44355
C49: EXPEDIENTE | D49: LICEIS - vcto 03/06 | E49: 44356 | F49: 217.79 | G49: Empresa 2 | H49: =VLOOKUP(E49,$E$2892:$H$2947,4,FALSE) -> 44356
C50: ASSESSORIA | D50: GT3 - vcto 20/05 | E50: 44356 | F50: 901.44 | G50: Empresa 2 | H50: =VLOOKUP(E50,$E$2892:$H$2947,4,FALSE) -> 44356
C51: CURSO | D51: RAFAEL SCOPEL - vcto 10/05 | E51: 44356 | F51: 1500 | G51: Empresa 2 | H51: =VLOOKUP(E51,$E$2892:$H$2947,4,FALSE) -> 44356
C52: COMUNICACAO | D52: NET - vcto 20/05 | E52: 44356 | F52: 213.63 | G52: Empresa 2 | H52: =VLOOKUP(E52,$E$2892:$H$2947,4,FALSE) -> 44356
... C57: EPI | D57: CORSUL | E57: 44357 | F57: 173.64 | G57: Empresa 2 | H57: =VLOOKUP(E57,$E$2892:$H$2947,4,FALSE) -> 44357
C58: MATERIAL | D58: CELETRO - ZANOL | E58: 44357 | F58: =1383.96+1102.25+522 -> 3008.21 | G58: Empresa 1 | H58: =VLOOKUP(E58,$E$2892:$H$2947,4,FALSE) -> 44357
C59: SOCIOS | D59: RETIRADA ROGERIO | E59: 44357 | F59: 3000 | G59: Distribuição de Lucros | H59: =VLOOKUP(E59,$E$2892:$H$2947,4,FALSE) -> 44357
C60: RESCISAO | D60: MISAEL GUIMARAES - LIBRELATO | E60: 44357 | F60: 303.08 | G60: Empresa 2 | H60: =VLOOKUP(E60,$E$2892:$H$2947,4,FALSE) -> 44357
C61: RESCISAO | D61: ANA MARIA - em dinheiro (Sindicato) | E61: 44358 | F61: 442.25 | G61: Empresa 2 | H61: =VLOOKUP(E61,$E$2892:$H$2947,4,FALSE) -> 44358
C62: RESCISAO | D62: FGTS RESCISORIO LIAMARA + DAIANE + DANILZA | E62: 44358 | F62: =11.34+7.94+6.01 -> 25.29 | G62: Empresa 2 | H62: =VLOOKUP(E62,$E$2892:$H$2947,4,FALSE) -> 44358
C63: MATERIAL | D63: RS GASES - cartorio | E63: 44358 | F63: 411.6 | G63: Empresa 1 | H63: =VLOOKUP(E63,$E$2892:$H$2947,4,FALSE) -> 44358
C64: SOCIOS | D64: SPADETTO - REEMBOLSAR SR.LUIS | E64: 44358 | F64: =108+22-50 -> 80 | G64: Distribuição de Lucros | H64: =VLOOKUP(E64,$E$2892:$H$2947,4,FALSE) -> 44358
C65: COMBUSTIVEL | D65: GABRIEL | E65: 44358 | F65: 100 | G65: Empresa 2 | H65: =VLOOKUP(E65,$E$2892:$H$2947,4,FALSE) -> 44358
C66: COMBUSTIVEL | D66: CLEBER | E66: 44358 | F66: 100 | G66: Empresa 2 | H66: =VLOOKUP(E66,$E$2892:$H$2947,4,FALSE) -> 44358
C67: VIAGEM | D67: FLAVIO + TROCA AGUA RADIADOR | E67: 44358 | F67: =400+120+30 -> 550 | G67: Empresa 2 | H67: =VLOOKUP(E67,$E$2892:$H$2947,4,FALSE) -> 44358
C68: SOCIOS | D68: RETIRADA LUIS b | E68: 44358 | F68: 2000 | G68: Distribuição de Lucros | H68: =VLOOKUP(E68,$E$2892:$H$2947,4,FALSE) -> 44358
C69: RESCISAO | D69: LEANDRO GONCALVES | E69: 44358 | F69: 157.5 | G69: Empresa 2 | H69: =VLOOKUP(E69,$E$2892:$H$2947,4,FALSE) -> 44358
C70: SAUDE | D70: PROMED - vcto 15/04/21 | E70: 44358 | F70: 3138.11 | G70: Empresa 2 | H70: =VLOOKUP(E70,$E$2892:$H$2947,4,FALSE) -> 44358
C71: RESCISAO | D71: DANILZA d | E71: 44361 | F71: 226.11 | G71: Empresa 2 | H71: =VLOOKUP(E71,$E$2892:$H$2947,4,FALSE) -> 44361
C72: RESCISAO | D72: ASSANE WADE | E72: 44361 | F72: 409.11 | G72: Empresa 2 | H72: =VLOOKUP(E72,$E$2892:$H$2947,4,FALSE) -> 44361
C73: VIAGEM | D73: JOEL - 01/03 | E73: 44361 | F73: 2876 | G73: Empresa 2 | H73: =VLOOKUP(E73,$E$2892:$H$2947,4,FALSE) -> 44361
C74: ACORDO | D74: NATHAN PEREIRA - 03/04 | E74: 44361 | F74: 1571.61 | G74: Empresa 2 | H74: =VLOOKUP(E74,$E$2892:$H$2947,4,FALSE) -> 44361
C75: SOCIOS | D75: RETIRADA PAULO d | E75: 44361 | F75: 2000 | G75: Distribuição de Lucros | H75: =VLOOKUP(E75,$E$2892:$H$2947,4,FALSE) -> 44361
C76: COMBUSTIVEL | D76: LUIS b | E76: 44361 | F76: 100 | G76: Distribuição de Lucros | H76: =VLOOKUP(E76,$E$2892:$H$2947,4,FALSE) -> 44361
C77: COMUNICACAO | D77: CLARO - vcto 20/05 | E77: 44361 | F77: 1636.57 | G77: Empresa 1 | H77: =VLOOKUP(E77,$E$2892:$H$2947,4,FALSE) -> 44361
C78: INFORMATICA | D78: DIGISAM | E78: 44361 | F78: 619 | G78: Empresa 1 | H78: =VLOOKUP(E78,$E$2892:$H$2947,4,FALSE) -> 44361
C79: MATERIAL | D79: RS GASES - vcto 11/06 | E79: 44361 | F79: 738.72 | G79: Empresa 1 | H79: =VLOOKUP(E79,$E$2892:$H$2947,4,FALSE) -> 44361
... C91: TRANSPORTE | D91: SCHEILA PACHECO - ultima nota fiscal | E91: 44362 | F91: 1700 | G91: Empresa 2 | H91: =VLOOKUP(E91,$E$2892:$H$2947,4,FALSE) -> 44362
C92: COMBUSTIVEL | D92: GENILSON - MENSAL | E92: 44362 | F92: =250 -> 250 | G92: Empresa 2 | H92: =VLOOKUP(E92,$E$2892:$H$2947,4,FALSE) -> 44362
C93: VIAGEM | D93: LUIS/GABRIEL | E93: 44362 | F93: 500 | G93: Empresa 2 | H93: =VLOOKUP(E93,$E$2892:$H$2947,4,FALSE) -> 44362
C94: TERCEIROS | D94: MARCIA - LIMPEZA | E94: 44362 | F94: 70 | G94: Empresa 2 | H94: =VLOOKUP(E94,$E$2892:$H$2947,4,FALSE) -> 44362
C95: EPI | D95: ZAPA- VCTO 28/05 - cartorio | E95: 44362 | F95: 647.2 | G95: Empresa 2 | H95: =VLOOKUP(E95,$E$2892:$H$2947,4,FALSE) -> 44362
C96: SAUDE | D96: PROMED | E96: 44362 | F96: 80.25 | G96: Empresa 1 | H96: =VLOOKUP(E96,$E$2892:$H$2947,4,FALSE) -> 44362
C97: SAUDE | D97: UNIMED | E97: 44362 | F97: 3594.05 | G97: PKS | H97: =VLOOKUP(E97,$E$2892:$H$2947,4,FALSE) -> 44362
C98: CONVENIO | D98: MICROEMPA | E98: 44362 | F98: 84 | G98: Empresa 2 | H98: =VLOOKUP(E98,$E$2892:$H$2947,4,FALSE) -> 44362
C99: CONVENIO | D99: MICROEMPA | E99: 44362 | F99: 1251.76 | G99: SOLUTEC | H99: =VLOOKUP(E99,$E$2892:$H$2947,4,FALSE) -> 44362
C100: COMBUSTIVEL | D100: UNO CLEBER - ENTREGUE PARA GABRIEL | E100: 44362 | F100: 50 | G100: Empresa 2 | H100: =VLOOKUP(E100,$E$2892:$H$2947,4,FALSE) -> 44362
C101: TERCEIROS | D101: IONICE - CHAVEIRO CASA DE PEDRA - em dinheiro | E101: 44362 | F101: 72 | G101: Empresa 1 | H101: =VLOOKUP(E101,$E$2892:$H$2947,4,FALSE) -> 44362
C102: CONSUMO | D102: DE TONI | E102: 44362 | F102: 151.4 | G102: Empresa 2 | H102: =VLOOKUP(E102,$E$2892:$H$2947,4,FALSE) -> 44362
C103: EPI | D103: ZAPA - VCTO 28/05 - cartorio | E103: 44363 | F103: 272.72 | G103: Empresa 2 | H103: =VLOOKUP(E103,$E$2892:$H$2947,4,FALSE) -> 44363
C104: AGUA | D104: SAMAE | E104: 44363 | F104: 178.23 | G104: Empresa 1 | H104: =VLOOKUP(E104,$E$2892:$H$2947,4,FALSE) -> 44363
... C149: COMBUSTIVEL | D149: REEMBOLSAR LUIS | E149: 44370 | F149: 100 | G149: Distribuição de Lucros | H149: =VLOOKUP(E149,$E$2892:$H$2947,4,FALSE) -> 44370
C150: COMBUSTIVEL | D150: REEMBOLSAR ROGERIO | E150: 44370 | F150: =100+100 -> 200 | G150: Distribuição de Lucros | H150: =VLOOKUP(E150,$E$2892:$H$2947,4,FALSE) -> 44370
C151: VIAGEM | D151: REEMBOLSAR LUIS - viagem Gabriel/SC - total 615,80 | E151: 44370 | F151: 115.8 | G151: Empresa 2 | H151: =VLOOKUP(E151,$E$2892:$H$2947,4,FALSE) -> 44370
C152: COMBUSTIVEL | D152: GABRIEL | E152: 44370 | F152: 130 | G152: Empresa 2 | H152: =VLOOKUP(E152,$E$2892:$H$2947,4,FALSE) -> 44370
C153: ACORDO | D153: RAMON - 02/04 | E153: 44370 | F153: 2000 | G153: Empresa 2 | H153: =VLOOKUP(E153,$E$2892:$H$2947,4,FALSE) -> 44370
C154: EPI | D154: ALSCO - vcto 21/06 | E154: 44370 | F154: 123.8 | G154: Empresa 2 | H154: =VLOOKUP(E154,$E$2892:$H$2947,4,FALSE) -> 44370
C155: EPI | D155: ALSCO - vcto 21/06 | E155: 44370 | F155: 125.63 | G155: Empresa 2 | H155: =VLOOKUP(E155,$E$2892:$H$2947,4,FALSE) -> 44370
C156: BANCOS | D156: GUIA BSP x ITAU | E156: 44370 | F156: 202.89 | G156: BSP | H156: =VLOOKUP(E156,$E$2892:$H$2947,4,FALSE) -> 44370
C157: ACORDO | D157: MICROEMPA - 04/13 | E157: 44370 | F157: 500 | G157: SOLUTEC | H157: =VLOOKUP(E157,$E$2892:$H$2947,4,FALSE) -> 44370
C158: ALUGUEL | D158: CANTON E FREITAS - vcto 21/06 | E158: 44370 | F158: 110 | G158: Empresa 1 | H158: =VLOOKUP(E158,$E$2892:$H$2947,4,FALSE) -> 44370
C159: EXPEDIENTE | D159: IDENTIFICA - CRACHAS - vcto 21/06 | E159: 44370 | F159: 399.6 | G159: Empresa 2 | H159: =VLOOKUP(E159,$E$2892:$H$2947,4,FALSE) -> 44370
C160: MATERIAL | D160: MARCARINI TINTAS - 01/02 - vcto 21/06 | E160: 44370 | F160: 2191 | G160: Empresa 1 | H160: =VLOOKUP(E160,$E$2892:$H$2947,4,FALSE) -> 44370
...

Sheet Fluxo_06_21
B1: =IF(B5=1,"Domingo",IF(B5=2,"Segunda",IF(B5=3,"Terça",IF(B5=4,"Quarta",IF(B5=5,"Quinta",IF(B5=6,"Sexta",IF(B5=7,"Sábado",0))))))) -> Terça | C1: =IF(C5=1,"Domingo",IF(C5=2,"Segunda",IF(C5=3,"Terça",IF(C5=4,"Quarta",IF(C5=5,"Quinta",IF(C5=6,"Sexta",IF(C5=7,"Sábado",0))))))) -> Quarta | D1: =IF(D5=1,"Domingo",IF(D5=2,"Segunda",IF(D5=3,"Terça",IF(D5=4,"Quarta",IF(D5=5,"Quinta",IF(D5=6,"Sexta",IF(D5=7,"Sábado",0))))))) -> Quinta | E1: =IF(E5=1,"Domingo",IF(E5=2,"Segunda",IF(E5=3,"Terça",IF(E5=4,"Quarta",IF(E5=5,"Quinta",IF(E5=6,"Sexta",IF(E5=7,"Sábado",0))))))) -> Sexta | F1: =IF(F5=1,"Domingo",IF(F5=2,"Segunda",IF(F5=3,"Terça",IF(F5=4,"Quarta",IF(F5=5,"Quinta",IF(F5=6,"Sexta",IF(F5=7,"Sábado",0))))))) -> Segunda | G1: =IF(G5=1,"Domingo",IF(G5=2,"Segunda",IF(G5=3,"Terça",IF(G5=4,"Quarta",IF(G5=5,"Quinta",IF(G5=6,"Sexta",IF(G5=7,"Sábado",0))))))) -> Terça | H1: =IF(H5=1,"Domingo",IF(H5=2,"Segunda",IF(H5=3,"Terça",IF(H5=4,"Quarta",IF(H5=5,"Quinta",IF(H5=6,"Sexta",IF(H5=7,"Sábado",0))))))) -> Quarta | I1: =IF(I5=1,"Domingo",IF(I5=2,"Segunda",IF(I5=3,"Terça",IF(I5=4,"Quarta",IF(I5=5,"Quinta",IF(I5=6,"Sexta",IF(I5=7,"Sábado",0))))))) -> Quinta | ... W1: =IF(W5=1,"Domingo",IF(W5=2,"Segunda",IF(W5=3,"Terça",IF(W5=4,"Quarta",IF(W5=5,"Quinta",IF(W5=6,"Sexta",IF(W5=7,"Sábado",0))))))) -> Quarta
A2: Localizado no banco | B2: =B29 -> 44348 | C2: =C29 -> 44349 | D2: =D29 -> 44350 | E2: =E29 -> 44351 | F2: =F29 -> 44354 | G2: =G29 -> 44355 | H2: =H29 -> 44356 | I2: =I29 -> 44357 | ... W2: =W29 -> 44377
A4: SALDO INICIAL | B4: =Fluxo_05_21!V38 -> -11932.71 | C4: =B38 -> -19741.26 | D4: =C38 -> -19741.26 | E4: =D38 -> -19741.26 | F4: =E38 -> -11211.52 | G4: =F38 -> -20726.49 | H4: =G38 -> -18266.97 | I4: =H38 -> -17429.61 | J4: =I38 -> -14870.27 | ... W4: =V38 -> -18416.9
B5: =WEEKDAY(B2) -> 3 | C5: =WEEKDAY(C2) -> 4 | D5: =WEEKDAY(D2) -> 5 | E5: =WEEKDAY(E2) -> 6 | F5: =WEEKDAY(F2) -> 2 | G5: =WEEKDAY(G2) -> 3 | H5: =WEEKDAY(H2) -> 4 | I5: =WEEKDAY(I2) -> 5 | ... W5: =WEEKDAY(W2) -> 4
A6: RECEBIMENTOS (OPERAÇÃO) | B6: =SUM(B7:B26) -> 0 | C6: =SUM(C7:C26) -> 0 | D6: =SUM(D7:D26) -> 0 | E6: =SUM(E7:E26) -> 77150.25 | F6: =SUM(F7:F26) -> 85556.22 | G6: =SUM(G7:G26) -> 3924.52 | H6: =SUM(H7:H26) -> 3980.22 | I6: =SUM(I7:I26) -> 9044.27 | ... W6: =SUM(W7:W26) -> 1749.12
A7: MARCOPOLO/SEMAN | E7: 48354.51 | I7: 2260 | K7: =17057.8 -> 17057.8 | Q7: =17529.05 -> 17529.05 | S7: =15049.87 -> 15049.87
A8: MARCOPOLO
A9: VOLARE | E9: 17208.56 | F9: 85556.22 | K9: =14903.05 -> 14903.05 | R9: 12000 | T9: =9562.15+41587.41 -> 51149.56 | U9: 18979.47
A10: HIDROVER | P10: =1834.56+7338.24 -> 9172.8
A11: WSUL
A12: RUGERI | G12: 2211.23 | J12: 2153.33 | W12: 1749.12
A13: FLORENSE | G13: =1713.29 -> 1713.29
A14: SAN MARINO | H14: 3980.22 | I14: =6784.27 -> 6784.27 | K14: =331.95 -> 331.95 | L14: 4463.28 | R14: =5148.14-211.46 -> 4936.68 | V14: 3634.15
A15: LIBRELATO | K15: =3653.79+2258.73+3703.14 -> 9615.66 | U15: =3853.14+3822.62+1926.27 -> 9602.03
A16: RANDON
A17: Previsao Estufa | E17: 11587.18 | M17: 11480.96
A18: CIFERAL | N18: 7915.1
A27: PAGAMENTOS PROGRAMADOS
A28: Soma de Valor | B28: Pagto.
A29: tipo | B29: 44348 | C29: 44349 | D29: 44350 | E29: 44351 | F29: 44354 | G29: 44355 | H29: 44356 | I29: 44357 | J29: 44358 | K29: 44361 | L29: 44362 | M29: 44363 | N29: 44364 | O29: 44365 | P29: 44368 | Q29: 44369 | R29: 44370 | S29: 44371 | T29: 44372 | U29: 44375 | V29: 44376 | W29: 44377 | X29: Total Geral
A30: PARTICULAR | B30: 3699.5 | E30: 4678.5 | F30: 574.99 | I30: 3000 | J30: 2080 | K30: 2850 | N30: 2650 | O30: 2500 | R30: 300 | S30: 2500 | T30: 7968.68 | U30: 2876.77 | V30: 235 | X30: 35913.44
A31: VENTURE | B31: 3545 | C31: 0 | D31: 0 | E31: 10897.55 | F31: 3291.63 | G31: 1000 | I31: 3008.21 | J31: 411.6 | K31: 10732.39 | L31: 152.25 | M31: 2305.23 | N31: 2728.59 | O31: 3792 | P31: 770 | R31: 2863.44 | S31: 10024.56 | T31: 8871.14 | U31: 3160.18 | V31: 7206.83 | X31: 74760.6
A32: SOLUTEC | L32: 1251.76 | R32: 500 | X32: 1751.76
A33: PKS | L33: 3594.05 | M33: 380.73 | X33: 3974.78
A34: SEMAN | B34: 564.05 | E34: 53044.46 | F34: 91204.57 | G34: 465 | H34: 3142.86 | I34: 476.72 | J34: 4513.15 | K34: 10346.11 | L34: 3452.6 | M34: 6521.92 | N34: 11649.21 | O34: 720.96 | P34: 8826.52 | Q34: 9981.99 | R34: 16895.89 | S34: 1341.97 | T34: 21659.31 | U34: 18559.51 | V34: 16144.14 | W34: 2347.7 | X34: 281858.64
A35: BSP | R35: 202.89 | X35: 202.89
A36: Total Geral | B36: 7808.55 | C36: 0 | D36: 0 | E36: 68620.51 | F36: 95071.19 | G36: 1465 | H36: 3142.86 | I36: 6484.93 | J36: 7004.75 | K36: 23928.5 | L36: 8450.66 | M36: 9207.88 | N36: 17027.8 | O36: 7012.96 | P36: 9596.52 | Q36: 9981.99 | R36: 20762.22 | S36: 13866.53 | T36: 38499.13 | U36: 24596.46 | V36: 23585.97 | W36: 2347.7 | X36: 398462.11
A38: SALDO FINAL | B38: =B4+B6-GETPIVOTDATA("Valor",$A$28,"Pagto.",DATE(2021,6,1)) -> -19741.26 | C38: =C4+C6-GETPIVOTDATA("Valor",$A$28,"Pagto.",DATE(2021,6,2)) -> -19741.26 | D38: =D4+D6-GETPIVOTDATA("Valor",$A$28,"Pagto.",DATE(2021,6,3)) -> -19741.26 | E38: =E4+E6-GETPIVOTDATA("Valor",$A$28,"Pagto.",DATE(2021,6,4)) -> -11211.52 | F38: =F4+F6-GETPIVOTDATA("Valor",$A$28,"Pagto.",DATE(2021,6,7)) -> -20726.49 | G38: =G4+G6-GETPIVOTDATA("Valor",$A$28,"Pagto.",DATE(2021,6,8)) -> -18266.97 | H38: =H4+H6-GETPIVOTDATA("Valor",$A$28,"Pagto.",DATE(2021,6,9)) -> -17429.61 | I38: =I4+I6-GETPIVOTDATA("Valor",$A$28,"Pagto.",DATE(2021,6,10)) -> -14870.27 | J38: =J4+J6-GETPIVOTDATA("Valor",$A$28,"Pagto.",DATE(2021,6,11)) -> -19721.69 | K38: =K4+K6-GETPIVOTDATA("Valor",$A$28,"Pagto.",DATE(2021,6,14)) -> -1741.73 | L38: =L4+L6-GETPIVOTDATA("Valor",$A$28,"Pagto.",DATE(2021,6,15)) -> -5729.11 | M38: =M4+M6-GETPIVOTDATA("Valor",$A$28,"Pagto.",DATE(2021,6,16)) -> -3456.03 | N38: =N4+N6-GETPIVOTDATA("Valor",$A$28,"Pagto.",DATE(2021,6,17)) -> -12568.73 | O38: =O4+O6-GETPIVOTDATA("Valor",$A$28,"Pagto.",DATE(2021,6,18)) -> -19581.69 | P38: =P4+P6-GETPIVOTDATA("Valor",$A$28,"Pagto.",DATE(2021,6,21)) -> -20005.41 | Q38: =Q4+Q6-GETPIVOTDATA("Valor",$A$28,"Pagto.",DATE(2021,6,22)) -> -12458.35 | R38: =R4+R6-GETPIVOTDATA("Valor",$A$28,"Pagto.",DATE(2021,6,23)) -> -16283.89 | S38: =S4+S6-GETPIVOTDATA("Valor",$A$28,"Pagto.",DATE(2021,6,24)) -> -15100.55 | T38: =T4+T6-GETPIVOTDATA("Valor",$A$28,"Pagto.",DATE(2021,6,25)) -> -2450.12 | U38: =U4+U6-GETPIVOTDATA("Valor",$A$28,"Pagto.",DATE(2021,6,28)) -> 1534.92 | V38: =V4+V6-GETPIVOTDATA("Valor",$A$28,"Pagto.",DATE(2021,6,29)) -> -18416.9 | W38: =W4+W6-GETPIVOTDATA("Valor",$A$28,"Pagto.",DATE(2021,6,30)) -> -19015.48

Sheet 05_21
A1: 0 | B1: tm | C1: CodCli | D1: Nome | E1: dtvcto | F1: Valor | G1: tipo | H1: Pagto.
C2: MATERIAL | D2: MARCARINI - CARTORIO | E2: 44317 | F2: 133.47 | G2: Empresa 1 | H2: =VLOOKUP(E2,$E$2815:$H$2864,4,FALSE) -> 44319
C3: TERCEIROS | D3: MARCIA - LIMPEZA - DUAS Empresa 2AS | E3: 44318 | F3: 140 | G3: Empresa 2 | H3: =VLOOKUP(E3,$E$2815:$H$2864,4,FALSE) -> 44319
C4: TERCEIROS | D4: REEBOMSAR SR LUIS - CONSULTA FUNCIONARIO ORTOPEDISTA | E4: 44319 | F4: 300 | G4: Empresa 2 | H4: =VLOOKUP(E4,$E$2815:$H$2864,4,FALSE) -> 44319
C5: COMBUSTIVEL | D5: TEONAS - MENSAL | E5: 44319 | F5: 150 | G5: Empresa 2 | H5: =VLOOKUP(E5,$E$2815:$H$2864,4,FALSE) -> 44319
C6: COMBUSTIVEL | D6: GENILSON - MENSAL | E6: 44319 | F6: 250 | G6: Empresa 2 | H6: =VLOOKUP(E6,$E$2815:$H$2864,4,FALSE) -> 44319
C7: MATERIAL | D7: CHAPAS - WSUL - ACOPLANO | E7: 44319 | F7: 6342.63 | G7: Empresa 1 | H7: =VLOOKUP(E7,$E$2815:$H$2864,4,FALSE) -> 44319
C8: BANCOS | D8: JUROS E DESPESAS BANCARIAS | E8: 44319 | F8: =2093+125+113.49+980 -> 3311.49 | G8: Empresa 1 | H8: =VLOOKUP(E8,$E$2815:$H$2864,4,FALSE) -> 44319
C9: MATERIAL | D9: FORT SOLDAS - TEONAS URGENTE | E9: 44319 | F9: 437 | G9: Empresa 1 | H9: =VLOOKUP(E9,$E$2815:$H$2864,4,FALSE) -> 44319
C10: RESCISAO | D10: FGTS RESCISORIO ROBERTO COVA | E10: 44319 | F10: 136.08 | G10: Empresa 2 | H10: =VLOOKUP(E10,$E$2815:$H$2864,4,FALSE) -> 44319
C11: FÉRIAS | D11: ALGACIR MULLER - 01/03 | E11: 44319 | F11: 940 | G11: Empresa 2 | H11: =VLOOKUP(E11,$E$2815:$H$2864,4,FALSE) -> 44319
C12: EPI | D12: ZAPA - vcto 19/04 - cfe financ.zapa não permite pgto - cartorio | E12: 44319 | F12: 535.82 | G12: Empresa 2 | H12: =VLOOKUP(E12,$E$2815:$H$2864,4,FALSE) -> 44319
C13: EPI | D13: ZAPA - vcto 19/04 - cfe financ.zapa não permite pgto - cartorio | E13: 44319 | F13: 378.31 | G13: Empresa 2 | H13: =VLOOKUP(E13,$E$2815:$H$2864,4,FALSE) -> 44319
C14: EPI | D14: ZAPA - vcto 19/04 - cfe financ.zapa não permite pgto - cartorio | E14: 44319 | F14: 392.12 | G14: Empresa 2 | H14: =VLOOKUP(E14,$E$2815:$H$2864,4,FALSE) -> 44319
C15: MATERIAL | D15: RS GASES - vcto 15/04 - cartorio | E15: 44320 | F15: 751.08 | G15: Empresa 1 | H15: =VLOOKUP(E15,$E$2815:$H$2864,4,FALSE) -> 44320
C16: VIAGEM | D16: VOB HOTEL - VCTO 04/04 - cartorio | E16: 44320 | F16: 1168.79 | G16: Empresa 2 | H16: =VLOOKUP(E16,$E$2815:$H$2864,4,FALSE) -> 44320
C17: VIAGEM | D17: VOB HOTEL - vcto 15/04 - cartorio | E17: 44320 | F17: 1117.79 | G17: Empresa 2 | H17: =VLOOKUP(E17,$E$2815:$H$2864,4,FALSE) -> 44320
C18: INFORMATICA | D18: POWER LINE - vcto 26/04 - cartorio | E18: 44320 | F18: 330.68 | G18: Empresa 2 | H18: =VLOOKUP(E18,$E$2815:$H$2864,4,FALSE) -> 44320
C19: PARCELAMENTO | D19: EMPRESTIMO FOLHA BB - 05/30 | E19: 44320 | F19: =2267.32+25.54 -> 2292.86 | G19: Empresa 2 | H19: =VLOOKUP(E19,$E$2815:$H$2864,4,FALSE) -> 44320
C20: COMBUSTIVEL | D20: PAULO EDUARDO | E20: 44320 | F20: 50 | G20: Distribuição de Lucros | H20: =VLOOKUP(E20,$E$2815:$H$2864,4,FALSE) -> 44320
C21: TRANSPORTE | D21: VISATE - 33 CARTOES | E21: 44320 | F21: 613.8 | G21: Empresa 1 | H21: =VLOOKUP(E21,$E$2815:$H$2864,4,FALSE) -> 44320
C22: SOCIOS | D22: SEGURO ROGERIO - PARC 05 (ultimo prazo) | E22: 44321 | F22: 678.5 | G22: Distribuição de Lucros | H22: =VLOOKUP(E22,$E$2815:$H$2864,4,FALSE) -> 44321
C23: VIAGEM | D23: FLAVIO - LIBRELATO | E23: 44321 | F23: 370 | G23: Empresa 2 | H23: =VLOOKUP(E23,$E$2815:$H$2864,4,FALSE) -> 44321
C24: COMBUSTIVEL | D24: REEMBOLSAR GENILSON - abasteceu Uno Flavio | E24: 44321 | F24: 50 | G24: Empresa 2 | H24: =VLOOKUP(E24,$E$2815:$H$2864,4,FALSE) -> 44321
C25: COMBUSTIVEL | D25: GABRIEL - abastecer Uno Cleber | E25: 44321 | F25: 50 | G25: Empresa 2 | H25: =VLOOKUP(E25,$E$2815:$H$2864,4,FALSE) -> 44321
C26: ASSESSORIA | D26: VISAO - vcto 26/04 (Patricia prorrogou para 10 dias - maximo) | E26: 44321 | F26: 3250 | G26: Empresa 2 | H26: =VLOOKUP(E26,$E$2815:$H$2864,4,FALSE) -> 44321
C27: ASSESSORIA | D27: OLIVEIRA E PERES - boletos vencidos em 25/03/20 e 30/03/20 | E27: 44321 | F27: =2978.25+2978.25 -> 5956.5 | G27: Empresa 1 | H27: =VLOOKUP(E27,$E$2815:$H$2864,4,FALSE) -> 44321
C28: ACORDO | D28: SAMUEL - CIFERAL - 04/09 - VCTO 18/03 | E28: 44321 | F28: 1500 | G28: Empresa 2 | H28: =VLOOKUP(E28,$E$2815:$H$2864,4,FALSE) -> 44321
C29: ACORDO | D29: ARTHUR - CIFERAL - 04/08 - VCTO 18/03 | E29: 44321 | F29: 1500 | G29: Empresa 2 | H29: =VLOOKUP(E29,$E$2815:$H$2864,4,FALSE) -> 44321
C30: ACORDO | D30: LEONARDO - CIFERAL - 04/14 - VCTO 18/03 | E30: 44321 | F30: 1500 | G30: Empresa 2 | H30: =VLOOKUP(E30,$E$2815:$H$2864,4,FALSE) -> 44321
C31: SALARIOS | D31: SALARIOS - arquivo | E31: 44321 | F31: =1422+1529 -> 2951 | G31: Empresa 1 | H31: =VLOOKUP(E31,$E$2815:$H$2864,4,FALSE) -> 44321
C32: SALARIOS | D32: FUNC SEM CONTA - saque em dinheiro | E32: 44321 | F32: =8403-1421+1506-1389+613+142+549-117 -> 8286 | G32: Empresa 2 | H32: =VLOOKUP(E32,$E$2815:$H$2864,4,FALSE) -> 44321
C33: SALARIOS | D33: SALARIOS - arquivo producao | E33: 44321 | F33: =45107+710+767+606+731-212 -> 47709 | G33: Empresa 2 | H33: =VLOOKUP(E33,$E$2815:$H$2864,4,FALSE) -> 44321
C34: COMBUSTIVEL | D34: REEMBOLSAR ROGERIO | E34: 44321 | F34: =100+100 -> 200 | G34: Distribuição de Lucros | H34: =VLOOKUP(E34,$E$2815:$H$2864,4,FALSE) -> 44321
C35: COMBUSTIVEL | D35: ROGERIO | E35: 44322 | F35: 100 | G35: Distribuição de Lucros | H35: =VLOOKUP(E35,$E$2815:$H$2864,4,FALSE) -> 44322
C36: FÉRIAS | D36: DALNIR - 03/03 | E36: 44322 | F36: 1997 | G36: Empresa 1 | H36: =VLOOKUP(E36,$E$2815:$H$2864,4,FALSE) -> 44322
C37: SALARIOS | D37: FUNC SEM CONTA - saque em dinheiro | E37: 44322 | F37: =10323-1506-627-708-549-613-142-511-605-512-530 -> 4020 | G37: Empresa 2 | H37: =VLOOKUP(E37,$E$2815:$H$2864,4,FALSE) -> 44322
C38: PARCELAMENTO | D38: EMPRESTIMO FOLHA BB - 06/30 | E38: 44322 | F38: =2177.12+26.06 -> 2203.18 | G38: Empresa 2 | H38: =VLOOKUP(E38,$E$2815:$H$2864,4,FALSE) -> 44322
C39: ALIMENTACAO | D39: CANTINA DELA COLINA | E39: 44322 | F39: 1170 | G39: Empresa 2 | H39: =VLOOKUP(E39,$E$2815:$H$2864,4,FALSE) -> 44322
C40: ASSESSORIA | D40: ROGERIO - PROJETISTA - WSUL - 02/06 | E40: 44322 | F40: 2500 | G40: Empresa 1 | H40: =VLOOKUP(E40,$E$2815:$H$2864,4,FALSE) -> 44322
C41: COMBUSTIVEL | D41: CLEBER | E41: 44323 | F41: =80+50 -> 130 | G41: Empresa 2 | H41: =VLOOKUP(E41,$E$2815:$H$2864,4,FALSE) -> 44323
C42: RESCISAO | D42: FGTS RESCISORIO NEILI | E42: 44323 | F42: 91.23 | G42: Empresa 2 | H42: =VLOOKUP(E42,$E$2815:$H$2864,4,FALSE) -> 44323
C43: SALARIOS | D43: DALNIR | E43: 44323 | F43: 4632 | G43: Empresa 1 | H43: =VLOOKUP(E43,$E$2815:$H$2864,4,FALSE) -> 44323
C44: SALARIOS | D44: SALARIOS | E44: 44323 | F44: =13856+678+2763 -> 17297 | G44: Empresa 2 | H44: =VLOOKUP(E44,$E$2815:$H$2864,4,FALSE) -> 44323
C45: CONSUMO | D45: SIMOQUIMICA | E45: 44323 | F45: 220 | G45: Empresa 2 | H45: =VLOOKUP(E45,$E$2815:$H$2864,4,FALSE) -> 44323
C46: TRANSPORTE | D46: VAN - parte abril | E46: 44324 | F46: 2000 | G46: Empresa 1 | H46: =VLOOKUP(E46,$E$2815:$H$2864,4,FALSE) -> 44326
C47: MATERIAL | D47: FERRAMENTAS GERAIS - arame mig | E47: 44325 | F47: 700 | G47: Empresa 2 | H47: =VLOOKUP(E47,$E$2815:$H$2864,4,FALSE) -> 44326
C48: SALARIOS | D48: EDUARDA RODRIGUES - LIBRELATO | E48: 44326 | F48: 390 | G48: Empresa 2 | H48: =VLOOKUP(E48,$E$2815:$H$2864,4,FALSE) -> 44326
C49: SALARIOS | D49: LUIS ROBERTO DA d | E49: 44326 | F49: 1421 | G49: Empresa 2 | H49: =VLOOKUP(E49,$E$2815:$H$2864,4,FALSE) -> 44326
C50: SALARIOS | D50: INGRID MACIEL | E50: 44326 | F50: 708 | G50: Empresa 2 | H50: =VLOOKUP(E50,$E$2815:$H$2864,4,FALSE) -> 44326
C51: RESCISAO | D51: FABIANO PEREIRA DOS SANTOS - LIBRELATO | E51: 44326 | F51: 522.99 | G51: Empresa 2 | H51: =VLOOKUP(E51,$E$2815:$H$2864,4,FALSE) -> 44326
C52: SALARIOS | D52: MISAEL - LIBRELATO | E52: 44326 | F52: 497 | G52: Empresa 2 | H52: =VLOOKUP(E52,$E$2815:$H$2864,4,FALSE) -> 44326
C53: SALARIOS | D53: KENIA DA ROSA | E53: 44326 | F53: 627 | G53: Empresa 2 | H53: =VLOOKUP(E53,$E$2815:$H$2864,4,FALSE) -> 44326
C54: RESCISAO | D54: NEILI CABRAL | E54: 44326 | F54: 1290.65 | G54: Empresa 2 | H54: =VLOOKUP(E54,$E$2815:$H$2864,4,FALSE) -> 44326
C55: SALARIOS | D55: FLAVIO LOPES | E55: 44326 | F55: 4284 | G55: Empresa 2 | H55: =VLOOKUP(E55,$E$2815:$H$2864,4,FALSE) -> 44326
C56: SALARIOS | D56: CLEBER - sacar em dinheiro | E56: 44326 | F56: =4172-678 -> 3494 | G56: Empresa 2 | H56: =VLOOKUP(E56,$E$2815:$H$2864,4,FALSE) -> 44326
C57: COMBUSTIVEL | D57: REEMBOLSO LUIS b | E57: 44326 | F57: 250 | G57: Distribuição de Lucros | H57: =VLOOKUP(E57,$E$2815:$H$2864,4,FALSE) -> 44326
C58: TERCEIROS | D58: MARCIA - LIMPEZA | E58: 44326 | F58: 70 | G58: Empresa 2 | H58: =VLOOKUP(E58,$E$2815:$H$2864,4,FALSE) -> 44326
C59: FÉRIAS | D59: ARIANE - SALDO - vcto 15/04 - sem falta | E59: 44326 | F59: 1521.5 | G59: Empresa 2 | H59: =VLOOKUP(E59,$E$2815:$H$2864,4,FALSE) -> 44326
C60: FÉRIAS | D60: RICARDO DEGGERONE - 01/03 | E60: 44326 | F60: 1050 | G60: Empresa 2 | H60: =VLOOKUP(E60,$E$2815:$H$2864,4,FALSE) -> 44326
C61: VIAGEM | D61: VOB HOTEL - vcto 22/04 - sem falta cartorio | E61: 44326 | F61: 866.6 | G61: Empresa 2 | H61: =VLOOKUP(E61,$E$2815:$H$2864,4,FALSE) -> 44326
C62: SALARIOS | D62: SALARIOS (Gabriel, Joel) | E62: 44326 | F62: =6078+4284+5083+2763-4284-2763 -> 11161 | G62: Empresa 2 | H62: =VLOOKUP(E62,$E$2815:$H$2864,4,FALSE) -> 44326
C63: SALARIOS | D63: PENSAO ALIMENTICIA | E63: 44326 | F63: =376.58+750.09+623.06 -> 1749.73 | G63: Empresa 2 | H63: =VLOOKUP(E63,$E$2815:$H$2864,4,FALSE) -> 44326
C64: VIAGEM | D64: JOEL - 01/03 | E64: 44326 | F64: 2826 | G64: Empresa 2 | H64: =VLOOKUP(E64,$E$2815:$H$2864,4,FALSE) -> 44326
C65: ACORDO | D65: ARISTIDES FAGUNDES - 03/07 - vcto 29/12 | E65: 44326 | F65: 1350 | G65: Empresa 2 | H65: =VLOOKUP(E65,$E$2815:$H$2864,4,FALSE) -> 44326
C66: RESCISAO | D66: ROGER JULIO - LIBRELATO | E66: 44326 | F66: 678.44 | G66: Empresa 2 | H66: =VLOOKUP(E66,$E$2815:$H$2864,4,FALSE) -> 44326
C67: RESCISAO | D67: GILBERTO DOS SANTOS - LIBRELATO | E67: 44326 | F67: 235.9 | G67: Empresa 2 | H67: =VLOOKUP(E67,$E$2815:$H$2864,4,FALSE) -> 44326
C68: SALARIOS | D68: MARIA ADELMA - LIBRELATO | E68: 44326 | F68: 114 | G68: Empresa 2 | H68: =VLOOKUP(E68,$E$2815:$H$2864,4,FALSE) -> 44326
C69: TRANSPORTE | D69: VISATE - 10 CARTOES | E69: 44327 | F69: 186 | G69: Empresa 1 | H69: =VLOOKUP(E69,$E$2815:$H$2864,4,FALSE) -> 44327
C70: MATERIAL | D70: DANICA - entrada | E70: 44327 | F70: 4318 | G70: Empresa 2 | H70: =VLOOKUP(E70,$E$2815:$H$2864,4,FALSE) -> 44327
C71: TRANSPORTE | D71: SCHEILA PACHECO - vcto 15/04 (saldo) | E71: 44327 | F71: 1600 | G71: Empresa 2 | H71: =VLOOKUP(E71,$E$2815:$H$2864,4,FALSE) -> 44327
C72: ALIMENTACAO | D72: RODRIGO CARDOSO - vcto 17/04 - sem falta - data já prorrogada | E72: 44327 | F72: 531 | G72: Empresa 1 | H72: =VLOOKUP(E72,$E$2815:$H$2864,4,FALSE) -> 44327
C73: MATERIAL | D73: KASI MOTORES- ASPMAQ- vcto 16/04 - sem falta - titulo prorrogado | E73: 44327 | F73: 1020.1 | G73: Empresa 1 | H73: =VLOOKUP(E73,$E$2815:$H$2864,4,FALSE) -> 44327
C74: MATERIAL | D74: ACOPLANO - tubos WSUL | E74: 44327 | F74: 844.6 | G74: Empresa 1 | H74: =VLOOKUP(E74,$E$2815:$H$2864,4,FALSE) -> 44327
C75: SOCIOS | D75: RETIRADA PAULO d (R$ 1.200,00 paulo e 800,00 felipe) | E75: 44327 | F75: 2000 | G75: Distribuição de Lucros | H75: =VLOOKUP(E75,$E$2815:$H$2864,4,FALSE) -> 44327
... C80: SALARIOS | D80: BRUNO SOUZA - trabalhou de 20 a 30/04 no pavilhao pf | E80: 44327 | F80: 594 | G80: Empresa 2 | H80: =VLOOKUP(E80,$E$2815:$H$2864,4,FALSE) -> 44327
C81: ALIMENTACAO | D81: RESTAURANTE ZAPAROLLI - vcto 30/04 (sem falta) | E81: 44327 | F81: =3812+4000+85 -> 7897 | G81: Empresa 2 | H81: =VLOOKUP(E81,$E$2815:$H$2864,4,FALSE) -> 44327
C82: TERCEIROS | D82: SERGIO DAMBROS - NF 37 - (PIX 28186826068) sem falta qdo entrar R$ da estufa | E82: 44327 | F82: 1680 | G82: Empresa 1 | H82: =VLOOKUP(E82,$E$2815:$H$2864,4,FALSE) -> 44327
C83: ALIMENTACAO | D83: ALIMENTAR - vcto 08/04 - não permite compra sem este pgto | E83: 44327 | F83: 1833.6 | G83: Empresa 2 | H83: =VLOOKUP(E83,$E$2815:$H$2864,4,FALSE) -> 44327
C84: COMUNICACAO | D84: NET - 20/04 | E84: 44327 | F84: 225.94 | G84: Empresa 2 | H84: =VLOOKUP(E84,$E$2815:$H$2864,4,FALSE) -> 44327
C85: EPI | D85: MAJUSEG | E85: 44327 | F85: 993.84 | G85: Empresa 2 | H85: =VLOOKUP(E85,$E$2815:$H$2864,4,FALSE) -> 44327
C86: EPI | D86: MAJUSEG | E86: 44327 | F86: 774.68 | G86: Empresa 2 | H86: =VLOOKUP(E86,$E$2815:$H$2864,4,FALSE) -> 44327
C87: EPI | D87: MAJUSEG | E87: 44327 | F87: 755.56 | G87: Empresa 2 | H87: =VLOOKUP(E87,$E$2815:$H$2864,4,FALSE) -> 44327
C88: SALARIOS | D88: SABRINA - LIBRELATO | E88: 44327 | F88: 354 | G88: Empresa 2 | H88: =VLOOKUP(E88,$E$2815:$H$2864,4,FALSE) -> 44327
C89: EXPEDIENTE | D89: INGRID CANELLO - GRAFICA VISAO - vcto 20/04 - sem falta - cartorio | E89: 44328 | F89: 413.24 | G89: Empresa 2 | H89: =VLOOKUP(E89,$E$2815:$H$2864,4,FALSE) -> 44328
C90: RESCISAO | D90: ROBERTO COVAS - metade | E90: 44328 | F90: 1025 | G90: Empresa 2 | H90: =VLOOKUP(E90,$E$2815:$H$2864,4,FALSE) -> 44328
C91: RESCISAO | D91: LUIS ROBERTO DA d | E91: 44328 | F91: 1295.15 | G91: Empresa 2 | H91: =VLOOKUP(E91,$E$2815:$H$2864,4,FALSE) -> 44328
C92: COMUNICACAO | D92: CLARO - 20/04 | E92: 44328 | F92: =42.92+1394.6+189.33 -> 1626.85 | G92: Empresa 1 | H92: =VLOOKUP(E92,$E$2815:$H$2864,4,FALSE) -> 44328
C93: SALARIOS | D93: PENSAO ALIMENTICIA REF FÉRIAS MARCIO SOARES | E93: 44328 | F93: 643.58 | G93: Empresa 2 | H93: =VLOOKUP(E93,$E$2815:$H$2864,4,FALSE) -> 44328
C94: SOCIOS | D94: RETIRADA ROGERIO | E94: 44328 | F94: 3000 | G94: Distribuição de Lucros | H94: =VLOOKUP(E94,$E$2815:$H$2864,4,FALSE) -> 44328
C95: MATERIAL | D95: FUSOPAR | E95: 44328 | F95: 298.65 | G95: Empresa 1 | H95: =VLOOKUP(E95,$E$2815:$H$2864,4,FALSE) -> 44328
C96: MANUTENCAO | D96: STEDILE - vcto 01/05 | E96: 44328 | F96: 207.26 | G96: Empresa 1 | H96: =VLOOKUP(E96,$E$2815:$H$2864,4,FALSE) -> 44328
C97: VEICULOS | D97: MECANICA ADEMIR - vcto 28/04 | E97: 44328 | F97: 604.7 | G97: Empresa 1 | H97: =VLOOKUP(E97,$E$2815:$H$2864,4,FALSE) -> 44328
C98: EPI | D98: ZAPA - vcto 08/05 | E98: 44328 | F98: 328.97 | G98: Empresa 2 | H98: =VLOOKUP(E98,$E$2815:$H$2864,4,FALSE) -> 44328
C99: IMPOSTOS | D99: ART CREA - ROGERIO/WSUL | E99: 44328 | F99: 88.78 | G99: Empresa 1 | H99: =VLOOKUP(E99,$E$2815:$H$2864,4,FALSE) -> 44328
C100: MATERIAL | D100: LUCHETTI COM DE GAS | E100: 44328 | F100: 90.05 | G100: Empresa 1 | H100: =VLOOKUP(E100,$E$2815:$H$2864,4,FALSE) -> 44328
C101: VIAGEM | D101: VOB HOTEL | E101: 44328 | F101: 456 | G101: Empresa 2 | H101: =VLOOKUP(E101,$E$2815:$H$2864,4,FALSE) -> 44328
C102: EPI | D102: CORSUL | E102: 44329 | F102: 239.55 | G102: Empresa 2 | H102: =VLOOKUP(E102,$E$2815:$H$2864,4,FALSE) -> 44329
C103: MANUTENCAO | D103: BT5 | E103: 44329 | F103: 500 | G103: Empresa 1 | H103: =VLOOKUP(E103,$E$2815:$H$2864,4,FALSE) -> 44329
C104: EPI | D104: ZAPA - vcto 29/04 - cartorio | E104: 44329 | F104: 535.82 | G104: Empresa 2 | H104: =VLOOKUP(E104,$E$2815:$H$2864,4,FALSE) -> 44329
...

Sheet Fluxo_05_21
B1: =IF(B5=1,"Domingo",IF(B5=2,"Segunda",IF(B5=3,"Terça",IF(B5=4,"Quarta",IF(B5=5,"Quinta",IF(B5=6,"Sexta",IF(B5=7,"Sábado",0))))))) -> Segunda | C1: =IF(C5=1,"Domingo",IF(C5=2,"Segunda",IF(C5=3,"Terça",IF(C5=4,"Quarta",IF(C5=5,"Quinta",IF(C5=6,"Sexta",IF(C5=7,"Sábado",0))))))) -> Terça | D1: =IF(D5=1,"Domingo",IF(D5=2,"Segunda",IF(D5=3,"Terça",IF(D5=4,"Quarta",IF(D5=5,"Quinta",IF(D5=6,"Sexta",IF(D5=7,"Sábado",0))))))) -> Quarta | E1: =IF(E5=1,"Domingo",IF(E5=2,"Segunda",IF(E5=3,"Terça",IF(E5=4,"Quarta",IF(E5=5,"Quinta",IF(E5=6,"Sexta",IF(E5=7,"Sábado",0))))))) -> Quinta | F1: =IF(F5=1,"Domingo",IF(F5=2,"Segunda",IF(F5=3,"Terça",IF(F5=4,"Quarta",IF(F5=5,"Quinta",IF(F5=6,"Sexta",IF(F5=7,"Sábado",0))))))) -> Sexta | G1: =IF(G5=1,"Domingo",IF(G5=2,"Segunda",IF(G5=3,"Terça",IF(G5=4,"Quarta",IF(G5=5,"Quinta",IF(G5=6,"Sexta",IF(G5=7,"Sábado",0))))))) -> Segunda | H1: =IF(H5=1,"Domingo",IF(H5=2,"Segunda",IF(H5=3,"Terça",IF(H5=4,"Quarta",IF(H5=5,"Quinta",IF(H5=6,"Sexta",IF(H5=7,"Sábado",0))))))) -> Terça | I1: =IF(I5=1,"Domingo",IF(I5=2,"Segunda",IF(I5=3,"Terça",IF(I5=4,"Quarta",IF(I5=5,"Quinta",IF(I5=6,"Sexta",IF(I5=7,"Sábado",0))))))) -> Quarta | ... V1: =IF(V5=1,"Domingo",IF(V5=2,"Segunda",IF(V5=3,"Terça",IF(V5=4,"Quarta",IF(V5=5,"Quinta",IF(V5=6,"Sexta",IF(V5=7,"Sábado",0))))))) -> Segunda
A2: Localizado no banco | B2: =B29 -> 44319 | C2: =C29 -> 44320 | D2: =D29 -> 44321 | E2: =E29 -> 44322 | F2: =F29 -> 44323 | G2: =G29 -> 44326 | H2: =H29 -> 44327 | I2: =I29 -> 44328 | ... V2: =V29 -> 44347
A4: SALDO INICIAL | B4: =Fluxo_04_21!V38 -> 5598.23 | C4: =B38 -> 887.31 | D4: =C38 -> 7106.15 | E4: =D38 -> -3786.91 | F4: =E38 -> -15777.09 | G4: =F38 -> -20664.61 | H4: =G38 -> -17794.42 | I4: =H38 -> -15885.54 | J4: =I38 -> 7977.23 | ... V4: =U38 -> 16204.96
B5: =WEEKDAY(B2) -> 2 | C5: =WEEKDAY(C2) -> 3 | D5: =WEEKDAY(D2) -> 4 | E5: =WEEKDAY(E2) -> 5 | F5: =WEEKDAY(F2) -> 6 | G5: =WEEKDAY(G2) -> 2 | H5: =WEEKDAY(H2) -> 3 | I5: =WEEKDAY(I2) -> 4 | ... V5: =WEEKDAY(V2) -> 2
A6: RECEBIMENTOS (OPERAÇÃO) | B6: =SUM(B7:B26) -> 8736 | C6: =SUM(C7:C26) -> 12543.84 | D6: =SUM(D7:D26) -> 63107.94 | E6: =SUM(E7:E26) -> 0 | F6: =SUM(F7:F26) -> 17482.71 | G6: =SUM(G7:G26) -> 40678 | H6: =SUM(H7:H26) -> 34892.2 | I6: =SUM(I7:I26) -> 33941 | ... V6: =SUM(V7:V26) -> 0
A7: MARCOPOLO/SEMAN | F7: 17482.71 | G7: =14480.85-830 -> 13650.85 | J7: 17319.25 | Q7: =850 -> 850
A8: MARCOPOLO | D8: 34221.94 | O8: 39164.69
A9: VOLARE | C9: 12543.84 | D9: 28886 | G9: 9700 | H9: =26510.26-338.72 -> 26171.54 | L9: =20000 -> 20000 | O9: =4093.6 -> 4093.6 | T9: 45810.49
A10: HIDROVER | B10: 8736 | U10: =7338.24+1834.56 -> 9172.8
A11: WSUL | I11: 33941 | U11: 35729.55
A12: RUGERI | G12: 2604.97 | M12: 2648.16
A13: CIFERAL
A14: SAN MARINO | H14: =7252.13 -> 7252.13 | N14: 3270.52 | U14: 6098.59
A15: LIBRELATO | J15: =3653+3399.7+3653.84 -> 10706.54 | T15: =1594.4+4628.18+4473.18+3853.14 -> 14548.9
A16: RANDON | G16: 3135
A17: Previsao Estufa | G17: 11587.18
A18: FLORENSE | H18: 1468.53
A27: PAGAMENTOS PROGRAMADOS
A28: Soma de Valor | B28: Pagto.
A29: tipo | B29: 44319 | C29: 44320 | D29: 44321 | E29: 44322 | F29: 44323 | G29: 44326 | H29: 44327 | I29: 44328 | J29: 44329 | K29: 44330 | L29: 44333 | M29: 44334 | N29: 44335 | O29: 44336 | P29: 44337 | Q29: 44340 | R29: 44341 | S29: 44342 | T29: 44343 | U29: 44344 | V29: 44347 | W29: Total Geral
A30: PARTICULAR | C30: 50 | D30: 878.5 | E30: 100 | G30: 250 | H30: 4500 | I30: 3000 | J30: 1805.32 | K30: 2589.31 | L30: 2500 | P30: 2325.74 | T30: 5135.06 | U30: 5818.11 | V30: 1020.5 | W30: 29972.54
A31: VENTURE | B31: 10224.59 | C31: 1364.88 | D31: 8907.5 | E31: 4497 | F31: 4632 | G31: 2000 | H31: 5336.7 | I31: 2916.29 | J31: 6073.26 | K31: 3944.5 | L31: 5260.41 | M31: 1181.25 | O31: 970.56 | P31: 5727.46 | Q31: 2188.98 | R31: 80 | S31: 0 | T31: 6137.47 | U31: 8697.06 | W31: 80139.91
A32: SOLUTEC | J32: 1288.65 | V32: 1794.47 | W32: 3083.12
A33: PKS | K33: 380.52 | L33: 3594.05 | W33: 3974.57
A34: SEMAN | B34: 3222.33 | C34: 4910.12 | D34: 64215 | E34: 7393.18 | F34: 17738.23 | G34: 35557.81 | H34: 23146.62 | I34: 4161.94 | J34: 20262.1 | K34: 10713.64 | L34: 4720.5 | M34: 2881.9 | N34: 4313.83 | O34: 18686.76 | P34: 10016.13 | Q34: 2573.22 | R34: 5375.44 | T34: 35957.11 | U34: 18942.02 | V34: 25322.7 | W34: 320110.58
A35: BSP | Q35: 1045 | W35: 1045
A36: Total Geral | B36: 13446.92 | C36: 6325 | D36: 74001 | E36: 11990.18 | F36: 22370.23 | G36: 37807.81 | H36: 32983.32 | I36: 10078.23 | J36: 29429.33 | K36: 17627.97 | L36: 16074.96 | M36: 4063.15 | N36: 4313.83 | O36: 19657.32 | P36: 18069.33 | Q36: 5807.2 | R36: 5455.44 | S36: 0 | T36: 47229.64 | U36: 33457.19 | V36: 28137.67 | W36: 438325.72
A38: SALDO FINAL | B38: =B4+B6-GETPIVOTDATA("Valor",$A$28,"Pagto.",DATE(2021,5,3)) -> 887.31 | C38: =C4+C6-GETPIVOTDATA("Valor",$A$28,"Pagto.",DATE(2021,5,4)) -> 7106.15 | D38: =D4+D6-GETPIVOTDATA("Valor",$A$28,"Pagto.",DATE(2021,5,5)) -> -3786.91 | E38: =E4+E6-GETPIVOTDATA("Valor",$A$28,"Pagto.",DATE(2021,5,6)) -> -15777.09 | F38: =F4+F6-GETPIVOTDATA("Valor",$A$28,"Pagto.",DATE(2021,5,7)) -> -20664.61 | G38: =G4+G6-GETPIVOTDATA("Valor",$A$28,"Pagto.",DATE(2021,5,10)) -> -17794.42 | H38: =H4+H6-GETPIVOTDATA("Valor",$A$28,"Pagto.",DATE(2021,5,11)) -> -15885.54 | I38: =I4+I6-GETPIVOTDATA("Valor",$A$28,"Pagto.",DATE(2021,5,12)) -> 7977.23 | J38: =J4+J6-GETPIVOTDATA("Valor",$A$28,"Pagto.",DATE(2021,5,13)) -> 6573.69 | K38: =K4+K6-GETPIVOTDATA("Valor",$A$28,"Pagto.",DATE(2021,5,14)) -> -11054.28 | L38: =L4+L6-GETPIVOTDATA("Valor",$A$28,"Pagto.",DATE(2021,5,17)) -> -7129.24 | M38: =M4+M6-GETPIVOTDATA("Valor",$A$28,"Pagto.",DATE(2021,5,18)) -> -8544.23 | N38: =N4+N6-GETPIVOTDATA("Valor",$A$28,"Pagto.",DATE(2021,5,19)) -> -9587.54 | O38: =O4+O6-GETPIVOTDATA("Valor",$A$28,"Pagto.",DATE(2021,5,20)) -> 14013.43 | P38: =P4+P6-GETPIVOTDATA("Valor",$A$28,"Pagto.",DATE(2021,5,21)) -> -4055.9 | Q38: =Q4+Q6-GETPIVOTDATA("Valor",$A$28,"Pagto.",DATE(2021,5,24)) -> -9013.1 | R38: =R4+R6-GETPIVOTDATA("Valor",$A$28,"Pagto.",DATE(2021,5,25)) -> -14468.54 | S38: =S4+S6-GETPIVOTDATA("Valor",$A$28,"Pagto.",DATE(2021,5,26)) -> -14468.54 | T38: =T4+T6-GETPIVOTDATA("Valor",$A$28,"Pagto.",DATE(2021,5,27)) -> -1338.79 | U38: =U4+U6-GETPIVOTDATA("Valor",$A$28,"Pagto.",DATE(2021,5,28)) -> 16204.96 | V38: =V4+V6-GETPIVOTDATA("Valor",$A$28,"Pagto.",DATE(2021,5,31)) -> -11932.71

Sheet 04_21
A1: 0 | B1: tm | C1: CodCli | D1: Nome | E1: dtvcto | F1: Valor | G1: tipo | H1: Pagto.
C2: EXPEDIENTE | D2: LICEIS | E2: 44287 | F2: 215.8 | G2: Empresa 2 | H2: =VLOOKUP(E2,$E$2818:$H$2876,4,FALSE) -> 44287
C3: SOCIOS | D3: RETIRADA PAULO d | E3: 44287 | F3: 2000 | G3: Distribuição de Lucros | H3: =VLOOKUP(E3,$E$2818:$H$2876,4,FALSE) -> 44287
C4: EPI | D4: ZAPA | E4: 44287 | F4: 312 | G4: Empresa 2 | H4: =VLOOKUP(E4,$E$2818:$H$2876,4,FALSE) -> 44287
C5: COMBUSTIVEL | D5: TEONAS - MENSAL. Obs. Disponibilizar em 01.04 | E5: 44287 | F5: 150 | G5: Empresa 2 | H5: =VLOOKUP(E5,$E$2818:$H$2876,4,FALSE) -> 44287
C6: COMBUSTIVEL | D6: GENILSON - MENSAL Obs. Disponibilizar em 01.04 | E6: 44287 | F6: 300 | G6: Empresa 2 | H6: =VLOOKUP(E6,$E$2818:$H$2876,4,FALSE) -> 44287
C7: SALARIOS | D7: DIF HORAS KIMBERLY | E7: 44287 | F7: 255 | G7: Empresa 2 | H7: =VLOOKUP(E7,$E$2818:$H$2876,4,FALSE) -> 44287
C8: BANCOS | D8: JUROS E DESPESAS BANCARIAS | E8: 44287 | F8: =2310.37+125+423+340+490 -> 3688.37 | G8: Empresa 1 | H8: =VLOOKUP(E8,$E$2818:$H$2876,4,FALSE) -> 44287
C9: MANUTENCAO | D9: KIPEL | E9: 44287 | F9: 137 | G9: Empresa 2 | H9: =VLOOKUP(E9,$E$2818:$H$2876,4,FALSE) -> 44287
C10: COMBUSTIVEL | D10: MECANICA | E10: 44287 | F10: 100 | G10: Empresa 2 | H10: =VLOOKUP(E10,$E$2818:$H$2876,4,FALSE) -> 44287
C11: COMBUSTIVEL | D11: CLEBER | E11: 44287 | F11: 50 | G11: Empresa 2 | H11: =VLOOKUP(E11,$E$2818:$H$2876,4,FALSE) -> 44287
C12: SALARIOS | D12: SALARIOS - ARQUIVO PRODUCAO | E12: 44287 | F12: 31581 | G12: Empresa 2 | H12: =VLOOKUP(E12,$E$2818:$H$2876,4,FALSE) -> 44287
C13: EPI | D13: JUSTINA - CHEQUE 23/03 | E13: 44288 | F13: 450 | G13: Empresa 2 | H13: =VLOOKUP(E13,$E$2818:$H$2876,4,FALSE) -> 44291
C14: EPI | D14: JUSTINA - CHEQUE 31/03 | E14: 44288 | F14: 1125 | G14: Empresa 2 | H14: =VLOOKUP(E14,$E$2818:$H$2876,4,FALSE) -> 44291
C15: PARCELAMENTO | D15: EMPRESTIMO FOLHA BB - 04/30 | E15: 44289 | F15: 2315.35 | G15: Empresa 2 | H15: =VLOOKUP(E15,$E$2818:$H$2876,4,FALSE) -> 44291
C16: COMBUSTIVEL | D16: REEMBOLSAR LUIS b | E16: 44290 | F16: =61.52+200+250 -> 511.52 | G16: Distribuição de Lucros | H16: =VLOOKUP(E16,$E$2818:$H$2876,4,FALSE) -> 44291
C17: EXPEDIENTE | D17: REEMBOLSAR DALNIR COMPRA LAMPADAS | E17: 44291 | F17: 100 | G17: Empresa 2 | H17: =VLOOKUP(E17,$E$2818:$H$2876,4,FALSE) -> 44291
C18: SOCIOS | D18: RETIRADA LUIS b | E18: 44291 | F18: 2500 | G18: Distribuição de Lucros | H18: =VLOOKUP(E18,$E$2818:$H$2876,4,FALSE) -> 44291
C19: SOCIOS | D19: SEGURO DE VIDA RUBENS c | E19: 44291 | F19: 725 | G19: Distribuição de Lucros | H19: =VLOOKUP(E19,$E$2818:$H$2876,4,FALSE) -> 44291
C20: COMBUSTIVEL | D20: LUIS b | E20: 44291 | F20: 200 | G20: Distribuição de Lucros | H20: =VLOOKUP(E20,$E$2818:$H$2876,4,FALSE) -> 44291
C21: TERCEIROS | D21: LIMPEZA MARCIA | E21: 44291 | F21: 70 | G21: Empresa 2 | H21: =VLOOKUP(E21,$E$2818:$H$2876,4,FALSE) -> 44291
C22: ACORDO | D22: ARTHUR - CIFERAL - 03/08 - vcto 18/02 | E22: 44291 | F22: 1500 | G22: Empresa 2 | H22: =VLOOKUP(E22,$E$2818:$H$2876,4,FALSE) -> 44291
C23: ACORDO | D23: LEONARDO - CIFERAL - 03/14 - vcto 18/02 | E23: 44291 | F23: 1500 | G23: Empresa 2 | H23: =VLOOKUP(E23,$E$2818:$H$2876,4,FALSE) -> 44291
C24: ACORDO | D24: SAMUEL - CIFERAL - 03/09 - vcto 18/02 | E24: 44291 | F24: 1500 | G24: Empresa 2 | H24: =VLOOKUP(E24,$E$2818:$H$2876,4,FALSE) -> 44291
C25: SALARIOS | D25: SALARIOS - ARQUIVO LIDERES E SEGURANCA | E25: 44291 | F25: =8476+602+833+292+2654+2077+2469 -> 17403 | G25: Empresa 2 | H25: =VLOOKUP(E25,$E$2818:$H$2876,4,FALSE) -> 44291
C26: SALARIOS | D26: SALARIOS - VOLARE/CIFERAL | E26: 44292 | F26: =22440+622+1009 -> 24071 | G26: Empresa 2 | H26: =VLOOKUP(E26,$E$2818:$H$2876,4,FALSE) -> 44292
C27: PARCELAMENTO | D27: EMPRESTIMO FOLHA BB - 05/30 | E27: 44292 | F27: 2201.2 | G27: Empresa 2 | H27: =VLOOKUP(E27,$E$2818:$H$2876,4,FALSE) -> 44292
C28: SOCIOS | D28: IPVA CAMINHONETE LUIS b | E28: 44292 | F28: 882.17 | G28: Distribuição de Lucros | H28: =VLOOKUP(E28,$E$2818:$H$2876,4,FALSE) -> 44292
C29: FÉRIAS | D29: FLAVIO DA d LOPES - vcto 02/03 - pagar integral | E29: 44292 | F29: 5901 | G29: Empresa 2 | H29: =VLOOKUP(E29,$E$2818:$H$2876,4,FALSE) -> 44292
C30: MATERIAL | D30: FERRAGEM DO TONINHO | E30: 44292 | F30: 83.16 | G30: Empresa 2 | H30: =VLOOKUP(E30,$E$2818:$H$2876,4,FALSE) -> 44292
C31: SALARIOS | D31: SALARIOS - FUNCIONARIOS SEM CONTA - CAX SUL (dinheiro) | E31: 44293 | F31: 16811 | G31: Empresa 2 | H31: =VLOOKUP(E31,$E$2818:$H$2876,4,FALSE) -> 44293
C32: SALARIOS | D32: SALARIO CLEBER MELO LINS - em dinheiro | E32: 44293 | F32: 3729 | G32: Empresa 2 | H32: =VLOOKUP(E32,$E$2818:$H$2876,4,FALSE) -> 44293
C33: SALARIOS | D33: SALETE PAIM - pf | E33: 44293 | F33: 1212 | G33: Empresa 2 | H33: =VLOOKUP(E33,$E$2818:$H$2876,4,FALSE) -> 44293
C34: SALARIOS | D34: SALARIOS - FUNCIONARIOS SEM CONTA - LIBRELATO (dinheiro) | E34: 44293 | F34: =2662-622 -> 2040 | G34: Empresa 2 | H34: =VLOOKUP(E34,$E$2818:$H$2876,4,FALSE) -> 44293
C35: MATERIAL | D35: CELETRO - email Dalnir | E35: 44293 | F35: 260 | G35: Empresa 2 | H35: =VLOOKUP(E35,$E$2818:$H$2876,4,FALSE) -> 44293
C36: TERCEIROS | D36: TRABALHOS LUAN - LT MANUTENCAO - vcto 11/12 | E36: 44293 | F36: 1000 | G36: Empresa 2 | H36: =VLOOKUP(E36,$E$2818:$H$2876,4,FALSE) -> 44293
C37: SALARIOS | D37: PENSAO ALIMENTICIA JOSE LUIS MARIA RODRIGUES | E37: 44293 | F37: 308.13 | G37: Empresa 2 | H37: =VLOOKUP(E37,$E$2818:$H$2876,4,FALSE) -> 44293
C38: EPI | D38: CORSUL | E38: 44294 | F38: 311.78 | G38: Empresa 2 | H38: =VLOOKUP(E38,$E$2818:$H$2876,4,FALSE) -> 44294
C39: MATERIAL | D39: LF - carrinho de mao | E39: 44294 | F39: 380 | G39: Empresa 2 | H39: =VLOOKUP(E39,$E$2818:$H$2876,4,FALSE) -> 44294
C40: MATERIAL | D40: MUTERLE | E40: 44294 | F40: 90 | G40: Empresa 2 | H40: =VLOOKUP(E40,$E$2818:$H$2876,4,FALSE) -> 44294
C41: TRANSPORTE | D41: VISATE - 30 CARTOES | E41: 44294 | F41: 558 | G41: Empresa 2 | H41: =VLOOKUP(E41,$E$2818:$H$2876,4,FALSE) -> 44294
C42: VIAGEM | D42: GABRIEL/LIRANE | E42: 44295 | F42: 410.02 | G42: Empresa 2 | H42: =VLOOKUP(E42,$E$2818:$H$2876,4,FALSE) -> 44295
C43: COMBUSTIVEL | D43: FLAVIO - CLEBER - PAULO EDUARDO | E43: 44295 | F43: 300 | G43: Empresa 2 | H43: =VLOOKUP(E43,$E$2818:$H$2876,4,FALSE) -> 44295
C44: RESCISAO | D44: LUCIANE OLIVEIRA - em dinheiro | E44: 44295 | F44: 95.18 | G44: Empresa 2 | H44: =VLOOKUP(E44,$E$2818:$H$2876,4,FALSE) -> 44295
C45: VEICULOS | D45: MANO MOTORS - UNO | E45: 44295 | F45: 200 | G45: Empresa 1 | H45: =VLOOKUP(E45,$E$2818:$H$2876,4,FALSE) -> 44295
C46: MATERIAL | D46: POLIMEROS SUL | E46: 44295 | F46: 27 | G46: Empresa 1 | H46: =VLOOKUP(E46,$E$2818:$H$2876,4,FALSE) -> 44295
... C56: FÉRIAS | D56: FABIANA DECO - PARCELA 02/03 | E56: 44299 | F56: 1830 | G56: Empresa 1 | H56: =VLOOKUP(E56,$E$2818:$H$2876,4,FALSE) -> 44299
C57: SALARIOS | D57: PENSAO ALIMENTICIA | E57: 44299 | F57: =308.13+750.08+750.33-308.13 -> 1500.41 | G57: Empresa 2 | H57: =VLOOKUP(E57,$E$2818:$H$2876,4,FALSE) -> 44299
C58: SALARIOS | D58: JOEL | E58: 44299 | F58: 6078 | G58: Empresa 2 | H58: =VLOOKUP(E58,$E$2818:$H$2876,4,FALSE) -> 44299
C59: SALARIOS | D59: SALARIOS - Nelci, Gabriel (parte) | E59: 44299 | F59: =2094+2541 -> 4635 | G59: Empresa 2 | H59: =VLOOKUP(E59,$E$2818:$H$2876,4,FALSE) -> 44299
C60: SALARIOS | D60: PAULO EDUARDO | E60: 44299 | F60: 2885 | G60: Empresa 2 | H60: =VLOOKUP(E60,$E$2818:$H$2876,4,FALSE) -> 44299
C61: SALARIOS | D61: SALARIOS - Ramon | E61: 44299 | F61: 2892 | G61: Empresa 2 | H61: =VLOOKUP(E61,$E$2818:$H$2876,4,FALSE) -> 44299
C62: TERCEIROS | D62: LIMPEZA MARCIA | E62: 44300 | F62: 70 | G62: Empresa 2 | H62: =VLOOKUP(E62,$E$2818:$H$2876,4,FALSE) -> 44300
C63: ENERGIA | D63: RGE - vcto 04/03/21 | E63: 44300 | F63: 1106.44 | G63: Empresa 1 | H63: =VLOOKUP(E63,$E$2818:$H$2876,4,FALSE) -> 44300
C64: ENERGIA | D64: RGE - vcto 04/03/21 | E64: 44300 | F64: 959.21 | G64: Empresa 1 | H64: =VLOOKUP(E64,$E$2818:$H$2876,4,FALSE) -> 44300
C65: COMBUSTIVEL | D65: REEMBOLSAR DALNIR - COMBUSTIVEL UNO | E65: 44300 | F65: 50 | G65: Empresa 2 | H65: =VLOOKUP(E65,$E$2818:$H$2876,4,FALSE) -> 44300
C66: MATERIAL | D66: REEMBOLSAR DALNIR - STEDILE | E66: 44300 | F66: 50 | G66: Empresa 1 | H66: =VLOOKUP(E66,$E$2818:$H$2876,4,FALSE) -> 44300
C67: INFORMATICA | D67: BIG HEAD - COMP.FLAVIO | E67: 44300 | F67: 60 | G67: Empresa 2 | H67: =VLOOKUP(E67,$E$2818:$H$2876,4,FALSE) -> 44300
C68: CONSUMO | D68: SIMOQUIMICA | E68: 44300 | F68: 203.75 | G68: Empresa 2 | H68: =VLOOKUP(E68,$E$2818:$H$2876,4,FALSE) -> 44300
C69: COMBUSTIVEL | D69: REEMBOLSAR ROGERIO | E69: 44300 | F69: 100 | G69: Distribuição de Lucros | H69: =VLOOKUP(E69,$E$2818:$H$2876,4,FALSE) -> 44300
C70: TERCEIROS | D70: CARTORIO MARCOS | E70: 44300 | F70: 63.51 | G70: Empresa 1 | H70: =VLOOKUP(E70,$E$2818:$H$2876,4,FALSE) -> 44300
C71: TERCEIROS | D71: SERGIO DAMBROS - NF 15 - (PIX 28186826068) sem falta, já combinado com ele | E71: 44300 | F71: 1350 | G71: Empresa 1 | H71: =VLOOKUP(E71,$E$2818:$H$2876,4,FALSE) -> 44300
... C76: MANUTENCAO | D76: BT5 | E76: 44300 | F76: 120 | G76: Empresa 2 | H76: =VLOOKUP(E76,$E$2818:$H$2876,4,FALSE) -> 44300
C77: SALARIOS | D77: SALARIOS - Nelci, Dalnir, Fabiana, Gabriel (saldo) | E77: 44301 | F77: =14322+9110-1469-2009-4254-2892-2094-2541 -> 8173 | G77: Empresa 2 | H77: =VLOOKUP(E77,$E$2818:$H$2876,4,FALSE) -> 44301
C78: FÉRIAS | D78: NELCI - 01/03 | E78: 44301 | F78: 1272 | G78: Empresa 2 | H78: =VLOOKUP(E78,$E$2818:$H$2876,4,FALSE) -> 44301
C79: FÉRIAS | D79: DALNIR - 02/03 | E79: 44301 | F79: 1996 | G79: Empresa 1 | H79: =VLOOKUP(E79,$E$2818:$H$2876,4,FALSE) -> 44301
C80: TERCEIROS | D80: ART - ROGERIO - VOLARE | E80: 44301 | F80: =88.78+88.78 -> 177.56 | G80: Empresa 1 | H80: =VLOOKUP(E80,$E$2818:$H$2876,4,FALSE) -> 44301
C81: EPI | D81: CORSUL | E81: 44301 | F81: 404.9 | G81: Empresa 2 | H81: =VLOOKUP(E81,$E$2818:$H$2876,4,FALSE) -> 44301
C82: SAUDE | D82: UNIMED | E82: 44301 | F82: 3594.05 | G82: PKS | H82: =VLOOKUP(E82,$E$2818:$H$2876,4,FALSE) -> 44301
C83: MATERIAL | D83: KIPEL - reembolsar Cleber | E83: 44301 | F83: 39.2 | G83: Empresa 1 | H83: =VLOOKUP(E83,$E$2818:$H$2876,4,FALSE) -> 44301
C84: COMBUSTIVEL | D84: REEMBOLSAR ROGERIO | E84: 44301 | F84: 150 | G84: Distribuição de Lucros | H84: =VLOOKUP(E84,$E$2818:$H$2876,4,FALSE) -> 44301
C85: SAUDE | D85: REEMBOLSO MEDICACAO IVANETE ZANOTTO | E85: 44301 | F85: 209.5 | G85: Empresa 2 | H85: =VLOOKUP(E85,$E$2818:$H$2876,4,FALSE) -> 44301
C86: VEICULOS | D86: IPVA UNO IUZ7335 | E86: 44301 | F86: 627 | G86: Empresa 2 | H86: =VLOOKUP(E86,$E$2818:$H$2876,4,FALSE) -> 44301
C87: RESCISAO | D87: DANIEL FERRARI + FGTS | E87: 44301 | F87: =32.98+603.83 -> 636.81 | G87: Empresa 2 | H87: =VLOOKUP(E87,$E$2818:$H$2876,4,FALSE) -> 44301
C88: EPI | D88: MAJUSEG | E88: 44301 | F88: 1245.96 | G88: Empresa 2 | H88: =VLOOKUP(E88,$E$2818:$H$2876,4,FALSE) -> 44301
C89: VIAGEM | D89: FLAVIO - CRICIUMA | E89: 44301 | F89: 217.4 | G89: Empresa 2 | H89: =VLOOKUP(E89,$E$2818:$H$2876,4,FALSE) -> 44301
C90: COMBUSTIVEL | D90: CLEBER | E90: 44301 | F90: 100 | G90: Empresa 2 | H90: =VLOOKUP(E90,$E$2818:$H$2876,4,FALSE) -> 44301
C91: SAUDE | D91: PROMED | E91: 44301 | F91: 80.25 | G91: Empresa 1 | H91: =VLOOKUP(E91,$E$2818:$H$2876,4,FALSE) -> 44301
C92: CONVENIO | D92: MICROEMPA | E92: 44301 | F92: 84 | G92: Empresa 2 | H92: =VLOOKUP(E92,$E$2818:$H$2876,4,FALSE) -> 44301
C93: COMUNICACAO | D93: CLARO - vcto 20/03 | E93: 44301 | F93: =177.15+42.88+1322.3 -> 1542.33 | G93: Empresa 1 | H93: =VLOOKUP(E93,$E$2818:$H$2876,4,FALSE) -> 44301
C94: VEICULOS | D94: FORZZA - 03/03 | E94: 44301 | F94: 430.83 | G94: Empresa 1 | H94: =VLOOKUP(E94,$E$2818:$H$2876,4,FALSE) -> 44301
C95: MATERIAL | D95: IBP METALURGICA - PAGAR SEM FALTA (cfe Sr.Paulo) | E95: 44301 | F95: 350.87 | G95: Empresa 1 | H95: =VLOOKUP(E95,$E$2818:$H$2876,4,FALSE) -> 44301
C96: CURSO | D96: RAFAEL SCOPEL - vcto 10/03 | E96: 44301 | F96: 1500 | G96: Empresa 2 | H96: =VLOOKUP(E96,$E$2818:$H$2876,4,FALSE) -> 44301
C97: VEICULOS | D97: MECANIA ADEMIR - CARRO CLEBER - 02/03 | E97: 44301 | F97: 566.66 | G97: Empresa 1 | H97: =VLOOKUP(E97,$E$2818:$H$2876,4,FALSE) -> 44301
C98: RESCISAO | D98: FGTS RESCISORIO FABINAO PEREIRA - Criciuma | E98: 44301 | F98: 29.13 | G98: Empresa 2 | H98: =VLOOKUP(E98,$E$2818:$H$2876,4,FALSE) -> 44301
C99: EPI | D99: JUSTINA | E99: 44302 | F99: 675 | G99: Empresa 2 | H99: =VLOOKUP(E99,$E$2818:$H$2876,4,FALSE) -> 44302
C100: COMBUSTIVEL | D100: LUIS b | E100: 44303 | F100: 200 | G100: Distribuição de Lucros | H100: =VLOOKUP(E100,$E$2818:$H$2876,4,FALSE) -> 44305
C101: SAUDE | D101: PRO SALUTE - PLANO - sem falta - já pago pelos funcionarios | E101: 44304 | F101: 880.59 | G101: Empresa 2 | H101: =VLOOKUP(E101,$E$2818:$H$2876,4,FALSE) -> 44305
C102: TERCEIROS | D102: MARCIA- LIMPEZA | E102: 44305 | F102: 70 | G102: Empresa 2 | H102: =VLOOKUP(E102,$E$2818:$H$2876,4,FALSE) -> 44305
C103: SALARIOS | D103: ADRIANO - CIFERAL - PF CFE JOEL | E103: 44306 | F103: 1650 | G103: Empresa 2 | H103: =VLOOKUP(E103,$E$2818:$H$2876,4,FALSE) -> 44306
C104: SALARIOS | D104: HELIO - CIFERAL - PF CFE JOEL | E104: 44306 | F104: 1100 | G104: Empresa 2 | H104: =VLOOKUP(E104,$E$2818:$H$2876,4,FALSE) -> 44306
C105: FÉRIAS | D105: MARCELO QUIRINO (Volare) - VCTO 09/04 | E105: 44306 | F105: 2614 | G105: Empresa 2 | H105: =VLOOKUP(E105,$E$2818:$H$2876,4,FALSE) -> 44306
C106: VIAGEM | D106: JOEL - 02/03 | E106: 44306 | F106: 2720 | G106: Empresa 2 | H106: =VLOOKUP(E106,$E$2818:$H$2876,4,FALSE) -> 44306
E107: 44307 | F107: 0 | G107: Empresa 2 | H107: =VLOOKUP(E107,$E$2818:$H$2876,4,FALSE) -> 44307
C108: RESCISAO | D108: ROGER JULIO - SC - FGTS RESCISORIO | E108: 44308 | F108: 39.89 | G108: Empresa 2 | H108: =VLOOKUP(E108,$E$2818:$H$2876,4,FALSE) -> 44308
C109: COMBUSTIVEL | D109: LUIS b | E109: 44308 | F109: 200 | G109: Distribuição de Lucros | H109: =VLOOKUP(E109,$E$2818:$H$2876,4,FALSE) -> 44308
C110: COMBUSTIVEL | D110: ROGERIO | E110: 44308 | F110: 150 | G110: Distribuição de Lucros | H110: =VLOOKUP(E110,$E$2818:$H$2876,4,FALSE) -> 44308
C111: COMBUSTIVEL | D111: CLEBER | E111: 44308 | F111: 100 | G111: Empresa 2 | H111: =VLOOKUP(E111,$E$2818:$H$2876,4,FALSE) -> 44308
C112: COMBUSTIVEL | D112: FLAVIO | E112: 44308 | F112: 100 | G112: Empresa 2 | H112: =VLOOKUP(E112,$E$2818:$H$2876,4,FALSE) -> 44308
C113: TERCEIROS | D113: TRABALHOS LUAN - LT MANUTENCAO - vcto 11/12 | E113: 44308 | F113: 1000 | G113: Empresa 2 | H113: =VLOOKUP(E113,$E$2818:$H$2876,4,FALSE) -> 44308
...

Sheet Fluxo_04_21
B1: =IF(B5=1,"Domingo",IF(B5=2,"Segunda",IF(B5=3,"Terça",IF(B5=4,"Quarta",IF(B5=5,"Quinta",IF(B5=6,"Sexta",IF(B5=7,"Sábado",0))))))) -> Quinta | C1: =IF(C5=1,"Domingo",IF(C5=2,"Segunda",IF(C5=3,"Terça",IF(C5=4,"Quarta",IF(C5=5,"Quinta",IF(C5=6,"Sexta",IF(C5=7,"Sábado",0))))))) -> Segunda | D1: =IF(D5=1,"Domingo",IF(D5=2,"Segunda",IF(D5=3,"Terça",IF(D5=4,"Quarta",IF(D5=5,"Quinta",IF(D5=6,"Sexta",IF(D5=7,"Sábado",0))))))) -> Terça | E1: =IF(E5=1,"Domingo",IF(E5=2,"Segunda",IF(E5=3,"Terça",IF(E5=4,"Quarta",IF(E5=5,"Quinta",IF(E5=6,"Sexta",IF(E5=7,"Sábado",0))))))) -> Quarta | F1: =IF(F5=1,"Domingo",IF(F5=2,"Segunda",IF(F5=3,"Terça",IF(F5=4,"Quarta",IF(F5=5,"Quinta",IF(F5=6,"Sexta",IF(F5=7,"Sábado",0))))))) -> Quinta | G1: =IF(G5=1,"Domingo",IF(G5=2,"Segunda",IF(G5=3,"Terça",IF(G5=4,"Quarta",IF(G5=5,"Quinta",IF(G5=6,"Sexta",IF(G5=7,"Sábado",0))))))) -> Sexta | H1: =IF(H5=1,"Domingo",IF(H5=2,"Segunda",IF(H5=3,"Terça",IF(H5=4,"Quarta",IF(H5=5,"Quinta",IF(H5=6,"Sexta",IF(H5=7,"Sábado",0))))))) -> Segunda | I1: =IF(I5=1,"Domingo",IF(I5=2,"Segunda",IF(I5=3,"Terça",IF(I5=4,"Quarta",IF(I5=5,"Quinta",IF(I5=6,"Sexta",IF(I5=7,"Sábado",0))))))) -> Terça | ... W1: =IF(W5=1,"Domingo",IF(W5=2,"Segunda",IF(W5=3,"Terça",IF(W5=4,"Quarta",IF(W5=5,"Quinta",IF(W5=6,"Sexta",IF(W5=7,"Sábado",0))))))) -> #VALUE!
A2: Localizado no banco | B2: =B29 -> 44287 | C2: =C29 -> 44291 | D2: =D29 -> 44292 | E2: =E29 -> 44293 | F2: =F29 -> 44294 | G2: =G29 -> 44295 | H2: =H29 -> 44298 | I2: =I29 -> 44299 | ... W2: =W29 -> Total Geral
A4: SALDO INICIAL | B4: =Fluxo_03_21!X38 -> 25773.51 | C4: =B38 -> -13015.66 | D4: =C38 -> -14344.66 | E4: =D38 -> -17898.88 | F4: =E38 -> -13094.55 | G4: =F38 -> -9525.42 | H4: =G38 -> -16827.62 | I4: =H38 -> -14996.36 | J4: =I38 -> -13622.92 | ... W4: =V38 -> 5598.23
B5: =WEEKDAY(B2) -> 5 | C5: =WEEKDAY(C2) -> 2 | D5: =WEEKDAY(D2) -> 3 | E5: =WEEKDAY(E2) -> 4 | F5: =WEEKDAY(F2) -> 5 | G5: =WEEKDAY(G2) -> 6 | H5: =WEEKDAY(H2) -> 2 | I5: =WEEKDAY(I2) -> 3 | ... W5: =WEEKDAY(W2) -> #VALUE!
A6: RECEBIMENTOS (OPERAÇÃO) | B6: =SUM(B7:B26) -> 0 | C6: =SUM(C7:C26) -> 28570.87 | D6: =SUM(D7:D26) -> 29584.31 | E6: =SUM(E7:E26) -> 30164.46 | F6: =SUM(F7:F26) -> 4908.91 | G6: =SUM(G7:G26) -> 0 | H6: =SUM(H7:H26) -> 2445 | I6: =SUM(I7:I26) -> 23063.8 | ... W6: =SUM(W7:W26) -> 0
A7: MARCO | D7: 25654.3 | E7: 17700.96 | H7: =1320 -> 1320 | S7: 15847.94 | T7: 27765.45 | U7: 27381 | V7: 13417.38
A8: MARCO | C8: 20302.05 | D8: =2464-855.6 -> 1608.4
A9: VOL | J9: 12889.89 | R9: =27762.48 -> 27762.48 | T9: 3553.26 | U9: =19190 -> 19190
A10: HIDR | H10: 1125
A11: WS
A12: RUG | D12: 2321.61 | I12: 2687.88
A13: CIF
A14: MARIN | C14: 6637.12 | F14: 4908.91 | J14: 5920.64 | R14: 4853.59 | V14: 7958.87
A15: LEBRE | E15: 12463.5 | I15: =1701+3465+3774+4453.14+4840.78+2142 -> 20375.92 | S15: =4494.27+3979+840+3465+4473.18+4281.28 -> 21532.73
A16: RAND
A17: FLOR | C17: 1631.7 | S17: 5409.6
A18: ESTU | J18: 11481.02 | U18: 11587.18
A19: REN | N19: 8084 | Q19: 2000
A27: PAGAMENTOS PROGRAMADOS
A28: Soma de Valor | B28: Pagto.
A29: tipo | B29: 44287 | C29: 44291 | D29: 44292 | E29: 44293 | F29: 44294 | G29: 44295 | H29: 44298 | I29: 44299 | J29: 44300 | K29: 44301 | L29: 44302 | M29: 44305 | N29: 44306 | O29: 44307 | P29: 44308 | Q29: 44309 | R29: 44312 | S29: 44313 | T29: 44314 | U29: 44315 | V29: 44316 | W29: Total Geral
A30: PARTICULAR | B30: 2000 | C30: 3936.52 | D30: 882.17 | G30: 50 | I30: 1769.95 | J30: 100 | K30: 150 | M30: 200 | P30: 350 | R30: 2200 | U30: 7335.73 | W30: 18974.37
A31: VENT | B31: 3688.37 | G31: 227 | H31: 90 | I31: 1830 | J31: 3529.16 | K31: 5183.7 | R31: 8393.21 | S31: 13900 | T31: 708.93 | U31: 9189.9 | V31: 3402.82 | W31: 50143.09
A32: SOL | V32: 510.83 | W32: 510.83
A33: P | K33: 3594.05 | R33: 380.78 | W33: 3974.83
A34: SEM | B34: 33100.8 | C34: 25963.35 | D34: 32256.36 | E34: 25360.13 | F34: 1339.78 | G34: 7025.2 | H34: 523.74 | I34: 18090.41 | J34: 2303.47 | K34: 14499.7 | L34: 675 | M34: 950.59 | N34: 8084 | O34: 0 | P34: 1425.89 | Q34: 2000 | R34: 13227.43 | S34: 25560.03 | T34: 37195.43 | U34: 25656.19 | V34: 16707.04 | W34: 291944.54
A35: Total Geral | B35: 38789.17 | C35: 29899.87 | D35: 33138.53 | E35: 25360.13 | F35: 1339.78 | G35: 7302.2 | H35: 613.74 | I35: 21690.36 | J35: 5932.63 | K35: 23427.45 | L35: 675 | M35: 1150.59 | N35: 8084 | O35: 0 | P35: 1775.89 | Q35: 2000 | R35: 24201.42 | S35: 39460.03 | T35: 37904.36 | U35: 42181.82 | V35: 20620.69 | W35: 365547.66
A38: SALDO FINAL | B38: =B4+B6-GETPIVOTDATA("Valor",$A$28,"Pagto.",DATE(2021,4,1)) -> -13015.66 | C38: =C4+C6-GETPIVOTDATA("Valor",$A$28,"Pagto.",DATE(2021,4,5)) -> -14344.66 | D38: =D4+D6-GETPIVOTDATA("Valor",$A$28,"Pagto.",DATE(2021,4,6)) -> -17898.88 | E38: =E4+E6-GETPIVOTDATA("Valor",$A$28,"Pagto.",DATE(2021,4,7)) -> -13094.55 | F38: =F4+F6-GETPIVOTDATA("Valor",$A$28,"Pagto.",DATE(2021,4,8)) -> -9525.42 | G38: =G4+G6-GETPIVOTDATA("Valor",$A$28,"Pagto.",DATE(2021,4,9)) -> -16827.62 | H38: =H4+H6-GETPIVOTDATA("Valor",$A$28,"Pagto.",DATE(2021,4,12)) -> -14996.36 | I38: =I4+I6-GETPIVOTDATA("Valor",$A$28,"Pagto.",DATE(2021,4,13)) -> -13622.92 | J38: =J4+J6-GETPIVOTDATA("Valor",$A$28,"Pagto.",DATE(2021,4,14)) -> 10736 | K38: =K4+K6-GETPIVOTDATA("Valor",$A$28,"Pagto.",DATE(2021,4,15)) -> -12691.45 | L38: =L4+L6-GETPIVOTDATA("Valor",$A$28,"Pagto.",DATE(2021,4,16)) -> -13366.45 | M38: =M4+M6-GETPIVOTDATA("Valor",$A$28,"Pagto.",DATE(2021,4,19)) -> -14517.04 | N38: =N4+N6-GETPIVOTDATA("Valor",$A$28,"Pagto.",DATE(2021,4,20)) -> -14517.04 | O38: =O4+O6-GETPIVOTDATA("Valor",$A$28,"Pagto.",DATE(2021,4,21)) -> -14517.04 | P38: =P4+P6-GETPIVOTDATA("Valor",$A$28,"Pagto.",DATE(2021,4,22)) -> -16292.93 | Q38: =Q4+Q6-GETPIVOTDATA("Valor",$A$28,"Pagto.",DATE(2021,4,23)) -> -16292.93 | R38: =R4+R6-GETPIVOTDATA("Valor",$A$28,"Pagto.",DATE(2021,4,26)) -> -7878.28 | S38: =S4+S6-GETPIVOTDATA("Valor",$A$28,"Pagto.",DATE(2021,4,27)) -> -4548.04 | T38: =T4+T6-GETPIVOTDATA("Valor",$A$28,"Pagto.",DATE(2021,4,28)) -> -11133.69 | U38: =U4+U6-GETPIVOTDATA("Valor",$A$28,"Pagto.",DATE(2021,4,29)) -> 4842.67 | V38: =V4+V6-GETPIVOTDATA("Valor",$A$28,"Pagto.",DATE(2021,4,30)) -> 5598.23

Sheet 03_21
A1: 0 | B1: tm | C1: CodCli | D1: Nome | E1: dtvcto | F1: Valor | G1: tipo | H1: Pagto.
C2: BANCOS | D2: JUROS E DESPESAS BANCARIAS - PREVISAO | E2: 44256 | F2: =1500.49+1105+1000 -> 3605.49 | G2: Empresa 1 | H2: =VLOOKUP(E2,$E$2848:$H$2879,4,FALSE) -> 44256
C3: ACORDO | D3: BOX RAPIDO - 01/10 | E3: 44256 | F3: 444.2 | G3: Empresa 1 | H3: =VLOOKUP(E3,$E$2848:$H$2879,4,FALSE) -> 44256
C4: TERCEIROS | D4: BUZZATTI - NF NEOBUS - saldo (em dinheiro) | E4: 44256 | F4: 4000 | G4: Empresa 2 | H4: =VLOOKUP(E4,$E$2848:$H$2879,4,FALSE) -> 44256
C5: EPI | D5: ZAPA | E5: 44256 | F5: 347.6 | G5: Empresa 2 | H5: =VLOOKUP(E5,$E$2848:$H$2879,4,FALSE) -> 44256
C6: ALIMENTACAO | D6: ALIMENTAR - acordo - 02/02 - sem falta (bloqueado) | E6: 44256 | F6: 2409.61 | G6: Empresa 2 | H6: =VLOOKUP(E6,$E$2848:$H$2879,4,FALSE) -> 44256
C7: VIAGEM | D7: LUIS/GABRIEL -LIBRELATO | E7: 44256 | F7: 454.93 | G7: Empresa 2 | H7: =VLOOKUP(E7,$E$2848:$H$2879,4,FALSE) -> 44256
C8: COMBUSTIVEL | D8: REEMBOLSO LUIS b | E8: 44256 | F8: 200 | G8: Empresa 2 | H8: =VLOOKUP(E8,$E$2848:$H$2879,4,FALSE) -> 44256
C9: TERCEIROS | D9: UBER - EXAMES (KARINA) | E9: 44256 | F9: 140 | G9: Empresa 2 | H9: =VLOOKUP(E9,$E$2848:$H$2879,4,FALSE) -> 44256
C10: TERCEIROS | D10: MARCIA | E10: 44256 | F10: 70 | G10: Empresa 2 | H10: =VLOOKUP(E10,$E$2848:$H$2879,4,FALSE) -> 44256
C11: COMBUSTIVEL | D11: TEONAS - MENSAL | E11: 44256 | F11: 150 | G11: Empresa 2 | H11: =VLOOKUP(E11,$E$2848:$H$2879,4,FALSE) -> 44256
C12: COMBUSTIVEL | D12: GENILSON - MENSAL | E12: 44256 | F12: 300 | G12: Empresa 2 | H12: =VLOOKUP(E12,$E$2848:$H$2879,4,FALSE) -> 44256
C13: COMUNICACAO | D13: NET - vcto 20/02 | E13: 44256 | F13: 233.19 | G13: Empresa 2 | H13: =VLOOKUP(E13,$E$2848:$H$2879,4,FALSE) -> 44256
C14: EXPEDIENTE | D14: TONER - FINANCEIRO | E14: 44256 | F14: 47.4 | G14: Empresa 1 | H14: =VLOOKUP(E14,$E$2848:$H$2879,4,FALSE) -> 44256
... C31: RESCISAO | D31: LUAN BARCELLOS - FGTS | E31: 44259 | F31: 31.18 | G31: Empresa 2 | H31: =VLOOKUP(E31,$E$2848:$H$2879,4,FALSE) -> 44259
C32: BANCOS | D32: BLOQUEIO JUDICIAL | E32: 44260 | F32: =45454.35+15074 -> 60528.35 | G32: Empresa 2 | H32: =VLOOKUP(E32,$E$2848:$H$2879,4,FALSE) -> 44260
E33: 44261 | F33: 0 | G33: Empresa 2 | H33: =VLOOKUP(E33,$E$2848:$H$2879,4,FALSE) -> 44263
E34: 44262 | F34: 0 | G34: Empresa 2 | H34: =VLOOKUP(E34,$E$2848:$H$2879,4,FALSE) -> 44263
C35: SALARIOS | D35: PENSAO ALIMENTICIA | E35: 44263 | F35: =632.29+750.08+743.7 -> 2126.07 | G35: Empresa 2 | H35: =VLOOKUP(E35,$E$2848:$H$2879,4,FALSE) -> 44263
C36: SALARIOS | D36: MARCIA - CHEQUE Empresa 1 | E36: 44263 | F36: 1037 | G36: Empresa 2 | H36: =VLOOKUP(E36,$E$2848:$H$2879,4,FALSE) -> 44263
C37: SALARIOS | D37: RUTIELE - CHEQUE Empresa 1 | E37: 44263 | F37: 810 | G37: Empresa 2 | H37: =VLOOKUP(E37,$E$2848:$H$2879,4,FALSE) -> 44263
C38: SALARIOS | D38: ADAIR - CHEQUE Empresa 1 | E38: 44263 | F38: 299 | G38: Empresa 2 | H38: =VLOOKUP(E38,$E$2848:$H$2879,4,FALSE) -> 44263
C39: SALARIOS | D39: SANDRO - CHEQUE Empresa 1 | E39: 44263 | F39: 206 | G39: Empresa 2 | H39: =VLOOKUP(E39,$E$2848:$H$2879,4,FALSE) -> 44263
C40: EPI | D40: MAJUSEG - CHEQUE Empresa 1 | E40: 44263 | F40: 495 | G40: Empresa 2 | H40: =VLOOKUP(E40,$E$2848:$H$2879,4,FALSE) -> 44263
C41: SALARIOS | D41: VOLARE/CIFERAL - depositado pela Empresa 1 | E41: 44263 | F41: 2000 | G41: Empresa 2 | H41: =VLOOKUP(E41,$E$2848:$H$2879,4,FALSE) -> 44263
C42: PARCELAMENTO | D42: EMPRESTIMO FOLHA BB - 04/30 | E42: 44263 | F42: 2201.61 | G42: Empresa 2 | H42: =VLOOKUP(E42,$E$2848:$H$2879,4,FALSE) -> 44263
C43: COMBUSTIVEL | D43: REEBOLSO LUIS b | E43: 44264 | F43: 100 | G43: Empresa 2 | H43: =VLOOKUP(E43,$E$2848:$H$2879,4,FALSE) -> 44264
C44: SALARIOS | D44: SALARIOS - Caxias | E44: 44265 | F44: 26641 | G44: Empresa 1 | H44: =VLOOKUP(E44,$E$2848:$H$2879,4,FALSE) -> 44265
C45: EXPEDIENTE | D45: LICEIS - VCTO 08/03 | E45: 44265 | F45: 41.31 | G45: Empresa 2 | H45: =VLOOKUP(E45,$E$2848:$H$2879,4,FALSE) -> 44265
C46: TRANSPORTE | D46: VISATE SMART | E46: 44265 | F46: 93 | G46: Empresa 1 | H46: =VLOOKUP(E46,$E$2848:$H$2879,4,FALSE) -> 44265
C47: CONSUMO | D47: LUCHETTI COM DE AGUA | E47: 44265 | F47: 105 | G47: Empresa 1 | H47: =VLOOKUP(E47,$E$2848:$H$2879,4,FALSE) -> 44265
C48: COMUNICACAO | D48: CLARO - vcto 20/02/21 | E48: 44265 | F48: =1208.45+201.28+41.34 -> 1451.07 | G48: Empresa 1 | H48: =VLOOKUP(E48,$E$2848:$H$2879,4,FALSE) -> 44265
C49: EPI | D49: ZAPA - vcto 08/03 | E49: 44265 | F49: 151.26 | G49: Empresa 2 | H49: =VLOOKUP(E49,$E$2848:$H$2879,4,FALSE) -> 44265
C50: ACORDO | D50: MICROEMPA - 04/05 | E50: 44265 | F50: 280 | G50: Empresa 2 | H50: =VLOOKUP(E50,$E$2848:$H$2879,4,FALSE) -> 44265
C51: ALIMENTACAO | D51: CANTINA DELA COLINA - 03/06 - vcto 30/12 | E51: 44265 | F51: 1000 | G51: Empresa 2 | H51: =VLOOKUP(E51,$E$2848:$H$2879,4,FALSE) -> 44265
C52: RESCISAO | D52: LUAN BARCELLOS | E52: 44265 | F52: 391.72 | G52: Empresa 2 | H52: =VLOOKUP(E52,$E$2848:$H$2879,4,FALSE) -> 44265
C53: SALARIOS | D53: PAULO EDUARDO - salario + reembolso lanche | E53: 44266 | F53: =2800+37.6 -> 2837.6 | G53: Empresa 2 | H53: =VLOOKUP(E53,$E$2848:$H$2879,4,FALSE) -> 44266
C54: VIAGEM | D54: CAIXINHA JOEL | E54: 44266 | F54: 2624 | G54: Empresa 2 | H54: =VLOOKUP(E54,$E$2848:$H$2879,4,FALSE) -> 44266
C55: VIAGEM | D55: FLAVIO | E55: 44266 | F55: 334.2 | G55: Empresa 2 | H55: =VLOOKUP(E55,$E$2848:$H$2879,4,FALSE) -> 44266
C56: COMBUSTIVEL | D56: COMBUSTIVEL CLEBER | E56: 44266 | F56: 120 | G56: Empresa 2 | H56: =VLOOKUP(E56,$E$2848:$H$2879,4,FALSE) -> 44266
C57: COMBUSTIVEL | D57: COMBUSTIVEL ROGERIO | E57: 44266 | F57: 150 | G57: Empresa 2 | H57: =VLOOKUP(E57,$E$2848:$H$2879,4,FALSE) -> 44266
C58: COMBUSTIVEL | D58: COMBUSTIVEL FLAVIO | E58: 44266 | F58: 50 | G58: Empresa 2 | H58: =VLOOKUP(E58,$E$2848:$H$2879,4,FALSE) -> 44266
C59: FÉRIAS | D59: LUCINARA MARQUES | E59: 44266 | F59: 747 | G59: Empresa 2 | H59: =VLOOKUP(E59,$E$2848:$H$2879,4,FALSE) -> 44266
C60: MATERIAL | D60: SUMIG | E60: 44266 | F60: 635.36 | G60: Empresa 2 | H60: =VLOOKUP(E60,$E$2848:$H$2879,4,FALSE) -> 44266
C61: RESCISAO | D61: EVA GUTERRES - FGTS | E61: 44266 | F61: 7.05 | G61: Empresa 2 | H61: =VLOOKUP(E61,$E$2848:$H$2879,4,FALSE) -> 44266
C62: ACORDO | D62: SERGIO JOSE MARTINS - 04/05 - vcto 27/01 | E62: 44266 | F62: 1971.74 | G62: Empresa 2 | H62: =VLOOKUP(E62,$E$2848:$H$2879,4,FALSE) -> 44266
C63: EPI | D63: MAJUSEG | E63: 44266 | F63: 650.28 | G63: Empresa 2 | H63: =VLOOKUP(E63,$E$2848:$H$2879,4,FALSE) -> 44266
C64: TERCEIROS | D64: ZANOL - CEF (Ag 3112 - Cc 2747-4) - CNPJ 33.442.780/0001-89 - Projeta | E64: 44266 | F64: 400 | G64: Empresa 2 | H64: =VLOOKUP(E64,$E$2848:$H$2879,4,FALSE) -> 44266
C65: RESCISAO | D65: ANDREINA | E65: 44266 | F65: 485.13 | G65: Empresa 2 | H65: =VLOOKUP(E65,$E$2848:$H$2879,4,FALSE) -> 44266
... C100: ASSESSORIA | D100: PSP ADVOGADOS - PKS | E100: 44272 | F100: 369 | G100: Empresa 2 | H100: =VLOOKUP(E100,$E$2848:$H$2879,4,FALSE) -> 44272
C101: SALARIOS | D101: SALARIOS - Volare/Ciferal - devolver para Joel (juros) | E101: 44272 | F101: =16293+6077 -> 22370 | G101: Empresa 2 | H101: =VLOOKUP(E101,$E$2848:$H$2879,4,FALSE) -> 44272
C102: SOCIOS | D102: DEPOSITO PAULO d | E102: 44272 | F102: 1000 | G102: Empresa 2 | H102: =VLOOKUP(E102,$E$2848:$H$2879,4,FALSE) -> 44272
C103: FÉRIAS | D103: JOSE LUIS MARIA RODRIGUES - vcto 12/03 | E103: 44272 | F103: 3651 | G103: Empresa 2 | H103: =VLOOKUP(E103,$E$2848:$H$2879,4,FALSE) -> 44272
C104: ALIMENTACAO | D104: CRISTINE LANCHES | E104: 44272 | F104: 1840.72 | G104: Empresa 2 | H104: =VLOOKUP(E104,$E$2848:$H$2879,4,FALSE) -> 44272
C105: TRANSPORTE | D105: VAN - VCTO 16/03 - metade | E105: 44272 | F105: 3572 | G105: Empresa 2 | H105: =VLOOKUP(E105,$E$2848:$H$2879,4,FALSE) -> 44272
C106: SOCIOS | D106: RETIRADA LUIS b | E106: 44272 | F106: 1500 | G106: Empresa 2 | H106: =VLOOKUP(E106,$E$2848:$H$2879,4,FALSE) -> 44272
C107: CONVENIO | D107: MICROEMPA - vcto 15/03 | E107: 44272 | F107: 1277.63 | G107: SOLUTEC | H107: =VLOOKUP(E107,$E$2848:$H$2879,4,FALSE) -> 44272
C108: VIAGEM | D108: CAIXINHA JOEL | E108: 44272 | F108: 2624 | G108: Empresa 2 | H108: =VLOOKUP(E108,$E$2848:$H$2879,4,FALSE) -> 44272
C109: TERCEIROS | D109: CORREIO | E109: 44272 | F109: 24.3 | G109: Empresa 2 | H109: =VLOOKUP(E109,$E$2848:$H$2879,4,FALSE) -> 44272
C110: SALARIOS | D110: SALARIOS - Volare/Ciferal - devolver Kely em dinheiro | E110: 44273 | F110: 10000 | G110: Empresa 2 | H110: =VLOOKUP(E110,$E$2848:$H$2879,4,FALSE) -> 44273
C111: MATERIAL | D111: ACOPLANO | E111: 44273 | F111: 10914.68 | G111: Empresa 1 | H111: =VLOOKUP(E111,$E$2848:$H$2879,4,FALSE) -> 44273
C112: TERCEIROS | D112: BUZZATTI - NF NEOBUS - saldo (R$ 500,00) + 1.500,00 (salario) | E112: 44273 | F112: 2000 | G112: Empresa 1 | H112: =VLOOKUP(E112,$E$2848:$H$2879,4,FALSE) -> 44273
C113: COMUNICACAO | D113: VIVO - vcto 28/02 | E113: 44273 | F113: 388.19 | G113: PKS | H113: =VLOOKUP(E113,$E$2848:$H$2879,4,FALSE) -> 44273
C114: TERCEIROS | D114: CARTORIO | E114: 44273 | F114: 72.96 | G114: Empresa 1 | H114: =VLOOKUP(E114,$E$2848:$H$2879,4,FALSE) -> 44273
C115: INFORMATICA | D115: CORPORATIVA TI - AVISO DE CARTORIO (vcto 11/01 e 14/12) | E115: 44273 | F115: =339.83+339.33 -> 679.16 | G115: Empresa 1 | H115: =VLOOKUP(E115,$E$2848:$H$2879,4,FALSE) -> 44273
C116: TERCEIROS | D116: CHAVEIRO CASA DE PEDRA - cartao debito | E116: 44273 | F116: 82 | G116: Empresa 1 | H116: =VLOOKUP(E116,$E$2848:$H$2879,4,FALSE) -> 44273
C117: MATERIAL | D117: LF SILVEIRA | E117: 44273 | F117: 82 | G117: Empresa 2 | H117: =VLOOKUP(E117,$E$2848:$H$2879,4,FALSE) -> 44273
C118: EXPEDIENTE | D118: LICEIS | E118: 44273 | F118: 26 | G118: Empresa 2 | H118: =VLOOKUP(E118,$E$2848:$H$2879,4,FALSE) -> 44273
C119: MATERIAL | D119: KIPEL | E119: 44273 | F119: 20 | G119: Empresa 2 | H119: =VLOOKUP(E119,$E$2848:$H$2879,4,FALSE) -> 44273
C120: EPI | D120: MAJUSEG | E120: 44273 | F120: 1826.9 | G120: Empresa 2 | H120: =VLOOKUP(E120,$E$2848:$H$2879,4,FALSE) -> 44273
C121: COMBUSTIVEL | D121: UNO FLAVIO | E121: 44274 | F121: 100 | G121: Empresa 2 | H121: =VLOOKUP(E121,$E$2848:$H$2879,4,FALSE) -> 44274
C122: VIAGEM | D122: FLAVIO | E122: 44274 | F122: 350 | G122: Empresa 2 | H122: =VLOOKUP(E122,$E$2848:$H$2879,4,FALSE) -> 44274
C123: COMBUSTIVEL | D123: REEMBOLSAR LUIS b | E123: 44274 | F123: 100 | G123: Distribuição de Lucros | H123: =VLOOKUP(E123,$E$2848:$H$2879,4,FALSE) -> 44274
C124: COMBUSTIVEL | D124: REEMBOLSAR ROGERIO | E124: 44274 | F124: 150 | G124: Distribuição de Lucros | H124: =VLOOKUP(E124,$E$2848:$H$2879,4,FALSE) -> 44274
C125: EMPRESTIMO | D125: VERA KARLING - 08/17 | E125: 44274 | F125: 1750 | G125: Empresa 1 | H125: =VLOOKUP(E125,$E$2848:$H$2879,4,FALSE) -> 44274
C126: MATERIAL | D126: CHAPAS WSUL - Guilherme | E126: 44274 | F126: 11675.16 | G126: Empresa 1 | H126: =VLOOKUP(E126,$E$2848:$H$2879,4,FALSE) -> 44274
C127: ACORDO | D127: NATHAN PEREIRA - 01/04 - vcto 12/03 | E127: 44274 | F127: 1571.61 | G127: Empresa 2 | H127: =VLOOKUP(E127,$E$2848:$H$2879,4,FALSE) -> 44274
... C136: ENCARGOS | D136: INSS - somente parte funcionarios | E136: 44274 | F136: 1573.72 | G136: Empresa 1 | H136: =VLOOKUP(E136,$E$2848:$H$2879,4,FALSE) -> 44274
C137: ENCARGOS | D137: INSS | E137: 44274 | F137: =11074.61+350.32 -> 11424.93 | G137: Empresa 2 | H137: =VLOOKUP(E137,$E$2848:$H$2879,4,FALSE) -> 44274
C138: SOCIOS | D138: SEGURO STRADA LUIS - 06/07 | E138: 44274 | F138: 216.67 | G138: Distribuição de Lucros | H138: =VLOOKUP(E138,$E$2848:$H$2879,4,FALSE) -> 44274
C139: RESCISAO | D139: HELIO DE CASTRO | E139: 44274 | F139: 2049.25 | G139: Empresa 2 | H139: =VLOOKUP(E139,$E$2848:$H$2879,4,FALSE) -> 44274
C140: RESCISAO | D140: ADRIANO PEREIRA | E140: 44274 | F140: 2528.36 | G140: Empresa 2 | H140: =VLOOKUP(E140,$E$2848:$H$2879,4,FALSE) -> 44274
C141: RESCISAO | D141: FGTS RESCISORIO - HELIO e ADRIANO | E141: 44274 | F141: 265.64 | G141: Empresa 2 | H141: =VLOOKUP(E141,$E$2848:$H$2879,4,FALSE) -> 44274
C142: ASSESSORIA | D142: HOLUS | E142: 44274 | F142: 220 | G142: Empresa 1 | H142: =VLOOKUP(E142,$E$2848:$H$2879,4,FALSE) -> 44274
C143: VEICULOS | D143: MECANIA ADEMIR | E143: 44274 | F143: 553.34 | G143: Empresa 1 | H143: =VLOOKUP(E143,$E$2848:$H$2879,4,FALSE) -> 44274
C144: TERCEIROS | D144: LIMPEZA - MARCIA | E144: 44274 | F144: 70 | G144: Empresa 2 | H144: =VLOOKUP(E144,$E$2848:$H$2879,4,FALSE) -> 44274
C145: ALIMENTACAO | D145: CANTINA DELA COLINA | E145: 44274 | F145: 1000 | G145: Empresa 2 | H145: =VLOOKUP(E145,$E$2848:$H$2879,4,FALSE) -> 44274
C146: TRANSPORTE | D146: VISATE - 45 CARTOES | E146: 44274 | F146: 837 | G146: Empresa 2 | H146: =VLOOKUP(E146,$E$2848:$H$2879,4,FALSE) -> 44274
C147: TERCEIROS | D147: ROGERIO - ENGENHEIRO - NF 1452 VOLARE (R$ 10.000,00) | E147: 44274 | F147: 3500 | G147: Empresa 2 | H147: =VLOOKUP(E147,$E$2848:$H$2879,4,FALSE) -> 44274
C148: EPI | D148: JUSTINA - cheque Empresa 2 | E148: 44275 | F148: 2137 | G148: Empresa 2 | H148: =VLOOKUP(E148,$E$2848:$H$2879,4,FALSE) -> 44277
C149: TRANSPORTE | D149: VISATE - 40 CARTOES - cheque Empresa 2 | E149: 44276 | F149: 744 | G149: Empresa 2 | H149: =VLOOKUP(E149,$E$2848:$H$2879,4,FALSE) -> 44277
... C227: PARCELAMENTO | D227: CSLL - DEBITO BB | E227: 44286 | F227: 523.5 | G227: Empresa 2 | H227: =VLOOKUP(E227,$E$2848:$H$2879,4,FALSE) -> 44286
D2847: CALENDÁRIO A AJUSTAR | E2847: VCTO
A2848: RELAÇÃO DAS CONTAS DO FLUXO | D2848: DIAS CORRIDOS > | E2848: 44256 | G2848: A VERIFICAR | H2848: 44256 | I2848: >>Data de Pagto
A2849: (Preenchet até a linha 2.100) | D2849: DIAS CORRIDOS > | E2849: 44257 | G2849: ALUGUEIS DEPÓSITOS PFT/GUGELMIN - MATRIZ | H2849: 44257 | I2849: >>Data de Pagto
D2850: DIAS CORRIDOS > | E2850: 44258 | G2850: ALUGUEL EQUIPAMENTOS E MÁQUINAS | H2850: 44258 | I2850: >>Data de Pagto
D2851: DIAS CORRIDOS > | E2851: 44259 | G2851: COMBUSTÍVEIS E LUBRIFICANTES | H2851: 44259 | I2851: >>Data de Pagto
D2852: DIAS CORRIDOS > | E2852: 44260 | G2852: COMISSÕES COM VENDAS | H2852: 44260 | I2852: >>Data de Pagto
D2853: DIAS CORRIDOS > | E2853: 44261 | G2853: COMPRA DE MADEIRA | H2853: 44263 | I2853: >>Data de Pagto
D2854: DIAS CORRIDOS > | E2854: 44262 | G2854: COMPRA DE TORAS | H2854: 44263 | I2854: >>Data de Pagto
...

Sheet Fluxo_03_21
A1: 1 | B1: =IF(B5=1,"Domingo",IF(B5=2,"Segunda",IF(B5=3,"Terça",IF(B5=4,"Quarta",IF(B5=5,"Quinta",IF(B5=6,"Sexta",IF(B5=7,"Sábado",0))))))) -> Segunda | C1: =IF(C5=1,"Domingo",IF(C5=2,"Segunda",IF(C5=3,"Terça",IF(C5=4,"Quarta",IF(C5=5,"Quinta",IF(C5=6,"Sexta",IF(C5=7,"Sábado",0))))))) -> Terça | D1: =IF(D5=1,"Domingo",IF(D5=2,"Segunda",IF(D5=3,"Terça",IF(D5=4,"Quarta",IF(D5=5,"Quinta",IF(D5=6,"Sexta",IF(D5=7,"Sábado",0))))))) -> Quarta | E1: =IF(E5=1,"Domingo",IF(E5=2,"Segunda",IF(E5=3,"Terça",IF(E5=4,"Quarta",IF(E5=5,"Quinta",IF(E5=6,"Sexta",IF(E5=7,"Sábado",0))))))) -> Quinta | F1: =IF(F5=1,"Domingo",IF(F5=2,"Segunda",IF(F5=3,"Terça",IF(F5=4,"Quarta",IF(F5=5,"Quinta",IF(F5=6,"Sexta",IF(F5=7,"Sábado",0))))))) -> Sexta | G1: =IF(G5=1,"Domingo",IF(G5=2,"Segunda",IF(G5=3,"Terça",IF(G5=4,"Quarta",IF(G5=5,"Quinta",IF(G5=6,"Sexta",IF(G5=7,"Sábado",0))))))) -> Segunda | H1: =IF(H5=1,"Domingo",IF(H5=2,"Segunda",IF(H5=3,"Terça",IF(H5=4,"Quarta",IF(H5=5,"Quinta",IF(H5=6,"Sexta",IF(H5=7,"Sábado",0))))))) -> Terça | I1: =IF(I5=1,"Domingo",IF(I5=2,"Segunda",IF(I5=3,"Terça",IF(I5=4,"Quarta",IF(I5=5,"Quinta",IF(I5=6,"Sexta",IF(I5=7,"Sábado",0))))))) -> Quarta | ... X1: =IF(X5=1,"Domingo",IF(X5=2,"Segunda",IF(X5=3,"Terça",IF(X5=4,"Quarta",IF(X5=5,"Quinta",IF(X5=6,"Sexta",IF(X5=7,"Sábado",0))))))) -> 0
A2: Localizado no banco | B2: =B29 -> 44256 | C2: =C29 -> 44257 | D2: =D29 -> 44258 | E2: =E29 -> 44259 | F2: =F29 -> 44260 | G2: =G29 -> 44263 | H2: =H29 -> 44264 | I2: =I29 -> 44265 | ... X2: =X29 -> 44286
A4: SALDO INICIAL | B4: =Fluxo_02_21!U34 -> 25852.98 | C4: =B38 -> 14127.09 | D4: =C38 -> 12387.24 | E4: =D38 -> 10789.24 | F4: =E38 -> 35754.52 | G4: =F38 -> -6884.83 | H4: =G38 -> -12834.14 | I4: =H38 -> -12934.14 | J4: =I38 -> 2036.99 | ... X4: =W38 -> 53113.13
B5: =WEEKDAY(B2) -> 2 | C5: =WEEKDAY(C2) -> 3 | D5: =WEEKDAY(D2) -> 4 | E5: =WEEKDAY(E2) -> 5 | F5: =WEEKDAY(F2) -> 6 | G5: =WEEKDAY(G2) -> 2 | H5: =WEEKDAY(H2) -> 3 | I5: =WEEKDAY(I2) -> 4 | ... W5: =WEEKDAY(W2) -> 3
A6: RECEBIMENTOS (OPERAÇÃO) | B6: =SUM(B7:B26) -> 1750 | C6: =SUM(C7:C26) -> 0 | D6: =SUM(D7:D26) -> 815 | E6: =SUM(E7:E26) -> 32491.23 | F6: =SUM(F7:F26) -> 17889 | G6: =SUM(G7:G26) -> 3225.37 | H6: =SUM(H7:H26) -> 0 | I6: =SUM(I7:I26) -> 45125.49 | ... X6: =SUM(X7:X26) -> 1520
A7: MARCO | E7: =12636+11747.84+3500-837 -> 27046.84 | F7: =15074 -> 15074 | I7: 45125.49 | N7: =18467 -> 18467 | Q7: 17534.9 | W7: 50476.4
A8: MARCO | T8: =16626 -> 16626
A9: VOL | L9: =10000+9700+16032 -> 35732 | N9: =48000+6102+3167+5208.99-756.14 -> 61721.85 | O9: =16000+10000 -> 26000 | T9: 19000
A10: HIDR | R10: 8736
A11: WS | B11: 1750 | D11: 815 | F11: 2815 | T11: 30000 | X11: 1520
A12: RUG | G12: 3225.37
A13: CIF
A14: MARIN | E14: 5444.39
A15: LEBRE | K15: =5784.56 -> 5784.56 | L15: 4080 | V15: =4080+4065 -> 8145
A16: RAND
A17: FLOR | O17: 4480
A27: PAGAMENTOS PROGRAMADOS
A28: Soma de Valor | B28: Pagto.
A29: tipo | B29: 44256 | C29: 44257 | D29: 44258 | E29: 44259 | F29: 44260 | G29: 44263 | H29: 44264 | I29: 44265 | J29: 44266 | K29: 44267 | L29: 44270 | M29: 44271 | N29: 44272 | O29: 44273 | P29: 44274 | Q29: 44277 | R29: 44278 | S29: 44279 | T29: 44280 | U29: 44281 | V29: 44284 | W29: 44285 | X29: 44286 | Y29: Total Geral
A30: PARTICULAR | C30: 725 | K30: 4500 | L30: 4700 | P30: 466.67 | Q30: 645.61 | U30: 8982 | X30: 2616.95 | Y30: 22636.23
A31: VENT | B31: 5097.09 | D31: 1883 | I31: 28290.07 | K31: 195 | L31: 18880.29 | M31: 439.6 | O31: 13748.8 | P31: 20177.64 | Q31: 1973.71 | S31: 319.91 | V31: 2014.08 | W31: 1596 | X31: 7201.37 | Y31: 101816.56
A32: SOL | N32: 1277.63 | T32: 500 | Y32: 1777.63
A33: P | L33: 3594.05 | O33: 388.19 | Y33: 3982.24
A34: SEM | B34: 8378.8 | C34: 1014.85 | D34: 530 | E34: 7525.95 | F34: 60528.35 | G34: 9174.68 | H34: 100 | I34: 1864.29 | J34: 11012.36 | K34: 2491.67 | L34: 7073.59 | M34: 2100.8 | N34: 37509.22 | O34: 11954.9 | P34: 32082.77 | Q34: 6178.91 | R34: 17109.83 | S34: 1188.06 | T34: 31082.31 | U34: 7573.36 | V34: 920.95 | W34: 3029.66 | X34: 19041.3 | Y34: 279466.61
A35: Total Geral | B35: 13475.89 | C35: 1739.85 | D35: 2413 | E35: 7525.95 | F35: 60528.35 | G35: 9174.68 | H35: 100 | I35: 30154.36 | J35: 11012.36 | K35: 7186.67 | L35: 34247.93 | M35: 2540.4 | N35: 38786.85 | O35: 26091.89 | P35: 52727.08 | Q35: 8798.23 | R35: 17109.83 | S35: 1507.97 | T35: 31582.31 | U35: 16555.36 | V35: 2935.03 | W35: 4625.66 | X35: 28859.62 | Y35: 409679.27
A38: SALDO FINAL | B38: =B4+B6-GETPIVOTDATA("Valor",$A$28,"Pagto.",DATE(2021,3,1)) -> 14127.09 | C38: =C4+C6-GETPIVOTDATA("Valor",$A$28,"Pagto.",DATE(2021,3,2)) -> 12387.24 | D38: =D4+D6-GETPIVOTDATA("Valor",$A$28,"Pagto.",DATE(2021,3,3)) -> 10789.24 | E38: =E4+E6-GETPIVOTDATA("Valor",$A$28,"Pagto.",DATE(2021,3,4)) -> 35754.52 | F38: =F4+F6-GETPIVOTDATA("Valor",$A$28,"Pagto.",DATE(2021,3,5)) -> -6884.83 | G38: =G4+G6-GETPIVOTDATA("Valor",$A$28,"Pagto.",DATE(2021,3,8)) -> -12834.14 | H38: =H4+H6-GETPIVOTDATA("Valor",$A$28,"Pagto.",DATE(2021,3,9)) -> -12934.14 | I38: =I4+I6-GETPIVOTDATA("Valor",$A$28,"Pagto.",DATE(2021,3,10)) -> 2036.99 | J38: =J4+J6-GETPIVOTDATA("Valor",$A$28,"Pagto.",DATE(2021,3,11)) -> -8975.37 | K38: =K4+K6-GETPIVOTDATA("Valor",$A$28,"Pagto.",DATE(2021,3,12)) -> -10377.48 | L38: =L4+L6-GETPIVOTDATA("Valor",$A$28,"Pagto.",DATE(2021,3,15)) -> -4813.41 | M38: =M4+M6-GETPIVOTDATA("Valor",$A$28,"Pagto.",DATE(2021,3,16)) -> -7353.81 | N38: =N4+N6-GETPIVOTDATA("Valor",$A$28,"Pagto.",DATE(2021,3,17)) -> 34048.19 | O38: =O4+O6-GETPIVOTDATA("Valor",$A$28,"Pagto.",DATE(2021,3,18)) -> 38436.3 | P38: =P4+P6-GETPIVOTDATA("Valor",$A$28,"Pagto.",DATE(2021,3,19)) -> -14290.78 | Q38: =Q4+Q6-GETPIVOTDATA("Valor",$A$28,"Pagto.",DATE(2021,3,22)) -> -5554.11 | R38: =R4+R6-GETPIVOTDATA("Valor",$A$28,"Pagto.",DATE(2021,3,23)) -> -13927.94 | S38: =S4+S6-GETPIVOTDATA("Valor",$A$28,"Pagto.",DATE(2021,3,24)) -> -15435.91 | T38: =T4+T6-GETPIVOTDATA("Valor",$A$28,"Pagto.",DATE(2021,3,25)) -> 18607.78 | U38: =U4+U6-GETPIVOTDATA("Valor",$A$28,"Pagto.",DATE(2021,3,26)) -> 2052.42 | V38: =V4+V6-GETPIVOTDATA("Valor",$A$28,"Pagto.",DATE(2021,3,29)) -> 7262.39 | W38: =W4+W6-GETPIVOTDATA("Valor",$A$28,"Pagto.",DATE(2021,3,30)) -> 53113.13 | X38: =X4+X6-GETPIVOTDATA("Valor",$A$28,"Pagto.",DATE(2021,3,31)) -> 25773.51

Sheet 02_21
A1: 0 | B1: tm | C1: CodCli | D1: Nome | E1: dtvcto | F1: valor | G1: tipo | H1: Pagto.
C2: IMPOSTOS | D2: ART - BONDIOLLI/BUZZATTI | E2: 44228 | F2: 88.78 | G2: Empresa 1 | H2: =VLOOKUP(E2,$E$2803:$H$2834,4,FALSE) -> 44228
C3: BANCOS | D3: JUROS E DESPESAS BANCARIAS | E3: 44228 | F3: =2268.49+125+125+153+246+1000 -> 3917.49 | G3: Empresa 1 | H3: =VLOOKUP(E3,$E$2803:$H$2834,4,FALSE) -> 44228
C4: EPI | D4: JUSTINA | E4: 44228 | F4: 787.5 | G4: Empresa 2 | H4: =VLOOKUP(E4,$E$2803:$H$2834,4,FALSE) -> 44228
C5: TERCEIROS | D5: MARCIA - LIMPEZA - (devo 20,00) | E5: 44229 | F5: 50 | G5: Empresa 2 | H5: =VLOOKUP(E5,$E$2803:$H$2834,4,FALSE) -> 44229
C6: TRANSPORTE | D6: VISATE - 28 CARTOES | E6: 44229 | F6: 520.8 | G6: Empresa 2 | H6: =VLOOKUP(E6,$E$2803:$H$2834,4,FALSE) -> 44229
C7: ALIMENTACAO | D7: BOM TEMPERO - VCTO 25/01 | E7: 44229 | F7: 1363.85 | G7: Empresa 2 | H7: =VLOOKUP(E7,$E$2803:$H$2834,4,FALSE) -> 44229
C8: PARCELAMENTO | D8: SIMPLES - entrada | E8: 44230 | F8: 151864.5 | G8: Empresa 2 | H8: =VLOOKUP(E8,$E$2803:$H$2834,4,FALSE) -> 44230
C9: VIAGEM | D9: JOEL - 03/03 - saldo | E9: 44230 | F9: 1360 | G9: Empresa 2 | H9: =VLOOKUP(E9,$E$2803:$H$2834,4,FALSE) -> 44230
C10: SOCIOS | D10: RETIRADA PAULO d | E10: 44230 | F10: 300 | G10: Distribuição de Lucros | H10: =VLOOKUP(E10,$E$2803:$H$2834,4,FALSE) -> 44230
C11: PARCELAMENTO | D11: EMPRESTIMO FOLHA BB - 02/30 | E11: 44231 | F11: 2322.87 | G11: Empresa 2 | H11: =VLOOKUP(E11,$E$2803:$H$2834,4,FALSE) -> 44231
C12: RESCISAO | D12: ELISSANDRA TRINDADE | E12: 44231 | F12: 459.36 | G12: Empresa 2 | H12: =VLOOKUP(E12,$E$2803:$H$2834,4,FALSE) -> 44231
C13: SALARIOS | D13: SALARIOS - arquivo | E13: 44231 | F13: =44659+673 -> 45332 | G13: Empresa 2 | H13: =VLOOKUP(E13,$E$2803:$H$2834,4,FALSE) -> 44231
C14: EPI | D14: CORSUL | E14: 44232 | F14: 541.82 | G14: Empresa 2 | H14: =VLOOKUP(E14,$E$2803:$H$2834,4,FALSE) -> 44232
C15: TRANSPORTE | D15: VISATE - FUNC.FLORENSE | E15: 44232 | F15: 93 | G15: Empresa 2 | H15: =VLOOKUP(E15,$E$2803:$H$2834,4,FALSE) -> 44232
C16: COMBUSTIVEL | D16: COMBUSTIVEL: 458,00 Librelato - uno flavio + 100 uno cleber | E16: 44232 | F16: 558 | G16: Empresa 2 | H16: =VLOOKUP(E16,$E$2803:$H$2834,4,FALSE) -> 44232
C17: COMBUSTIVEL | D17: LUIS b | E17: 44232 | F17: 150 | G17: Distribuição de Lucros | H17: =VLOOKUP(E17,$E$2803:$H$2834,4,FALSE) -> 44232
C18: COMBUSTIVEL | D18: ROGERIO | E18: 44232 | F18: 100 | G18: Distribuição de Lucros | H18: =VLOOKUP(E18,$E$2803:$H$2834,4,FALSE) -> 44232
C19: TRANSPORTE | D19: UBER - EXAMES 03 FUNCIONARIOS CRICIUMA | E19: 44232 | F19: 140 | G19: Empresa 2 | H19: =VLOOKUP(E19,$E$2803:$H$2834,4,FALSE) -> 44232
C20: SOCIOS | D20: LUIS b | E20: 44232 | F20: 300 | G20: Distribuição de Lucros | H20: =VLOOKUP(E20,$E$2803:$H$2834,4,FALSE) -> 44232
C21: ACORDO | D21: ARTHUR - CIFERAL - 01/08 - vcto 18/12 - SR.PAULO/JOEL | E21: 44232 | F21: 1500 | G21: Empresa 2 | H21: =VLOOKUP(E21,$E$2803:$H$2834,4,FALSE) -> 44232
C22: ACORDO | D22: LEONARDO - CIFERAL - 01/14 - vcto 18/12 - SR.PAULO/JOEL | E22: 44232 | F22: 1500 | G22: Empresa 2 | H22: =VLOOKUP(E22,$E$2803:$H$2834,4,FALSE) -> 44232
C23: ACORDO | D23: SAMUEL - CIFERAL - 01/09 - vcto 18/12 - SR.PAULO/JOEL | E23: 44232 | F23: 1500 | G23: Empresa 2 | H23: =VLOOKUP(E23,$E$2803:$H$2834,4,FALSE) -> 44232
C24: SEGURO | D24: ROGERIO - 02/06 - ULTIMO PRAZO - SEM FALTA | E24: 44232 | F24: 678.5 | G24: Distribuição de Lucros | H24: =VLOOKUP(E24,$E$2803:$H$2834,4,FALSE) -> 44232
